{"episode": "The_Heart_Is_a_Lonely_Hunter", "scenes": [{"sceneDesc": "Storybrooke. Present. Granny's Diner. Graham throws a dart.", "tense": "Present", "location": "Storybrooke", "dialog": [{"character": "Sidney", "dialog": " Nice shot, chief. I betcha 20 bucks you can't do it again.", "dialogSplit": ["Nice", "shot", "chief", "I", "betcha", "20", "bucks", "you", "can't", "do", "it", "again"]}, {"character": "Sheriff Graham", "dialog": " Next round's on him.", "dialogSplit": ["Next", "round's", "on", "him"]}, {"character": "Ruby", "dialog": "Emma, what can I get you?", "dialogSplit": ["Emma", "what", "can", "I", "get", "you"]}, {"character": "Emma", "dialog": " Nothing.  What the hell? You could have hit me.", "dialogSplit": ["Nothing", "What", "the", "hell", "You", "could", "have", "hit", "me"]}, {"character": "Sheriff Graham", "dialog": " I never miss. You've been avoiding me... since last night when you saw me ...", "dialogSplit": ["I", "never", "miss", "You've", "been", "avoiding", "me", "since", "last", "night", "when", "you", "saw", "me"]}, {"character": "Emma", "dialog": " Leaving the mayor's? And, yes, that is a euphemism. I'm not avoiding you, Graham. I just have no interest in having this conversation. It's your life, and I really don't care.", "dialogSplit": ["Leaving", "the", "mayor's", "And", "yes", "that", "is", "a", "euphemism", "I'm", "not", "avoiding", "you", "Graham", "I", "just", "have", "no", "interest", "in", "having", "this", "conversation", "It's", "your", "life", "and", "I", "really", "don't", "care"]}, {"character": "Sheriff Graham", "dialog": " If you don't care, then why are you so upset?", "dialogSplit": ["If", "you", "don't", "care", "then", "why", "are", "you", "so", "upset"]}, {"character": "Emma", "dialog": " I'm not upset!", "dialogSplit": ["I'm", "not", "upset"]}, {"character": "Sheriff Graham", "dialog": " If that were true, you'd be at the bar with me having a drink and not running away. Can we please talk about this? I need you to understand.", "dialogSplit": ["If", "that", "were", "true", "you'd", "be", "at", "the", "bar", "with", "me", "having", "a", "drink", "and", "not", "running", "away", "Can", "we", "please", "talk", "about", "this", "I", "need", "you", "to", "understand"]}, {"character": "Emma", "dialog": " Why?", "dialogSplit": ["Why"]}, {"character": "Sheriff Graham", "dialog": " I don't know. Uh, maybe so I can understand.", "dialogSplit": ["I", "don't", "know", "Uh", "maybe", "so", "I", "can", "understand"]}, {"character": "Emma", "dialog": " You need analysis, go talk to Archie.", "dialogSplit": ["You", "need", "analysis", "go", "talk", "to", "Archie"]}, {"character": "Sheriff Graham", "dialog": " I wanna talk to you.", "dialogSplit": ["I", "wanna", "talk", "to", "you"]}, {"character": "Emma", "dialog": " Well, your bad judgment is your problem, not mine.", "dialogSplit": ["Well", "your", "bad", "judgment", "is", "your", "problem", "not", "mine"]}, {"character": "Sheriff Graham", "dialog": " You don't know what it's like with her. I don't feel anything. Can you understand that?", "dialogSplit": ["You", "don't", "know", "what", "it's", "like", "with", "her", "I", "don't", "feel", "anything", "Can", "you", "understand", "that"]}, {"character": "Emma", "dialog": " A bad relationship? Yeah. I understand a bad relationship. I just don't wanna talk about yours.", "dialogSplit": ["A", "bad", "relationship", "Yeah", "I", "understand", "a", "bad", "relationship", "I", "just", "don't", "wanna", "talk", "about", "yours"]}, {"character": "Sheriff Graham", "dialog": " Look, I know you and Regina have your own issues, and I should've told you about that before you took the job.", "dialogSplit": ["Look", "I", "know", "you", "and", "Regina", "have", "your", "own", "issues", "and", "I", "should've", "told", "you", "about", "that", "before", "you", "took", "the", "job"]}, {"character": "Emma", "dialog": " Yeah, why the secrecy? We're all adults. You can do whatever you want.", "dialogSplit": ["Yeah", "why", "the", "secrecy", "We're", "all", "adults", "You", "can", "do", "whatever", "you", "want"]}, {"character": "Sheriff Graham", "dialog": " 'Cause I-I didn't want you to look at me the way you are now.", "dialogSplit": ["Cause", "I", "I", "didn't", "want", "you", "to", "look", "at", "me", "the", "way", "you", "are", "now"]}, {"character": "Emma", "dialog": " Why do you care how I look at you?", "dialogSplit": ["Why", "do", "you", "care", "how", "I", "look", "at", "you"]}, {"character": "Sheriff Graham", "dialog": " Because...", "dialogSplit": ["Because"]}]}, {"sceneDesc": "Storybrooke. Present. Granny's Diner. Graham throws a dart.", "tense": "Present", "location": "Storybrooke", "dialog": [{"character": "", "dialog": "Blurred impressions of a forest. As the scene becomes clear a wolf with eyes of different colors - one red, the other one blue, appears briefly.", "dialogSplit": ["Blurred", "impressions", "of", "a", "forest", "As", "the", "scene", "becomes", "clear", "a", "wolf", "with", "eyes", "of", "different", "colors", "one", "red", "the", "other", "one", "blue", "appears", "briefly"]}]}, {"sceneDesc": "Storybrooke. Present. Granny's Diner. Graham throws a dart.", "tense": "Present", "location": "Storybrooke", "dialog": [{"character": "Emma", "dialog": " What?  What the hell was that?", "dialogSplit": ["What", "What", "the", "hell", "was", "that"]}, {"character": "Sheriff Graham", "dialog": " Did you see that?", "dialogSplit": ["Did", "you", "see", "that"]}, {"character": "Emma", "dialog": " How much have you been drinking? That was way over the line.", "dialogSplit": ["How", "much", "have", "you", "been", "drinking", "That", "was", "way", "over", "the", "line"]}, {"character": "Sheriff Graham", "dialog": " I'm sorry. I just...?", "dialogSplit": ["I'm", "sorry", "I", "just"]}, {"character": "Emma", "dialog": " What? You what?", "dialogSplit": ["What", "You", "what"]}, {"character": "Sheriff Graham", "dialog": " I need to feel something.", "dialogSplit": ["I", "need", "to", "feel", "something"]}, {"character": "Emma", "dialog": " Listen to me, Graham. You are drunk and full of regret. I get it. But whatever it is you are looking to feel, I can tell you one thing.You're not getting it with me.", "dialogSplit": ["Listen", "to", "me", "Graham", "You", "are", "drunk", "and", "full", "of", "regret", "I", "get", "it", "But", "whatever", "it", "is", "you", "are", "looking", "to", "feel", "I", "can", "tell", "you", "one", "thing", "You're", "not", "getting", "it", "with", "me"]}]}, {"sceneDesc": "Storybrooke. Present. Sheriff Graham standing in front of the Mills House. Sheriff Graham knocks on the door.", "tense": "Present", "location": "Storybrooke", "dialog": [{"character": "Regina", "dialog": " Graham.", "dialogSplit": ["Graham"]}, {"character": "Sheriff Graham", "dialog": " Is Henry asleep?", "dialogSplit": ["Is", "Henry", "asleep"]}, {"character": "Regina", "dialog": " Yes. Why? ", "dialogSplit": ["Yes", "Why"]}]}, {"sceneDesc": "The Enchanted Forest. Past. Evil Queen's palace. Snow White places a white rose on her father's coffin. The Evil Queen watches her.", "tense": "Past", "location": "The Enchanted Forest", "dialog": [{"character": "Snow White", "dialog": " Goodbye, father.", "dialogSplit": ["Goodbye", "father"]}, {"character": "Evil Queen", "dialog": " I'm so sorry, Snow.", "dialogSplit": ["I'm", "so", "sorry", "Snow"]}, {"character": "Snow White", "dialog": " I loved him so much.", "dialogSplit": ["I", "loved", "him", "so", "much"]}, {"character": "Evil Queen", "dialog": " So did I do. So did I. The loss I feel for my husband must be nothing compared to the loss you feel for your father.  If there is anything I can do, please let me know. I may only be your mother trough marriage, but I'm here for you dear. Truly and forever.", "dialogSplit": ["So", "did", "I", "do", "So", "did", "I", "The", "loss", "I", "feel", "for", "my", "husband", "must", "be", "nothing", "compared", "to", "the", "loss", "you", "feel", "for", "your", "father", "If", "there", "is", "anything", "I", "can", "do", "please", "let", "me", "know", "I", "may", "only", "be", "your", "mother", "trough", "marriage", "but", "I'm", "here", "for", "you", "dear", "Truly", "and", "forever"]}]}, {"sceneDesc": "The Enchanted Forest. Past. Dark Palace. The Evil Queen's chamber.", "tense": "Past", "location": "The Enchanted Forest", "dialog": [{"character": "Magic Mirror", "dialog": " Congratulations. Your revenge is almost complete.", "dialogSplit": ["Congratulations", "Your", "revenge", "is", "almost", "complete"]}, {"character": "Evil Queen", "dialog": " One down. One to go.", "dialogSplit": ["One", "down", "One", "to", "go"]}, {"character": "Magic Mirror", "dialog": " She has no idea, does she?", "dialogSplit": ["She", "has", "no", "idea", "does", "she"]}, {"character": "Evil Queen", "dialog": " That I'm responsible for his passing? She sought comfort with me. Sickening. I could have ended her miserable existence right there. Believe me, it was tempting.", "dialogSplit": ["That", "I'm", "responsible", "for", "his", "passing", "She", "sought", "comfort", "with", "me", "Sickening", "I", "could", "have", "ended", "her", "miserable", "existence", "right", "there", "Believe", "me", "it", "was", "tempting"]}, {"character": "Magic Mirror", "dialog": " It would have sated your soul.", "dialogSplit": ["It", "would", "have", "sated", "your", "soul"]}, {"character": "Evil Queen", "dialog": " The kingdom is still loyal to her. They would turn on me. They don't know the wretchedness inside of her as I do. They don't know what she did to me. We must be delicate in this next phase. Her demise must be handled with care.", "dialogSplit": ["The", "kingdom", "is", "still", "loyal", "to", "her", "They", "would", "turn", "on", "me", "They", "don't", "know", "the", "wretchedness", "inside", "of", "her", "as", "I", "do", "They", "don't", "know", "what", "she", "did", "to", "me", "We", "must", "be", "delicate", "in", "this", "next", "phase", "Her", "demise", "must", "be", "handled", "with", "care"]}, {"character": "Magic Mirror", "dialog": " Perhaps one of your knights, your Majesty.", "dialogSplit": ["Perhaps", "one", "of", "your", "knights", "your", "Majesty"]}, {"character": "Evil Queen", "dialog": " No. I need someone adept at murder. Bereft of mercy.", "dialogSplit": ["No", "I", "need", "someone", "adept", "at", "murder", "Bereft", "of", "mercy"]}, {"character": "Magic Mirror", "dialog": " Someone with no heart.", "dialogSplit": ["Someone", "with", "no", "heart"]}, {"character": "Evil Queen", "dialog": " Now you understand.", "dialogSplit": ["Now", "you", "understand"]}, {"character": "Magic Mirror", "dialog": " Well, in that case you need a huntsman.", "dialogSplit": ["Well", "in", "that", "case", "you", "need", "a", "huntsman"]}]}, {"sceneDesc": "The Enchanted Forest. Past. Somewhere in a forest. The Huntsman kills a stag.", "tense": "Past", "location": "The Enchanted Forest", "dialog": [{"character": "Huntsman", "dialog": " You have died so that I may live. Forgive me. Your sacrifice is honorable. Thank you. . Don't worry boy, you won't go hungry tonight.", "dialogSplit": ["You", "have", "died", "so", "that", "I", "may", "live", "Forgive", "me", "Your", "sacrifice", "is", "honorable", "Thank", "you", "Don't", "worry", "boy", "you", "won't", "go", "hungry", "tonight"]}]}, {"sceneDesc": "Storybrooke. Present. Mills House. Sheriff Graham wakes up soaked with sweat.", "tense": "Present", "location": "Storybrooke", "dialog": [{"character": "Regina", "dialog": " What is it?", "dialogSplit": ["What", "is", "it"]}, {"character": "Sheriff Graham", "dialog": " I had a most intense dream. I was in the woods hunting and I killed a deer. There was a wolf.", "dialogSplit": ["I", "had", "a", "most", "intense", "dream", "I", "was", "in", "the", "woods", "hunting", "and", "I", "killed", "a", "deer", "There", "was", "a", "wolf"]}, {"character": "Regina", "dialog": " A wolf?", "dialogSplit": ["A", "wolf"]}, {"character": "Sheriff Graham", "dialog": " Its eyes. One was blood-red and the other one was black as night. The funny thing is, I think I've seen the wolf before.", "dialogSplit": ["Its", "eyes", "One", "was", "blood", "red", "and", "the", "other", "one", "was", "black", "as", "night", "The", "funny", "thing", "is", "I", "think", "I've", "seen", "the", "wolf", "before"]}, {"character": "Regina", "dialog": " Come back to sleep, Graham. It was only a dream.", "dialogSplit": ["Come", "back", "to", "sleep", "Graham", "It", "was", "only", "a", "dream"]}, {"character": "Sheriff Graham", "dialog": " It didn't feel like a dream. It felt like a memory. .", "dialogSplit": ["It", "didn't", "feel", "like", "a", "dream", "It", "felt", "like", "a", "memory"]}, {"character": "Regina", "dialog": " Graham?", "dialogSplit": ["Graham"]}, {"character": "Sheriff Graham", "dialog": " I need some air. I need to think.", "dialogSplit": ["I", "need", "some", "air", "I", "need", "to", "think"]}, {"character": "Regina", "dialog": " Graham, please. Come back to bed.", "dialogSplit": ["Graham", "please", "Come", "back", "to", "bed"]}, {"character": "Sheriff Graham", "dialog": " I left my car at Granny's, anyway. I need to go and get it. Clear my head. ", "dialogSplit": ["I", "left", "my", "car", "at", "Granny's", "anyway", "I", "need", "to", "go", "and", "get", "it", "Clear", "my", "head"]}, {"character": "Regina", "dialog": " Graham. Listen. It's late. You're tired, probably still drunk. Don't leave.", "dialogSplit": ["Graham", "Listen", "It's", "late", "You're", "tired", "probably", "still", "drunk", "Don't", "leave"]}, {"character": "Sheriff Graham", "dialog": " Since when do you want me to stay anyway?", "dialogSplit": ["Since", "when", "do", "you", "want", "me", "to", "stay", "anyway"]}, {"character": "Regina", "dialog": " You're not well.", "dialogSplit": ["You're", "not", "well"]}, {"character": "Sheriff Graham", "dialog": " I'm fine. ", "dialogSplit": ["I'm", "fine"]}]}, {"sceneDesc": "Storybrooke. Present. The Blanchard loft.", "tense": "Present", "location": "Storybrooke", "dialog": [{"character": "Emma", "dialog": " Really? ", "dialogSplit": ["Really"]}, {"character": "Mary Margaret", "dialog": " Oh. Hey. Wait, what are you doing?", "dialogSplit": ["Oh", "Hey", "Wait", "what", "are", "you", "doing"]}, {"character": "Emma", "dialog": " If Graham thinks flowers will work on me -", "dialogSplit": ["If", "Graham", "thinks", "flowers", "will", "work", "on", "me"]}, {"character": "Mary Margaret", "dialog": " No, those were mine.", "dialogSplit": ["No", "those", "were", "mine"]}, {"character": "Emma", "dialog": " Oh. From David?", "dialogSplit": ["Oh", "From", "David"]}, {"character": "Mary Margaret", "dialog": " No. Dr. Whale.", "dialogSplit": ["No", "Dr", "Whale"]}, {"character": "Emma", "dialog": " Why would Dr. Whale -  Are you serious?", "dialogSplit": ["Why", "would", "Dr", "Whale", "Are", "you", "serious"]}, {"character": "Mary Margaret", "dialog": " I know, it's a disaster.", "dialogSplit": ["I", "know", "it's", "a", "disaster"]}, {"character": "Emma", "dialog": " No. That's amazing. You're getting over David.", "dialogSplit": ["No", "That's", "amazing", "You're", "getting", "over", "David"]}, {"character": "Mary Margaret", "dialog": " First of all, there's nothing to get over. And second of all: just one-night-stand.", "dialogSplit": ["First", "of", "all", "there's", "nothing", "to", "get", "over", "And", "second", "of", "all", "just", "one", "night", "stand"]}, {"character": "Emma", "dialog": " Not according to those flowers.", "dialogSplit": ["Not", "according", "to", "those", "flowers"]}, {"character": "Mary Margaret", "dialog": " Yeah, maybe I shouldn't have called him.", "dialogSplit": ["Yeah", "maybe", "I", "shouldn't", "have", "called", "him"]}, {"character": "Emma", "dialog": " Oh my God. You called him? That's definitely not a one-night stand.", "dialogSplit": ["Oh", "my", "God", "You", "called", "him", "That's", "definitely", "not", "a", "one", "night", "stand"]}, {"character": "Mary Margaret", "dialog": " O-Okay, I'm still learning. I- I never had one before. I felt guilty.", "dialogSplit": ["O", "Okay", "I'm", "still", "learning", "I", "I", "never", "had", "one", "before", "I", "felt", "guilty"]}, {"character": "Emma", "dialog": " Why? There's nothing wrong with what you did. Trust me. One nighters is as far as I ever go.", "dialogSplit": ["Why", "There's", "nothing", "wrong", "with", "what", "you", "did", "Trust", "me", "One", "nighters", "is", "as", "far", "as", "I", "ever", "go"]}, {"character": "Mary Margaret", "dialog": " That's because you're-", "dialogSplit": ["That's", "because", "you're"]}, {"character": "Emma", "dialog": " Because I'm what?", "dialogSplit": ["Because", "I'm", "what"]}, {"character": "Mary Margaret", "dialog": " Never mind.", "dialogSplit": ["Never", "mind"]}, {"character": "Emma", "dialog": " Yeah. Tell me. What do I do?", "dialogSplit": ["Yeah", "Tell", "me", "What", "do", "I", "do"]}, {"character": "Mary Margaret", "dialog": " You're just protecting yourself. With that wall you put up.", "dialogSplit": ["You're", "just", "protecting", "yourself", "With", "that", "wall", "you", "put", "up"]}, {"character": "Emma", "dialog": " Just because I don't get emotional with a man.", "dialogSplit": ["Just", "because", "I", "don't", "get", "emotional", "with", "a", "man"]}, {"character": "Mary Margaret", "dialog": " You don't get emotional with a man? The floral abuse tells a different story.", "dialogSplit": ["You", "don't", "get", "emotional", "with", "a", "man", "The", "floral", "abuse", "tells", "a", "different", "story"]}, {"character": "Emma", "dialog": " What story is that?", "dialogSplit": ["What", "story", "is", "that"]}, {"character": "Mary Margaret", "dialog": " The one that's obvious to everyone - except apparently you. That you have feelings for Graham.", "dialogSplit": ["The", "one", "that's", "obvious", "to", "everyone", "except", "apparently", "you", "That", "you", "have", "feelings", "for", "Graham"]}, {"character": "Emma", "dialog": " Come on.", "dialogSplit": ["Come", "on"]}, {"character": "Mary Margaret", "dialog": " There's a wall.", "dialogSplit": ["There's", "a", "wall"]}, {"character": "Emma", "dialog": " That's not a wall. ", "dialogSplit": ["That's", "not", "a", "wall"]}, {"character": "Mary Margaret", "dialog": " Really?", "dialogSplit": ["Really"]}, {"character": "Emma: ", "dialog": "There's nothing wrong with being cautious.", "dialogSplit": ["There's", "nothing", "wrong", "with", "being", "cautious"]}, {"character": "Mary Margaret", "dialog": " Oh, true. True. But, Emma. That wall of yours, it may keep out pain. But it also may keep out love. ", "dialogSplit": ["Oh", "true", "True", "But", "Emma", "That", "wall", "of", "yours", "it", "may", "keep", "out", "pain", "But", "it", "also", "may", "keep", "out", "love"]}]}, {"sceneDesc": "Storybrooke. Present. In the woods. Sheriff Graham follows the wolf he noticed earlier. A distant howl of a wolf can be heard. Then there is a sound of a shovel digging. Mr. Gold appears.", "tense": "Present", "location": "Storybrooke", "dialog": [{"character": "Mr. Gold", "dialog": " Good morning, Sheriff. Sorry if I startled you.", "dialogSplit": ["Good", "morning", "Sheriff", "Sorry", "if", "I", "startled", "you"]}, {"character": "Sheriff Graham", "dialog": " Right. Sorry, I, I thought you were a wolf.", "dialogSplit": ["Right", "Sorry", "I", "I", "thought", "you", "were", "a", "wolf"]}, {"character": "Mr. Gold", "dialog": " Did I forget to shave?", "dialogSplit": ["Did", "I", "forget", "to", "shave"]}, {"character": "Sheriff Graham", "dialog": " What are you doing out here so early?", "dialogSplit": ["What", "are", "you", "doing", "out", "here", "so", "early"]}, {"character": "Mr. Gold", "dialog": " A sport of gardening. Yourself?", "dialogSplit": ["A", "sport", "of", "gardening", "Yourself"]}, {"character": "Sheriff Graham", "dialog": " I was looking for...", "dialogSplit": ["I", "was", "looking", "for"]}, {"character": "Mr. Gold", "dialog": " A wolf. Yeah, I think I've been able to catch on. You know, to the best of my knowledge there are no wolves in Storybrooke. Not the literal kind anyway. Why are you looking?", "dialogSplit": ["A", "wolf", "Yeah", "I", "think", "I've", "been", "able", "to", "catch", "on", "You", "know", "to", "the", "best", "of", "my", "knowledge", "there", "are", "no", "wolves", "in", "Storybrooke", "Not", "the", "literal", "kind", "anyway", "Why", "are", "you", "looking"]}, {"character": "Sheriff Graham: ", "dialog": "You'll think I'm crazy.", "dialogSplit": ["You'll", "think", "I'm", "crazy"]}, {"character": "Mr. Gold", "dialog": " Try me.", "dialogSplit": ["Try", "me"]}, {"character": "Sheriff Graham", "dialog": " I saw one in my dreams and then I saw one for real. Just a few hours ago. Did you- Did you see anything unusual right there?", "dialogSplit": ["I", "saw", "one", "in", "my", "dreams", "and", "then", "I", "saw", "one", "for", "real", "Just", "a", "few", "hours", "ago", "Did", "you", "Did", "you", "see", "anything", "unusual", "right", "there"]}, {"character": "Mr. Gold", "dialog": " I'm afraid not. I do wish I could be more helpful.  You know, Sheriff, they say that dreams  dreams are memories  memories of another life.", "dialogSplit": ["I'm", "afraid", "not", "I", "do", "wish", "I", "could", "be", "more", "helpful", "You", "know", "Sheriff", "they", "say", "that", "dreams", "dreams", "are", "memories", "memories", "of", "another", "life"]}, {"character": "Sheriff Graham", "dialog": " W- What do you believe?", "dialogSplit": ["W", "What", "do", "you", "believe"]}, {"character": "Mr. Gold", "dialog": " I never rule out anything. Good luck, Sheriff. I do hope you'll find what you're looking for.", "dialogSplit": ["I", "never", "rule", "out", "anything", "Good", "luck", "Sheriff", "I", "do", "hope", "you'll", "find", "what", "you're", "looking", "for"]}]}, {"sceneDesc": "The Enchanted Forest. Past. The Huntsman and the wolf who accompanies him are briefly seen walking in the woods. The scene is cut to a tavern. The Huntsman and his wolf enter the scene. A drink is placed in front of the Huntsman. The Huntsman throws a chunk of meat down to the wolf.", "tense": "Past", "location": "The Enchanted Forest", "dialog": [{"character": "Man 1", "dialog": " They are letting animals in here now?", "dialogSplit": ["They", "are", "letting", "animals", "in", "here", "now"]}, {"character": "Man 2", "dialog": " This isn't a slaughterhouse.", "dialogSplit": ["This", "isn't", "a", "slaughterhouse"]}, {"character": "Man 3", "dialog": " Forget it. He might as well be one, too. I heard he was raised by 'em.", "dialogSplit": ["Forget", "it", "He", "might", "as", "well", "be", "one", "too", "I", "heard", "he", "was", "raised", "by", "em"]}, {"character": "Man 4", "dialog": " He does smell like 'em.", "dialogSplit": ["He", "does", "smell", "like", "em"]}, {"character": "Man 5", "dialog": " Pathetic. I've heard he cries over his kills. You believe that?", "dialogSplit": ["Pathetic", "I've", "heard", "he", "cries", "over", "his", "kills", "You", "believe", "that"]}, {"character": "Man 2", "dialog": " Tell me, Huntsman: What kind of a man cries over an animal?", "dialogSplit": ["Tell", "me", "Huntsman", "What", "kind", "of", "a", "man", "cries", "over", "an", "animal"]}, {"character": "Huntsman", "dialog": " An honorable one.", "dialogSplit": ["An", "honorable", "one"]}, {"character": "Man 2: ", "dialog": "What do you know about honor?", "dialogSplit": ["What", "do", "you", "know", "about", "honor"]}, {"character": "The Huntsman", "dialog": " I have it. They have it. You don't.", "dialogSplit": ["I", "have", "it", "They", "have", "it", "You", "don't"]}, {"character": "Man 2", "dialog": " Animals have it?", "dialogSplit": ["Animals", "have", "it"]}, {"character": "The Huntsman", "dialog": " They are pure of heart. Not selfish and self-serving like people. .", "dialogSplit": ["They", "are", "pure", "of", "heart", "Not", "selfish", "and", "self", "serving", "like", "people"]}, {"character": "Man 2", "dialog": " Tell him to stop threatening me. Because you know, what I do to pets that threaten me? I hang them on my wall. ", "dialogSplit": ["Tell", "him", "to", "stop", "threatening", "me", "Because", "you", "know", "what", "I", "do", "to", "pets", "that", "threaten", "me", "I", "hang", "them", "on", "my", "wall"]}, {"character": "The Huntsman", "dialog": " He is not a pet.", "dialogSplit": ["He", "is", "not", "a", "pet"]}]}, {"sceneDesc": "The Enchanted Forest. Past. Dark Palace. The Evil Queen watches the scene in the tavern through a mirror.", "tense": "Past", "location": "The Enchanted Forest", "dialog": [{"character": "Evil Queen", "dialog": " He's perfect. Bring him to me. ", "dialogSplit": ["He's", "perfect", "Bring", "him", "to", "me"]}]}, {"sceneDesc": "Storybrooke. Present. In the woods. Sheriff Graham still tries to track down the wolf. Distant howling of a wolf can be heard again. Sheriff Graham catches a glimpse of the wolf's fur. The wolf stands still for a moment and Sheriff Graham is able to face him.", "tense": "Present", "location": "Storybrooke", "dialog": [{"character": "Sheriff Graham", "dialog": " What do you want?  HEY! ", "dialogSplit": ["What", "do", "you", "want", "HEY"]}]}, {"sceneDesc": "Storybrooke Elementary School. School bell rings. Sheriff Graham enters Mary Margaret's class.", "tense": null, "location": "Storybrooke", "dialog": [{"character": "Sheriff Graham", "dialog": " Mary Margaret, can I talk to you?", "dialogSplit": ["Mary", "Margaret", "can", "I", "talk", "to", "you"]}, {"character": "Mary Margaret", "dialog": " Graham, what's the matter? Are you okay?", "dialogSplit": ["Graham", "what's", "the", "matter", "Are", "you", "okay"]}, {"character": "Sheriff Graham: ", "dialog": "I think we- I think we know each other.", "dialogSplit": ["I", "think", "we", "I", "think", "we", "know", "each", "other"]}, {"character": "Mary Margaret", "dialog": " Of course we do.", "dialogSplit": ["Of", "course", "we", "do"]}, {"character": "Sheriff Graham", "dialog": " No, no, no. Not from here. Not from Storybrooke.", "dialogSplit": ["No", "no", "no", "Not", "from", "here", "Not", "from", "Storybrooke"]}, {"character": "Mary Margaret", "dialog": " From where then?", "dialogSplit": ["From", "where", "then"]}, {"character": "Sheriff Graham", "dialog": " Another life.", "dialogSplit": ["Another", "life"]}]}, {"sceneDesc": "The Enchanted Forest. Past. Dark Palace. The Huntsman enters the Evil Queen's chambers.", "tense": "Past", "location": "The Enchanted Forest", "dialog": [{"character": "Evil Queen", "dialog": " Do you have a name? Or shall I just call you the Huntsman?  You're a tortured one, aren't you, Huntsman? Is this because your parents abandoned you to the wolves?", "dialogSplit": ["Do", "you", "have", "a", "name", "Or", "shall", "I", "just", "call", "you", "the", "Huntsman", "You're", "a", "tortured", "one", "aren't", "you", "Huntsman", "Is", "this", "because", "your", "parents", "abandoned", "you", "to", "the", "wolves"]}, {"character": "Huntsman", "dialog": " Those weren't my parents. All they did was give birth to me. The wolves are my family.", "dialogSplit": ["Those", "weren't", "my", "parents", "All", "they", "did", "was", "give", "birth", "to", "me", "The", "wolves", "are", "my", "family"]}, {"character": "Evil Queen", "dialog": " Wolves, indeed. I always felt there were two kinds of people. Wolves and sheep. Those who kill and those who get killed. And you, Huntsman, you are most certainly a wolf.", "dialogSplit": ["Wolves", "indeed", "I", "always", "felt", "there", "were", "two", "kinds", "of", "people", "Wolves", "and", "sheep", "Those", "who", "kill", "and", "those", "who", "get", "killed", "And", "you", "Huntsman", "you", "are", "most", "certainly", "a", "wolf"]}, {"character": "Huntsman", "dialog": " Why am I here?", "dialogSplit": ["Why", "am", "I", "here"]}, {"character": "Evil Queen", "dialog": " I'd like you to kill someone for me. Can you do that?", "dialogSplit": ["I'd", "like", "you", "to", "kill", "someone", "for", "me", "Can", "you", "do", "that"]}, {"character": "Huntsman", "dialog": " I kill for me. Why would I do anything for you?", "dialogSplit": ["I", "kill", "for", "me", "Why", "would", "I", "do", "anything", "for", "you"]}, {"character": "Evil Queen", "dialog": " Because I have so much to offer. A place at my court. You'll become my official huntsman.", "dialogSplit": ["Because", "I", "have", "so", "much", "to", "offer", "A", "place", "at", "my", "court", "You'll", "become", "my", "official", "huntsman"]}, {"character": "Huntsman", "dialog": " I'm not interested in being a pet. This place is a cage.", "dialogSplit": ["I'm", "not", "interested", "in", "being", "a", "pet", "This", "place", "is", "a", "cage"]}, {"character": "Evil Queen", "dialog": " You'd be awash in luxury. Wanting for nothing.", "dialogSplit": ["You'd", "be", "awash", "in", "luxury", "Wanting", "for", "nothing"]}, {"character": "Huntsman", "dialog": " You've got an army at your disposal. What do you need of me?", "dialogSplit": ["You've", "got", "an", "army", "at", "your", "disposal", "What", "do", "you", "need", "of", "me"]}, {"character": "Evil Queen", "dialog": " My prey is beloved by all the kingdom. I need someone who won't be blinded by that. Someone without compassion. Someone who'll have no qualms carving a heart out and bringing it back for my collection.", "dialogSplit": ["My", "prey", "is", "beloved", "by", "all", "the", "kingdom", "I", "need", "someone", "who", "won't", "be", "blinded", "by", "that", "Someone", "without", "compassion", "Someone", "who'll", "have", "no", "qualms", "carving", "a", "heart", "out", "and", "bringing", "it", "back", "for", "my", "collection"]}, {"character": "Huntsman", "dialog": " That's me.", "dialogSplit": ["That's", "me"]}, {"character": "Evil Queen", "dialog": " As I suspected. Now, tell me: What will it take? What do you want? There must be something.", "dialogSplit": ["As", "I", "suspected", "Now", "tell", "me", "What", "will", "it", "take", "What", "do", "you", "want", "There", "must", "be", "something"]}, {"character": "Huntsman", "dialog": " Outlaw the hunting of wolves. They are to be left alone. They are to be protected.", "dialogSplit": ["Outlaw", "the", "hunting", "of", "wolves", "They", "are", "to", "be", "left", "alone", "They", "are", "to", "be", "protected"]}, {"character": "Evil Queen", "dialog": " Simple enough.", "dialogSplit": ["Simple", "enough"]}, {"character": "Huntsman", "dialog": " So, who do you want me to kill?", "dialogSplit": ["So", "who", "do", "you", "want", "me", "to", "kill"]}]}, {"sceneDesc": "Storybrooke. Present. Storybrooke Elementary School. Mary Margaret's classroom.", "tense": "Present", "location": "Storybrooke", "dialog": [{"character": "Sheriff Graham", "dialog": " Mary Margaret, how long have we known each other?", "dialogSplit": ["Mary", "Margaret", "how", "long", "have", "we", "known", "each", "other"]}, {"character": "Mary Margaret", "dialog": " I don't know. A while.", "dialogSplit": ["I", "don't", "know", "A", "while"]}, {"character": "Sheriff Graham", "dialog": " Do you remember when we met?", "dialogSplit": ["Do", "you", "remember", "when", "we", "met"]}, {"character": "Mary Margaret", "dialog": " No.", "dialogSplit": ["No"]}, {"character": "Sheriff Graham", "dialog": " Me neither. I can't remember when I met you or when I met anyone. Isn't that odd?", "dialogSplit": ["Me", "neither", "I", "can't", "remember", "when", "I", "met", "you", "or", "when", "I", "met", "anyone", "Isn't", "that", "odd"]}, {"character": "Mary Margaret", "dialog": " I don't know. I- I suppose. I think that's just life. Things get hazy.", "dialogSplit": ["I", "don't", "know", "I", "I", "suppose", "I", "think", "that's", "just", "life", "Things", "get", "hazy"]}, {"character": "Sheriff Graham", "dialog": " Have I ever hurt you?", "dialogSplit": ["Have", "I", "ever", "hurt", "you"]}, {"character": "Mary Margaret", "dialog": " Oh Graham, no. Of course not. What is going on?", "dialogSplit": ["Oh", "Graham", "no", "Of", "course", "not", "What", "is", "going", "on"]}, {"character": "Sheriff Graham", "dialog": " Do you believe in other lives?", "dialogSplit": ["Do", "you", "believe", "in", "other", "lives"]}, {"character": "Mary Margaret", "dialog": " Like heaven?", "dialogSplit": ["Like", "heaven"]}, {"character": "Sheriff Graham", "dialog": " I mean like past lives?", "dialogSplit": ["I", "mean", "like", "past", "lives"]}, {"character": "Mary Margaret", "dialog": " You've been talking to Henry.", "dialogSplit": ["You've", "been", "talking", "to", "Henry"]}, {"character": "Sheriff Graham", "dialog": " Henry?", "dialogSplit": ["Henry"]}, {"character": "Mary Margaret", "dialog": " Oh, he has this book of stories. He has been going on about how he thinks we are all characters from them. From another land. We've forgotten who we really are. Which, of course, makes no sense.", "dialogSplit": ["Oh", "he", "has", "this", "book", "of", "stories", "He", "has", "been", "going", "on", "about", "how", "he", "thinks", "we", "are", "all", "characters", "from", "them", "From", "another", "land", "We've", "forgotten", "who", "we", "really", "are", "Which", "of", "course", "makes", "no", "sense"]}, {"character": "Sheriff Graham", "dialog": " Right. No, of course.", "dialogSplit": ["Right", "No", "of", "course"]}, {"character": "Mary Margaret", "dialog": " Graham, you're burning up. Go home and get some rest. I think you'll feel much better after you've had some sleep.", "dialogSplit": ["Graham", "you're", "burning", "up", "Go", "home", "and", "get", "some", "rest", "I", "think", "you'll", "feel", "much", "better", "after", "you've", "had", "some", "sleep"]}, {"character": "Sheriff Graham", "dialog": " Right, you're absolutely right. I'm sorry I've disturbed you. Thank you.", "dialogSplit": ["Right", "you're", "absolutely", "right", "I'm", "sorry", "I've", "disturbed", "you", "Thank", "you"]}, {"character": "Mary Margaret", "dialog": " Of course.", "dialogSplit": ["Of", "course"]}]}, {"sceneDesc": "The Enchanted Forest. Past. Snow White and the Huntsman are in the woods.", "tense": "Past", "location": "The Enchanted Forest", "dialog": [{"character": "Snow White", "dialog": " You know, when I was a little girl, the summer palace was my favorite place. The mountains surrounding it felt like a cradle. They always made me feel safe. I look forward to returning to it now. Stuffy in there?  Here. ", "dialogSplit": ["You", "know", "when", "I", "was", "a", "little", "girl", "the", "summer", "palace", "was", "my", "favorite", "place", "The", "mountains", "surrounding", "it", "felt", "like", "a", "cradle", "They", "always", "made", "me", "feel", "safe", "I", "look", "forward", "to", "returning", "to", "it", "now", "Stuffy", "in", "there", "Here"]}, {"character": "Huntsman", "dialog": " No.", "dialogSplit": ["No"]}, {"character": "Snow White", "dialog": " You're not a knight, are you?", "dialogSplit": ["You're", "not", "a", "knight", "are", "you"]}, {"character": "Huntsman", "dialog": " What makes you say that?", "dialogSplit": ["What", "makes", "you", "say", "that"]}, {"character": "Snow White", "dialog": " Without fail every one of my father's men has offered me condolences. Except you.", "dialogSplit": ["Without", "fail", "every", "one", "of", "my", "father's", "men", "has", "offered", "me", "condolences", "Except", "you"]}, {"character": "Huntsman", "dialog": " Please accept my condolences.", "dialogSplit": ["Please", "accept", "my", "condolences"]}, {"character": "Snow White", "dialog": " And they all know how to wear armor. She picked you to take me. Why?", "dialogSplit": ["And", "they", "all", "know", "how", "to", "wear", "armor", "She", "picked", "you", "to", "take", "me", "Why"]}, {"character": "Huntsman", "dialog": " I think you know.", "dialogSplit": ["I", "think", "you", "know"]}, {"character": "Snow White", "dialog": " You're going to kill me.", "dialogSplit": ["You're", "going", "to", "kill", "me"]}, {"character": "Huntsman", "dialog": " You have good instincts.", "dialogSplit": ["You", "have", "good", "instincts"]}, {"character": "Snow White", "dialog": " And you have too much armor. ", "dialogSplit": ["And", "you", "have", "too", "much", "armor"]}]}, {"sceneDesc": "Storybrooke. Present. Storybrooke Sheriff Department. Emma is at the station. She places a file on Graham's desk and picks up a dart. She throws it, aiming at the dart board but misses it. Emma goes to pick up the darts as Regina walks in.)", "tense": "Present", "location": "Storybrooke", "dialog": [{"character": "Regina", "dialog": " Our taxes always hard at work, I see.", "dialogSplit": ["Our", "taxes", "always", "hard", "at", "work", "I", "see"]}, {"character": "Emma", "dialog": " Graham isn't here. I assumed he took a sick day - with you.", "dialogSplit": ["Graham", "isn't", "here", "I", "assumed", "he", "took", "a", "sick", "day", "with", "you"]}, {"character": "Regina", "dialog": " Oh, so you're aware of us? Good - that's why I'm here. Because I'm also aware of your relationship with him.", "dialogSplit": ["Oh", "so", "you're", "aware", "of", "us", "Good", "that's", "why", "I'm", "here", "Because", "I'm", "also", "aware", "of", "your", "relationship", "with", "him"]}, {"character": "Emma", "dialog": " I don't have a relationship with him.", "dialogSplit": ["I", "don't", "have", "a", "relationship", "with", "him"]}, {"character": "Regina", "dialog": " Oh? So, nothing's ever happened between the two of you? You forget, Miss Swan, I have eyes everywhere.", "dialogSplit": ["Oh", "So", "nothing's", "ever", "happened", "between", "the", "two", "of", "you", "You", "forget", "Miss", "Swan", "I", "have", "eyes", "everywhere"]}, {"character": "Emma", "dialog": " Nothing that meant anything.", "dialogSplit": ["Nothing", "that", "meant", "anything"]}, {"character": "Regina", "dialog": " Well, of course not. Because you're incapable of feeling anything for anyone. There's a reason you're alone, isn't there?", "dialogSplit": ["Well", "of", "course", "not", "Because", "you're", "incapable", "of", "feeling", "anything", "for", "anyone", "There's", "a", "reason", "you're", "alone", "isn't", "there"]}, {"character": "Emma", "dialog": " All due respect, the way I live my life is my business.", "dialogSplit": ["All", "due", "respect", "the", "way", "I", "live", "my", "life", "is", "my", "business"]}, {"character": "Regina", "dialog": " It is until it infringes on my life. Stay away from Graham. You may think you're doing nothing, but you're putting thoughts in his head. Thoughts that are not in his best interest. You are leading him on a path to self-destruction. Stay away.", "dialogSplit": ["It", "is", "until", "it", "infringes", "on", "my", "life", "Stay", "away", "from", "Graham", "You", "may", "think", "you're", "doing", "nothing", "but", "you're", "putting", "thoughts", "in", "his", "head", "Thoughts", "that", "are", "not", "in", "his", "best", "interest", "You", "are", "leading", "him", "on", "a", "path", "to", "self", "destruction", "Stay", "away"]}]}, {"sceneDesc": "Storybrooke. Present. Graham rings the doorbell at the Mills House. Henry answers the door.", "tense": "Present", "location": "Storybrooke", "dialog": [{"character": "Henry", "dialog": " Hey, Sheriff. My mom's not here.", "dialogSplit": ["Hey", "Sheriff", "My", "mom's", "not", "here"]}, {"character": "Sheriff Graham", "dialog": " Actually, uh, I'm here to see you, Henry. I was hoping you could help me.", "dialogSplit": ["Actually", "uh", "I'm", "here", "to", "see", "you", "Henry", "I", "was", "hoping", "you", "could", "help", "me"]}, {"character": "Henry", "dialog": " Help you with what?", "dialogSplit": ["Help", "you", "with", "what"]}, {"character": "Sheriff Graham", "dialog": " It's about your book. Am I... in it?", "dialogSplit": ["It's", "about", "your", "book", "Am", "I", "in", "it"]}]}, {"sceneDesc": "The Enchanted Forest. Past. Snow White rests in the forest, writing a letter. The Huntsman catches up with her.", "tense": "Past", "location": "The Enchanted Forest", "dialog": [{"character": "Huntsman", "dialog": " I hunt you, yet you stop to compose a letter? I will never understand your kind.", "dialogSplit": ["I", "hunt", "you", "yet", "you", "stop", "to", "compose", "a", "letter", "I", "will", "never", "understand", "your", "kind"]}, {"character": "Snow White", "dialog": " I don't know these woods. You're obviously a skilled hunter - you'll find me. No matter what I do, I know how this ends.", "dialogSplit": ["I", "don't", "know", "these", "woods", "You're", "obviously", "a", "skilled", "hunter", "you'll", "find", "me", "No", "matter", "what", "I", "do", "I", "know", "how", "this", "ends"]}, {"character": "Huntsman", "dialog": " Yes.", "dialogSplit": ["Yes"]}, {"character": "Snow White", "dialog": " There's one thing I ask that you do after you kill me. Please deliver this to the Queen. .", "dialogSplit": ["There's", "one", "thing", "I", "ask", "that", "you", "do", "after", "you", "kill", "me", "Please", "deliver", "this", "to", "the", "Queen"]}, {"character": "Huntsman", "dialog": " Your tricks won't work on me.", "dialogSplit": ["Your", "tricks", "won't", "work", "on", "me"]}, {"character": "Snow White", "dialog": " It's not a trick. Please, give it to her. Tell her I mean every word. ", "dialogSplit": ["It's", "not", "a", "trick", "Please", "give", "it", "to", "her", "Tell", "her", "I", "mean", "every", "word"]}, {"character": "Huntsman", "dialog": " Sign this when you need help.", "dialogSplit": ["Sign", "this", "when", "you", "need", "help"]}, {"character": "Snow White", "dialog": " What?", "dialogSplit": ["What"]}, {"character": "Huntsman", "dialog": " It's a whistle. It will bring you aid. You will be lead to safety. Now go, run.", "dialogSplit": ["It's", "a", "whistle", "It", "will", "bring", "you", "aid", "You", "will", "be", "lead", "to", "safety", "Now", "go", "run"]}, {"character": "Snow White", "dialog": " I don't understand. You're not going to kill me?", "dialogSplit": ["I", "don't", "understand", "You're", "not", "going", "to", "kill", "me"]}, {"character": "Huntsman", "dialog": " Run!", "dialogSplit": ["Run"]}]}, {"sceneDesc": "Storybrooke. Present. Mills House. Sheriff Graham and Henry look over the book in Henry's bedroom.", "tense": "Present", "location": "Storybrooke", "dialog": [{"character": "Henry", "dialog": " When did your flashes begin?", "dialogSplit": ["When", "did", "your", "flashes", "begin"]}, {"character": "Sheriff Graham", "dialog": " Right after I kissed Emma.", "dialogSplit": ["Right", "after", "I", "kissed", "Emma"]}, {"character": "Henry", "dialog": " You kissed my mom? What did you see?", "dialogSplit": ["You", "kissed", "my", "mom", "What", "did", "you", "see"]}, {"character": "Sheriff Graham", "dialog": " A wolf. I saw that I had a knife in my hand and I was with Mary Margaret.", "dialogSplit": ["A", "wolf", "I", "saw", "that", "I", "had", "a", "knife", "in", "my", "hand", "and", "I", "was", "with", "Mary", "Margaret"]}, {"character": "Henry", "dialog": " Were you about to hurt her?", "dialogSplit": ["Were", "you", "about", "to", "hurt", "her"]}, {"character": "Sheriff Graham", "dialog": " Yes! How'd you know that?", "dialogSplit": ["Yes", "How'd", "you", "know", "that"]}, {"character": "Henry", "dialog": " Because Mary Margaret is Snow White. Which makes you the Huntsman.", "dialogSplit": ["Because", "Mary", "Margaret", "is", "Snow", "White", "Which", "makes", "you", "the", "Huntsman"]}, {"character": "Sheriff Graham", "dialog": " So you really think that I could be another person?", "dialogSplit": ["So", "you", "really", "think", "that", "I", "could", "be", "another", "person"]}, {"character": "Henry", "dialog": " Makes totally sense. You were raised by wolves. That's why you keep seeing one. It's your friend, your guide. It's trying to help you.", "dialogSplit": ["Makes", "totally", "sense", "You", "were", "raised", "by", "wolves", "That's", "why", "you", "keep", "seeing", "one", "It's", "your", "friend", "your", "guide", "It's", "trying", "to", "help", "you"]}, {"character": "Sheriff Graham", "dialog": "I'm remembering this because I kissed your mother? H-How is that possible?", "dialogSplit": ["I'm", "remembering", "this", "because", "I", "kissed", "your", "mother", "H", "How", "is", "that", "possible"]}, {"character": "Henry", "dialog": " Well, you two do have a special connection. She owes you her life.", "dialogSplit": ["Well", "you", "two", "do", "have", "a", "special", "connection", "She", "owes", "you", "her", "life"]}, {"character": "Sheriff Graham", "dialog": "How?", "dialogSplit": ["How"]}, {"character": "Henry", "dialog": " Snow White's her mother. And you spared her. If you hadn't, my mom wouldn't have been born.", "dialogSplit": ["Snow", "White's", "her", "mother", "And", "you", "spared", "her", "If", "you", "hadn't", "my", "mom", "wouldn't", "have", "been", "born"]}, {"character": "Sheriff Graham", "dialog": "W-what happened after I spared Snow White?", "dialogSplit": ["W", "what", "happened", "after", "I", "spared", "Snow", "White"]}, {"character": "Henry", "dialog": " The Queen took your heart. She ripped it out. It's kind of her thing. She never wanted you to feel ever again.", "dialogSplit": ["The", "Queen", "took", "your", "heart", "She", "ripped", "it", "out", "It's", "kind", "of", "her", "thing", "She", "never", "wanted", "you", "to", "feel", "ever", "again"]}, {"character": "Sheriff Graham", "dialog": " Let me see the book.  What's that? I saw that too. The wolf was howling at it.", "dialogSplit": ["Let", "me", "see", "the", "book", "What's", "that", "I", "saw", "that", "too", "The", "wolf", "was", "howling", "at", "it"]}, {"character": "Henry", "dialog": "That's her vault. That's where she put your heart.", "dialogSplit": ["That's", "her", "vault", "That's", "where", "she", "put", "your", "heart"]}, {"character": "Sheriff Graham", "dialog": " The wolf wants me to find it. Thank you Henry. ", "dialogSplit": ["The", "wolf", "wants", "me", "to", "find", "it", "Thank", "you", "Henry"]}]}, {"sceneDesc": "Storybrooke. Present. Emma waits for Graham just outside the Mills House.", "tense": "Present", "location": "Storybrooke", "dialog": [{"character": "Emma", "dialog": " Hey! I hear that you're having a rough day.", "dialogSplit": ["Hey", "I", "hear", "that", "you're", "having", "a", "rough", "day"]}, {"character": "Sheriff Graham", "dialog": " Who says?", "dialogSplit": ["Who", "says"]}, {"character": "Emma", "dialog": " Pretty much everyone. Maybe you need to go home and get some rest.", "dialogSplit": ["Pretty", "much", "everyone", "Maybe", "you", "need", "to", "go", "home", "and", "get", "some", "rest"]}, {"character": "Sheriff Graham", "dialog": " I'm fine. ", "dialogSplit": ["I'm", "fine"]}, {"character": "Emma", "dialog": " No, Graham. You're not fine. You just went to see a 10-year-old for help.", "dialogSplit": ["No", "Graham", "You're", "not", "fine", "You", "just", "went", "to", "see", "a", "10", "year", "old", "for", "help"]}, {"character": "Sheriff Graham", "dialog": " He seems to be the only one making sense.", "dialogSplit": ["He", "seems", "to", "be", "the", "only", "one", "making", "sense"]}, {"character": "Emma", "dialog": " What's going on? What's...really going on?", "dialogSplit": ["What's", "going", "on", "What's", "really", "going", "on"]}, {"character": "Sheriff Graham", "dialog": " It's my heart, Emma. I need to find it.", "dialogSplit": ["It's", "my", "heart", "Emma", "I", "need", "to", "find", "it"]}, {"character": "Emma", "dialog": " Okay. So how are you going to do that?", "dialogSplit": ["Okay", "So", "how", "are", "you", "going", "to", "do", "that"]}, {"character": "Sheriff Graham", "dialog": " I just need to follow the wolf.", "dialogSplit": ["I", "just", "need", "to", "follow", "the", "wolf"]}, {"character": "Emma", "dialog": " What? What wolf?", "dialogSplit": ["What", "What", "wolf"]}, {"character": "Sheriff Graham", "dialog": " From my dreams. He gonna help me find my heart.", "dialogSplit": ["From", "my", "dreams", "He", "gonna", "help", "me", "find", "my", "heart"]}, {"character": "Emma", "dialog": " I'm sorry. I...thought we were talking in a metaphor here. You really think that you don't have a heart?", "dialogSplit": ["I'm", "sorry", "I", "thought", "we", "were", "talking", "in", "a", "metaphor", "here", "You", "really", "think", "that", "you", "don't", "have", "a", "heart"]}, {"character": "Sheriff Graham", "dialog": " It's the only thing that makes any sense. It's the only thing that explains why I don't feel anything.", "dialogSplit": ["It's", "the", "only", "thing", "that", "makes", "any", "sense", "It's", "the", "only", "thing", "that", "explains", "why", "I", "don't", "feel", "anything"]}, {"character": "Emma", "dialog": " Listen to me, Graham. You have a heart. I can prove it.  See, it's beating. It's real.  Feel that? That is your heart.", "dialogSplit": ["Listen", "to", "me", "Graham", "You", "have", "a", "heart", "I", "can", "prove", "it", "See", "it's", "beating", "It's", "real", "Feel", "that", "That", "is", "your", "heart"]}, {"character": "Sheriff Graham", "dialog": " No. It's the curse.", "dialogSplit": ["No", "It's", "the", "curse"]}, {"character": "Emma", "dialog": " You can't really believe that's true. ", "dialogSplit": ["You", "can't", "really", "believe", "that's", "true"]}, {"character": "Sheriff Graham", "dialog": " What? (he looks behind him and there's the wolf. He looks back and Emma and then goes after it. Emma follows.)", "dialogSplit": ["What", "he", "looks", "behind", "him", "and", "there's", "the", "wolf", "He", "looks", "back", "and", "Emma", "and", "then", "goes", "after", "it", "Emma", "follows"]}]}, {"sceneDesc": "Storybrooke. Present. Graham and Emma end up chasing after the wolf into the Storybrooke Graveyard.", "tense": "Present", "location": "Storybrooke", "dialog": [{"character": "Emma", "dialog": " Graham. Graham be careful!", "dialogSplit": ["Graham", "Graham", "be", "careful"]}, {"character": "Sheriff Graham", "dialog": " It's my friend. It won't hurt us. ", "dialogSplit": ["It's", "my", "friend", "It", "won't", "hurt", "us"]}, {"character": "Emma", "dialog": " What is it?", "dialogSplit": ["What", "is", "it"]}, {"character": "Sheriff Graham", "dialog": " It's my heart. It's in there. I have to look in there.", "dialogSplit": ["It's", "my", "heart", "It's", "in", "there", "I", "have", "to", "look", "in", "there"]}, {"character": "Emma", "dialog": " Oh, no. Stop, stop.", "dialogSplit": ["Oh", "no", "Stop", "stop"]}, {"character": "Sheriff Graham", "dialog": " I have to get in there. Please.", "dialogSplit": ["I", "have", "to", "get", "in", "there", "Please"]}, {"character": "Emma", "dialog": " Graham, come on. You really think that you're heart is in there.  Okay. Let's find out.  Come on! ", "dialogSplit": ["Graham", "come", "on", "You", "really", "think", "that", "you're", "heart", "is", "in", "there", "Okay", "Let's", "find", "out", "Come", "on"]}]}, {"sceneDesc": "The Enchanted Forest. Dark Palace. A guard escorts the Huntsman to the Evil Queen's chambers.", "tense": null, "location": "The Enchanted Forest", "dialog": [{"character": "Guard", "dialog": " Wait here. ", "dialogSplit": ["Wait", "here"]}, {"character": "The Huntsman", "dialog": " I see you're still in mourning.", "dialogSplit": ["I", "see", "you're", "still", "in", "mourning"]}, {"character": "The Evil Queen", "dialog": " The time for mourning is over. I simply found that black suits me. Now, tell me, is Snow dead? ", "dialogSplit": ["The", "time", "for", "mourning", "is", "over", "I", "simply", "found", "that", "black", "suits", "me", "Now", "tell", "me", "is", "Snow", "dead"]}, {"character": "The Huntsman", "dialog": " The young girl's heart as you requested.  First, there's something I must do. ", "dialogSplit": ["The", "young", "girl's", "heart", "as", "you", "requested", "First", "there's", "something", "I", "must", "do"]}, {"character": "The Evil Queen", "dialog": " What's this?", "dialogSplit": ["What's", "this"]}, {"character": "The Huntsman", "dialog": " The girl wanted you to have it.", "dialogSplit": ["The", "girl", "wanted", "you", "to", "have", "it"]}, {"character": "The Evil Queen", "dialog": " Read it to me.", "dialogSplit": ["Read", "it", "to", "me"]}, {"character": "The Huntsman", "dialog": " Dear Stepmother, ", "dialogSplit": ["Dear", "Stepmother"]}, {"character": "Snow White", "dialog": " By the time you read this I will be dead. I understand that you will never have love in your life because of me. So it's only fitting that I'll be denied that same joy as well. For the sake of the kingdom, I hope my death satisfies your need for revenge, allowing you to rule my father's subjects as they deserve, with compassion, and a gentle hand. I know what you think you're doing is vengeance, I prefer to think of it as sacrifice, for the good of all. With that in mind I welcome the end. I want you to take my last message to heart. I'm sorry, and I forgive you.", "dialogSplit": ["By", "the", "time", "you", "read", "this", "I", "will", "be", "dead", "I", "understand", "that", "you", "will", "never", "have", "love", "in", "your", "life", "because", "of", "me", "So", "it's", "only", "fitting", "that", "I'll", "be", "denied", "that", "same", "joy", "as", "well", "For", "the", "sake", "of", "the", "kingdom", "I", "hope", "my", "death", "satisfies", "your", "need", "for", "revenge", "allowing", "you", "to", "rule", "my", "father's", "subjects", "as", "they", "deserve", "with", "compassion", "and", "a", "gentle", "hand", "I", "know", "what", "you", "think", "you're", "doing", "is", "vengeance", "I", "prefer", "to", "think", "of", "it", "as", "sacrifice", "for", "the", "good", "of", "all", "With", "that", "in", "mind", "I", "welcome", "the", "end", "I", "want", "you", "to", "take", "my", "last", "message", "to", "heart", "I'm", "sorry", "and", "I", "forgive", "you"]}, {"character": "The Evil Queen", "dialog": " Don't tell me you're becoming a sheep. ", "dialogSplit": ["Don't", "tell", "me", "you're", "becoming", "a", "sheep"]}, {"character": "The Huntsman", "dialog": " She put others before herself and yet, you hate her. What did she do to you?", "dialogSplit": ["She", "put", "others", "before", "herself", "and", "yet", "you", "hate", "her", "What", "did", "she", "do", "to", "you"]}, {"character": "The Evil Queen", "dialog": " I shared a secret with her and she couldn't keep it and that betrayal cost me dearly. Now, show me her heart!  It should open.  This isn't her heart! This isn't a human heart! What did you do?", "dialogSplit": ["I", "shared", "a", "secret", "with", "her", "and", "she", "couldn't", "keep", "it", "and", "that", "betrayal", "cost", "me", "dearly", "Now", "show", "me", "her", "heart", "It", "should", "open", "This", "isn't", "her", "heart", "This", "isn't", "a", "human", "heart", "What", "did", "you", "do"]}]}, {"sceneDesc": " Storybrooke. Present day. Storybrooke Graveyard. The crypt. Sheriff Graham scours the room for his heart. There\u2019s a sarcophagus standing in the middle of the room. The inscription reads \u201aHenry Mills. Beloved father'.", "tense": "Present", "location": "Storybrooke", "dialog": [{"character": "Sheriff Graham", "dialog": " It's got to be in here. Somewhere.  There's got to be a hidden door. A lever. (he tries to open an urn.) Something.", "dialogSplit": ["It's", "got", "to", "be", "in", "here", "Somewhere", "There's", "got", "to", "be", "a", "hidden", "door", "A", "lever", "he", "tries", "to", "open", "an", "urn", "Something"]}, {"character": "Emma", "dialog": " Graham. Hey, Graham. There's nothing in here.", "dialogSplit": ["Graham", "Hey", "Graham", "There's", "nothing", "in", "here"]}, {"character": "Sheriff Graham", "dialog": " There has to be. If there isn't, then-", "dialogSplit": ["There", "has", "to", "be", "If", "there", "isn't", "then"]}, {"character": "Emma", "dialog": " It's okay. It's going to be okay.", "dialogSplit": ["It's", "okay", "It's", "going", "to", "be", "okay"]}, {"character": "Regina", "dialog": " What the hell do you think you're doing?", "dialogSplit": ["What", "the", "hell", "do", "you", "think", "you're", "doing"]}, {"character": "Emma", "dialog": " What are you doing here? (Emma and Sheriff Graham exit the crypt.)", "dialogSplit": ["What", "are", "you", "doing", "here", "Emma", "and", "Sheriff", "Graham", "exit", "the", "crypt"]}, {"character": "Regina", "dialog": " Bringing flowers to my father's grave. Like I do every Wednesday.", "dialogSplit": ["Bringing", "flowers", "to", "my", "father's", "grave", "Like", "I", "do", "every", "Wednesday"]}, {"character": "Sheriff Graham", "dialog": " Don't blame her. It's my fault. I wanted to look in there. ", "dialogSplit": ["Don't", "blame", "her", "It's", "my", "fault", "I", "wanted", "to", "look", "in", "there"]}, {"character": "Regina", "dialog": " Really? Why? What were you looking for?", "dialogSplit": ["Really", "Why", "What", "were", "you", "looking", "for"]}, {"character": "Sheriff Graham", "dialog": " Nothing. It was- uh, nothing. It was nothing.", "dialogSplit": ["Nothing", "It", "was", "uh", "nothing", "It", "was", "nothing"]}, {"character": "Regina", "dialog": " You don't look well, dear. Let's take you home. (She grabs Sheriff Graham dragging him with her. Sheriff Graham breaks free from her)", "dialogSplit": ["You", "don't", "look", "well", "dear", "Let's", "take", "you", "home", "She", "grabs", "Sheriff", "Graham", "dragging", "him", "with", "her", "Sheriff", "Graham", "breaks", "free", "from", "her"]}, {"character": "Sheriff Graham", "dialog": " Regina, I don't want to go home. Not with you.", "dialogSplit": ["Regina", "I", "don't", "want", "to", "go", "home", "Not", "with", "you"]}, {"character": "Regina", "dialog": " Oh, but you'll go with her?", "dialogSplit": ["Oh", "but", "you'll", "go", "with", "her"]}, {"character": "Emma", "dialog": " Hey, this is between you two. Leave me out of it.", "dialogSplit": ["Hey", "this", "is", "between", "you", "two", "Leave", "me", "out", "of", "it"]}, {"character": "Sheriff Graham", "dialog": " She's right. It's between us. And things have to change.", "dialogSplit": ["She's", "right", "It's", "between", "us", "And", "things", "have", "to", "change"]}, {"character": "Regina", "dialog": " And I wonder, why that is, all of a sudden.", "dialogSplit": ["And", "I", "wonder", "why", "that", "is", "all", "of", "a", "sudden"]}, {"character": "Sheriff Graham", "dialog": " It has nothing to do with her. I\u2019ve realized that I don't feel anything, Regina. And I know now, it's not me. It's you.", "dialogSplit": ["It", "has", "nothing", "to", "do", "with", "her", "I", "ve", "realized", "that", "I", "don't", "feel", "anything", "Regina", "And", "I", "know", "now", "it's", "not", "me", "It's", "you"]}, {"character": "Regina", "dialog": " So, you're leaving me for her.", "dialogSplit": ["So", "you're", "leaving", "me", "for", "her"]}, {"character": "Sheriff Graham", "dialog": " I'm leaving you for me.", "dialogSplit": ["I'm", "leaving", "you", "for", "me"]}, {"character": "Regina", "dialog": " Graham, you're not thinking straight.", "dialogSplit": ["Graham", "you're", "not", "thinking", "straight"]}, {"character": "Sheriff Graham", "dialog": " Actually, for the first time I am. I'd rather have nothing than settle for less. Nothing? Is better than what we have. I need to feel something, Regina, and the only way to do that is to give myself a chance.", "dialogSplit": ["Actually", "for", "the", "first", "time", "I", "am", "I'd", "rather", "have", "nothing", "than", "settle", "for", "less", "Nothing", "Is", "better", "than", "what", "we", "have", "I", "need", "to", "feel", "something", "Regina", "and", "the", "only", "way", "to", "do", "that", "is", "to", "give", "myself", "a", "chance"]}, {"character": "Regina", "dialog": " Graham.", "dialogSplit": ["Graham"]}, {"character": "Sheriff Graham", "dialog": " I'm sorry. It's over.", "dialogSplit": ["I'm", "sorry", "It's", "over"]}, {"character": "Regina", "dialog": " I don't know what I ever did to you, Miss Swan, to deserve this. To have you keep coming after everything I hold dear.", "dialogSplit": ["I", "don't", "know", "what", "I", "ever", "did", "to", "you", "Miss", "Swan", "to", "deserve", "this", "To", "have", "you", "keep", "coming", "after", "everything", "I", "hold", "dear"]}, {"character": "Sheriff Graham", "dialog": " I told you, it's not her.", "dialogSplit": ["I", "told", "you", "it's", "not", "her"]}, {"character": "Regina", "dialog": " None of this happened until she got here.", "dialogSplit": ["None", "of", "this", "happened", "until", "she", "got", "here"]}, {"character": "Emma", "dialog": " I'm sorry. Did you ever stop to think that maybe the problem isn't with me, but with you?", "dialogSplit": ["I'm", "sorry", "Did", "you", "ever", "stop", "to", "think", "that", "maybe", "the", "problem", "isn't", "with", "me", "but", "with", "you"]}, {"character": "Regina", "dialog": " Excuse me?", "dialogSplit": ["Excuse", "me"]}, {"character": "Emma", "dialog": " Henry came and found me. Graham kissed me. Both were miserable. Maybe, Madam Mayor, you need to take a good hard look in the mirror and ask yourself why that is. Why is everyone running away from you? ", "dialogSplit": ["Henry", "came", "and", "found", "me", "Graham", "kissed", "me", "Both", "were", "miserable", "Maybe", "Madam", "Mayor", "you", "need", "to", "take", "a", "good", "hard", "look", "in", "the", "mirror", "and", "ask", "yourself", "why", "that", "is", "Why", "is", "everyone", "running", "away", "from", "you"]}, {"character": "Sheriff Graham", "dialog": " Regina!(", "dialogSplit": ["Regina"]}, {"character": "Emma", "dialog": " Not worth it.", "dialogSplit": ["Not", "worth", "it"]}, {"character": "Regina", "dialog": " Graham. ", "dialogSplit": ["Graham"]}]}, {"sceneDesc": " Storybrooke. Present day. Storybrooke Sheriff Department. Sheriff Graham has prepared an ice pack and hands it to Emma. ", "tense": "Present", "location": "Storybrooke", "dialog": [{"character": "Sheriff Graham", "dialog": " I don't know what came over me. I kind of lost my mind.", "dialogSplit": ["I", "don't", "know", "what", "came", "over", "me", "I", "kind", "of", "lost", "my", "mind"]}, {"character": "Emma", "dialog": " It's okay. You were tired. And feverish. And heartbroken.", "dialogSplit": ["It's", "okay", "You", "were", "tired", "And", "feverish", "And", "heartbroken"]}, {"character": "Sheriff Graham", "dialog": " I don't know why I let myself get caught up with her.", "dialogSplit": ["I", "don't", "know", "why", "I", "let", "myself", "get", "caught", "up", "with", "her"]}, {"character": "Emma", "dialog": " Because it was easy. And safe. Not feeling anything is an attractive option when what you feel sucks. Felt that.", "dialogSplit": ["Because", "it", "was", "easy", "And", "safe", "Not", "feeling", "anything", "is", "an", "attractive", "option", "when", "what", "you", "feel", "sucks", "Felt", "that"]}]}, {"sceneDesc": " The Enchanted Forest Past. Dark Palace. The Evil Queen and the Huntsman are in the smaller room with the wall of drawers. She slams the heart down onto the pedestal.", "tense": "Past", "location": "The Enchanted Forest", "dialog": [{"character": "Evil Queen", "dialog": " Did you think you can fool me with the heart of a stag?  You're not going anywhere.", "dialogSplit": ["Did", "you", "think", "you", "can", "fool", "me", "with", "the", "heart", "of", "a", "stag", "You're", "not", "going", "anywhere"]}, {"character": "The Huntsman", "dialog": " She doesn't deserve to die. ", "dialogSplit": ["She", "doesn't", "deserve", "to", "die"]}, {"character": "The Evil Queen", "dialog": " That's not up to you. I wanted a heart, and a heart I shall have.Huntsman: What... What are you going to do to me?", "dialogSplit": ["That's", "not", "up", "to", "you", "I", "wanted", "a", "heart", "and", "a", "heart", "I", "shall", "have", "Huntsman", "What", "What", "are", "you", "going", "to", "do", "to", "me"]}, {"character": "Evil Queen", "dialog": " You're now mine, my pet.And this is your cage. From this moment forward, you will do everything that I say. And if you ever disobey me, if you ever try to run away, all I have to do is squeeze.Guards!Your life is now in my hands \u2013 forever. Take him to my bedchamber.", "dialogSplit": ["You're", "now", "mine", "my", "pet", "And", "this", "is", "your", "cage", "From", "this", "moment", "forward", "you", "will", "do", "everything", "that", "I", "say", "And", "if", "you", "ever", "disobey", "me", "if", "you", "ever", "try", "to", "run", "away", "all", "I", "have", "to", "do", "is", "squeeze", "Guards", "Your", "life", "is", "now", "in", "my", "hands", "forever", "Take", "him", "to", "my", "bedchamber"]}]}, {"sceneDesc": " Storybrooke. Present day. Storybrooke Sheriff Department. Sheriff Graham still attends to Emmas's wound.", "tense": "Present", "location": "Storybrooke", "dialog": [{"character": "Sheriff Graham", "dialog": " All better.", "dialogSplit": ["All", "better"]}, {"character": "Emma", "dialog": " Yeah.", "dialogSplit": ["Yeah"]}, {"character": "Sheriff Graham", "dialog": " What?", "dialogSplit": ["What"]}, {"character": "Emma", "dialog": " Graham?", "dialogSplit": ["Graham"]}]}, {"sceneDesc": " Storybrooke. Present day. Storybrooke Sheriff .", "tense": "Present", "location": "Storybrooke", "dialog": [{"character": "Emma", "dialog": " You're okay?", "dialogSplit": ["You're", "okay"]}, {"character": "Sheriff Graham", "dialog": " I remember.", "dialogSplit": ["I", "remember"]}, {"character": "Emma", "dialog": " Graham?", "dialogSplit": ["Graham"]}, {"character": "Sheriff Graham", "dialog": " I remember.", "dialogSplit": ["I", "remember"]}, {"character": "Emma", "dialog": " You remember what?", "dialogSplit": ["You", "remember", "what"]}]}, {"sceneDesc": "  Storybrooke. Present day. Storybrooke Sheriff Department. Graham slowly approaches Emma. He cups her face with his hands.", "tense": "Present", "location": "Storybrooke", "dialog": [{"character": "Sheriff Graham", "dialog": " Thank you. ", "dialogSplit": ["Thank", "you"]}]}, {"sceneDesc": "  Storybrooke. Present day. Storybrooke Sheriff Department. Sheriff Graham doubles over in pain and falls to the ground", "tense": "Present", "location": "Storybrooke", "dialog": [{"character": "Emma", "dialog": " Graham! Graham! Graham! ", "dialogSplit": ["Graham", "Graham", "Graham"]}]}, {"sceneDesc": " Storybrooke. Present day. Storybrooke Sheriff Department. Sobbing, Emma is still trying to wake Graham, Who now lies dead on the floor. ", "tense": "Present", "location": "Storybrooke", "dialog": [{"character": "Emma", "dialog": " Graham! Graham! Come on, Graham! Graham! ", "dialogSplit": ["Graham", "Graham", "Come", "on", "Graham", "Graham"]}]}, {"sceneDesc": " Storybrooke. Present day. Storybrooke Sheriff Department. Sobbing, Emma is still trying to wake Graham, Who now lies dead on the floor. ", "tense": "Present", "location": "Storybrooke", "dialog": [{"character": "", "dialog": "End", "dialogSplit": ["End"]}]}]}