{"episode": "The_Price_of_Gold", "scenes": [{"sceneDesc": "The Enchanted Forest. Past.  Tremaine Estate - Night. The wicked stepmother and the ugly stepsisters dressed in gowns get in their carriage that will take them to the ball, while Cinderella is left behind sweeping, dressed in rags. ", "tense": "Past", "location": "The Enchanted Forest", "dialog": [{"character": "Fairy Godmother", "dialog": " Do not despair, my dear, you will attend that ball.", "dialogSplit": ["Do", "not", "despair", "my", "dear", "you", "will", "attend", "that", "ball"]}, {"character": "Cinderella", "dialog": " Who are you?", "dialogSplit": ["Who", "are", "you"]}, {"character": "Fairy Godmother", "dialog": " I'm your Fairy Godmother, and I'm here to change your life Cinderella.", "dialogSplit": ["I'm", "your", "Fairy", "Godmother", "and", "I'm", "here", "to", "change", "your", "life", "Cinderella"]}, {"character": "Cinderella", "dialog": " But my Stepmother told me that I couldn't go, she forbade me to leave.", "dialogSplit": ["But", "my", "Stepmother", "told", "me", "that", "I", "couldn't", "go", "she", "forbade", "me", "to", "leave"]}, {"character": "Fairy Godmother", "dialog": " Your Stepmother doesn't have this.  This wand has the power to take you to your ball, to your prince, and to... ", "dialogSplit": ["Your", "Stepmother", "doesn't", "have", "this", "This", "wand", "has", "the", "power", "to", "take", "you", "to", "your", "ball", "to", "your", "prince", "and", "to"]}, {"character": "Cinderella", "dialog": " What did you do?", "dialogSplit": ["What", "did", "you", "do"]}, {"character": "Rumplestiltskin", "dialog": " Now now, I got what I wanted. There's no need to be frightened.", "dialogSplit": ["Now", "now", "I", "got", "what", "I", "wanted", "There's", "no", "need", "to", "be", "frightened"]}, {"character": "Cinderella", "dialog": " No need? You just killed my Fairy Godmother. She was trying to help me.", "dialogSplit": ["No", "need", "You", "just", "killed", "my", "Fairy", "Godmother", "She", "was", "trying", "to", "help", "me"]}, {"character": "Rumplestiltskin", "dialog": " Was she? Do you know what this is? ", "dialogSplit": ["Was", "she", "Do", "you", "know", "what", "this", "is"]}, {"character": "Cinderella", "dialog": " Pure magic.", "dialogSplit": ["Pure", "magic"]}, {"character": "Rumplestiltskin", "dialog": " Pure evil. Trust me. I've done you a favor. All magic comes with a price. Go on back to your life and thank your lucky stars you've still got something to go back to.", "dialogSplit": ["Pure", "evil", "Trust", "me", "I've", "done", "you", "a", "favor", "All", "magic", "comes", "with", "a", "price", "Go", "on", "back", "to", "your", "life", "and", "thank", "your", "lucky", "stars", "you've", "still", "got", "something", "to", "go", "back", "to"]}, {"character": "Cinderella", "dialog": " My life...it's wretched.", "dialogSplit": ["My", "life", "it's", "wretched"]}, {"character": "Rumplestiltskin", "dialog": " Then change it. You can't handle this. ", "dialogSplit": ["Then", "change", "it", "You", "can't", "handle", "this"]}, {"character": "Cinderella", "dialog": " Wait, please wait. I can handle it. Please, I will do anything to get out of here, anything.", "dialogSplit": ["Wait", "please", "wait", "I", "can", "handle", "it", "Please", "I", "will", "do", "anything", "to", "get", "out", "of", "here", "anything"]}, {"character": "Rumplestiltskin", "dialog": " Anything?", "dialogSplit": ["Anything"]}, {"character": "Cinderella", "dialog": " Do you know how to use the wand, Mr...", "dialogSplit": ["Do", "you", "know", "how", "to", "use", "the", "wand", "Mr"]}, {"character": "Rumplestiltskin", "dialog": " Rumplestiltskin. And yes, of course I do.", "dialogSplit": ["Rumplestiltskin", "And", "yes", "of", "course", "I", "do"]}, {"character": "Cinderella", "dialog": " Then help me.", "dialogSplit": ["Then", "help", "me"]}, {"character": "Rumplestiltskin", "dialog": " Well, if I do, and you can indeed shoulder the uh... consequences, then you'll owe me a favor.", "dialogSplit": ["Well", "if", "I", "do", "and", "you", "can", "indeed", "shoulder", "the", "uh", "consequences", "then", "you'll", "owe", "me", "a", "favor"]}, {"character": "Cinderella", "dialog": " Name it, what do you want?", "dialogSplit": ["Name", "it", "what", "do", "you", "want"]}, {"character": "Rumplestiltskin", "dialog": " Something precious.", "dialogSplit": ["Something", "precious"]}, {"character": "Cinderella", "dialog": " But I have nothing.", "dialogSplit": ["But", "I", "have", "nothing"]}, {"character": "Rumplestiltskin", "dialog": " Oh, but you will. With this wish will come riches more than you know.", "dialogSplit": ["Oh", "but", "you", "will", "With", "this", "wish", "will", "come", "riches", "more", "than", "you", "know"]}, {"character": "Cinderella", "dialog": " I care nothing for riches. I'll give you anything you want. Just get me out of here.", "dialogSplit": ["I", "care", "nothing", "for", "riches", "I'll", "give", "you", "anything", "you", "want", "Just", "get", "me", "out", "of", "here"]}, {"character": "Rumplestiltskin", "dialog": " Now we're talking.", "dialogSplit": ["Now", "we're", "talking"]}, {"character": "Cinderella", "dialog": " Well, how does it work?", "dialogSplit": ["Well", "how", "does", "it", "work"]}, {"character": "Rumplestiltskin", "dialog": " Fear not. My needs are small, and all you have to do is sign on the dotted line . Do we have a deal?", "dialogSplit": ["Fear", "not", "My", "needs", "are", "small", "and", "all", "you", "have", "to", "do", "is", "sign", "on", "the", "dotted", "line", "Do", "we", "have", "a", "deal"]}, {"character": "Cinderella", "dialog": " Yes, yes thank you. ", "dialogSplit": ["Yes", "yes", "thank", "you"]}, {"character": "Rumplestiltskin", "dialog": " Mmm...  There.", "dialogSplit": ["Mmm", "There"]}, {"character": "Cinderella", "dialog": " Glass?", "dialogSplit": ["Glass"]}, {"character": "Rumplestiltskin", "dialog": " Every story needs a memorable detail. Let's see how they fit, shall we?  Now you have a good time, but be sure to watch the clock.", "dialogSplit": ["Every", "story", "needs", "a", "memorable", "detail", "Let's", "see", "how", "they", "fit", "shall", "we", "Now", "you", "have", "a", "good", "time", "but", "be", "sure", "to", "watch", "the", "clock"]}]}, {"sceneDesc": "Storybrooke. Present day.  The bell of the clock tower rings out as Henry Mills and Emma Swan walk Main Street. ", "tense": "Present", "location": "Storybrooke", "dialog": [{"character": "Henry", "dialog": " Are you sure we can be seen out in the open?", "dialogSplit": ["Are", "you", "sure", "we", "can", "be", "seen", "out", "in", "the", "open"]}, {"character": "Emma", "dialog": " Enough sneaking around. If your mom has a problem with me walking you to a school bus, I am more than happy to have that chat.", "dialogSplit": ["Enough", "sneaking", "around", "If", "your", "mom", "has", "a", "problem", "with", "me", "walking", "you", "to", "a", "school", "bus", "I", "am", "more", "than", "happy", "to", "have", "that", "chat"]}, {"character": "Henry", "dialog": " You're brave. You'll need that for Operation Cobra. Speaking of, do you think we need code names?", "dialogSplit": ["You're", "brave", "You'll", "need", "that", "for", "Operation", "Cobra", "Speaking", "of", "do", "you", "think", "we", "need", "code", "names"]}, {"character": "Emma", "dialog": " Isn't \"Cobra\" our code name?", "dialogSplit": ["Isn't", "Cobra", "our", "code", "name"]}, {"character": "Henry", "dialog": " That's the mission. I mean us. I need something to call you.", "dialogSplit": ["That's", "the", "mission", "I", "mean", "us", "I", "need", "something", "to", "call", "you"]}, {"character": "Emma", "dialog": " Oh, um... well I don't... you can just call me \"Emma\" for now.", "dialogSplit": ["Oh", "um", "well", "I", "don't", "you", "can", "just", "call", "me", "Emma", "for", "now"]}, {"character": "Henry", "dialog": " Okay, well I'll see you later, Emma. ", "dialogSplit": ["Okay", "well", "I'll", "see", "you", "later", "Emma"]}, {"character": "Emma", "dialog": " What's with the siren?", "dialogSplit": ["What's", "with", "the", "siren"]}, {"character": "Graham", "dialog": " It's so hard to get your attention.", "dialogSplit": ["It's", "so", "hard", "to", "get", "your", "attention"]}, {"character": "Emma", "dialog": " Alright, well you got it. Are you arresting me again?", "dialogSplit": ["Alright", "well", "you", "got", "it", "Are", "you", "arresting", "me", "again"]}, {"character": "Graham", "dialog": " I'm thanking you  for your help finding that coma patient. We all owe you a debt of gratitude.", "dialogSplit": ["I'm", "thanking", "you", "for", "your", "help", "finding", "that", "coma", "patient", "We", "all", "owe", "you", "a", "debt", "of", "gratitude"]}, {"character": "Emma", "dialog": " Well, what do I get? A commendation? Key to the city?", "dialogSplit": ["Well", "what", "do", "I", "get", "A", "commendation", "Key", "to", "the", "city"]}, {"character": "Graham", "dialog": " How about a job? I could use a deputy.", "dialogSplit": ["How", "about", "a", "job", "I", "could", "use", "a", "deputy"]}, {"character": "Emma", "dialog": " Thank you, but I have a job.", "dialogSplit": ["Thank", "you", "but", "I", "have", "a", "job"]}, {"character": "Graham", "dialog": " As a bail bondsperson? There's not much of that going on here.", "dialogSplit": ["As", "a", "bail", "bondsperson", "There's", "not", "much", "of", "that", "going", "on", "here"]}, {"character": "Emma", "dialog": " I don't see a lot of sheriffing going on around here either.", "dialogSplit": ["I", "don't", "see", "a", "lot", "of", "sheriffing", "going", "on", "around", "here", "either"]}, {"character": "Graham", "dialog": " Well, here's your chance to see it up close. There's dental. Why don't you think about it and stay awhile.", "dialogSplit": ["Well", "here's", "your", "chance", "to", "see", "it", "up", "close", "There's", "dental", "Why", "don't", "you", "think", "about", "it", "and", "stay", "awhile"]}]}, {"sceneDesc": "Storybrooke. Present. Granny's Diner - Morning. Ruby is bringing Emma, who sits reading the newspaper, a cup of hot cocoa. ", "tense": "Present", "location": "Storybrooke", "dialog": [{"character": "Emma", "dialog": " Thank you .", "dialogSplit": ["Thank", "you"]}, {"character": "Regina", "dialog": " How was your walk with Henry? That's right I know everything. But relax I don't mind .", "dialogSplit": ["How", "was", "your", "walk", "with", "Henry", "That's", "right", "I", "know", "everything", "But", "relax", "I", "don't", "mind"]}, {"character": "Emma", "dialog": " You don't?", "dialogSplit": ["You", "don't"]}, {"character": "Regina", "dialog": " No. Because you no longer worry me, Ms. Swan. You see I did a little digging into who you are, and what I found out was quite soothing. It all comes down to the number seven.", "dialogSplit": ["No", "Because", "you", "no", "longer", "worry", "me", "Ms", "Swan", "You", "see", "I", "did", "a", "little", "digging", "into", "who", "you", "are", "and", "what", "I", "found", "out", "was", "quite", "soothing", "It", "all", "comes", "down", "to", "the", "number", "seven"]}, {"character": "Emma", "dialog": " Seven?", "dialogSplit": ["Seven"]}, {"character": "Regina", "dialog": " It's the number of addresses you've had in the past decade. Your longest stint anywhere was two years. Really, what did you enjoy so much about Tallahassee?", "dialogSplit": ["It's", "the", "number", "of", "addresses", "you've", "had", "in", "the", "past", "decade", "Your", "longest", "stint", "anywhere", "was", "two", "years", "Really", "what", "did", "you", "enjoy", "so", "much", "about", "Tallahassee"]}, {"character": "Emma", "dialog": " If you were wondering, I did find a place here in town.", "dialogSplit": ["If", "you", "were", "wondering", "I", "did", "find", "a", "place", "here", "in", "town"]}, {"character": "Regina", "dialog": " I know with Ms. Blanchard. How long is your lease? Oh wait. You don't have one. You see my point? In order for something to grow Ms. Swan, it needs roots, and you don't have any. People don't change they only fool themselves into believing they can.", "dialogSplit": ["I", "know", "with", "Ms", "Blanchard", "How", "long", "is", "your", "lease", "Oh", "wait", "You", "don't", "have", "one", "You", "see", "my", "point", "In", "order", "for", "something", "to", "grow", "Ms", "Swan", "it", "needs", "roots", "and", "you", "don't", "have", "any", "People", "don't", "change", "they", "only", "fool", "themselves", "into", "believing", "they", "can"]}, {"character": "Emma", "dialog": " You don't know me.", "dialogSplit": ["You", "don't", "know", "me"]}, {"character": "Regina", "dialog": " No, I think I do. All I ask as you carry on your transient life, you think about Henry and what's best for him. Perhaps consider a clean break. It's going to happen anyway. Enjoy your cocoa. ", "dialogSplit": ["No", "I", "think", "I", "do", "All", "I", "ask", "as", "you", "carry", "on", "your", "transient", "life", "you", "think", "about", "Henry", "and", "what's", "best", "for", "him", "Perhaps", "consider", "a", "clean", "break", "It's", "going", "to", "happen", "anyway", "Enjoy", "your", "cocoa"]}, {"character": "Emma", "dialog": " Ugh, really? ", "dialogSplit": ["Ugh", "really"]}, {"character": "Ruby", "dialog": " Eesh.", "dialogSplit": ["Eesh"]}, {"character": "Emma", "dialog": " Do you have a laundry room I can use?", "dialogSplit": ["Do", "you", "have", "a", "laundry", "room", "I", "can", "use"]}, {"character": "Ruby", "dialog": " Mhm!", "dialogSplit": ["Mhm"]}]}, {"sceneDesc": "Storybrooke. Present. Granny's Bed & Breakfast - Morning. Emma walks in the back to the laundry room where Ashley Boyd is working, puts her shirt in the washer, and takes one off of the clothesline.", "tense": "Present", "location": "Storybrooke", "dialog": [{"character": "Ashley", "dialog": " Oh, no, no, no, no, no!", "dialogSplit": ["Oh", "no", "no", "no", "no", "no"]}, {"character": "Emma", "dialog": " You okay?", "dialogSplit": ["You", "okay"]}, {"character": "Ashley", "dialog": " The sheets, they're uh... pink.", "dialogSplit": ["The", "sheets", "they're", "uh", "pink"]}, {"character": "Emma", "dialog": " You try bleach?  Oh.", "dialogSplit": ["You", "try", "bleach", "Oh"]}, {"character": "Ashley", "dialog": " Last night I felt contractions, and the doctor said that the baby could come any day now.", "dialogSplit": ["Last", "night", "I", "felt", "contractions", "and", "the", "doctor", "said", "that", "the", "baby", "could", "come", "any", "day", "now"]}, {"character": "Emma", "dialog": " So... that's great.", "dialogSplit": ["So", "that's", "great"]}, {"character": "Ashley", "dialog": " It's just that, um, when the... when the baby comes... no one thinks I can do this. No one thinks I can do anything. Maybe they're right.", "dialogSplit": ["It's", "just", "that", "um", "when", "the", "when", "the", "baby", "comes", "no", "one", "thinks", "I", "can", "do", "this", "No", "one", "thinks", "I", "can", "do", "anything", "Maybe", "they're", "right"]}, {"character": "Emma", "dialog": " Screw them.", "dialogSplit": ["Screw", "them"]}, {"character": "Ashley", "dialog": " What?", "dialogSplit": ["What"]}, {"character": "Emma", "dialog": " Screw them. How old are you?", "dialogSplit": ["Screw", "them", "How", "old", "are", "you"]}, {"character": "Ashley", "dialog": " 19.", "dialogSplit": ["19"]}, {"character": "Emma", "dialog": " I was 18.", "dialogSplit": ["I", "was", "18"]}, {"character": "Ashley", "dialog": " When you... when you had a kid?", "dialogSplit": ["When", "you", "when", "you", "had", "a", "kid"]}, {"character": "Emma", "dialog": " Yeah. I know what it's like. Everyone loves to tell you what you can and can't do especially with a kid, but ultimately whatever you're considering doing... or giving up... the choice is yours.", "dialogSplit": ["Yeah", "I", "know", "what", "it's", "like", "Everyone", "loves", "to", "tell", "you", "what", "you", "can", "and", "can't", "do", "especially", "with", "a", "kid", "but", "ultimately", "whatever", "you're", "considering", "doing", "or", "giving", "up", "the", "choice", "is", "yours"]}, {"character": "Ashley", "dialog": " It's not exactly what you might think it is.", "dialogSplit": ["It's", "not", "exactly", "what", "you", "might", "think", "it", "is"]}, {"character": "Emma", "dialog": " It never is. People are going to tell you who you are your whole life. You just gotta punch back and say, \"No, this is who I am.\" You want people to look at you differently? Make them. You want to change things you are going to have to go out there and change them yourself because there are no Fairy Godmothers in this world.", "dialogSplit": ["It", "never", "is", "People", "are", "going", "to", "tell", "you", "who", "you", "are", "your", "whole", "life", "You", "just", "gotta", "punch", "back", "and", "say", "No", "this", "is", "who", "I", "am", "You", "want", "people", "to", "look", "at", "you", "differently", "Make", "them", "You", "want", "to", "change", "things", "you", "are", "going", "to", "have", "to", "go", "out", "there", "and", "change", "them", "yourself", "because", "there", "are", "no", "Fairy", "Godmothers", "in", "this", "world"]}]}, {"sceneDesc": "Storybrooke. Present. Mr. Gold's Shop - Night. Mr. Gold walks up to his shop door and changes the sign from open to closed, shuts the lights off, and exits the shop locking the door behind him. After he is away from the shop, Ashley appears. She approaches the front door of the shop and bashes in the bottom left window pane of the door with a brick, and enters the store. She approaches a painting on the wall, which she reveals was covering a safe.", "tense": "Present", "location": "Storybrooke", "dialog": [{"character": "Mr. Gold", "dialog": " Ashley, what are you doing?", "dialogSplit": ["Ashley", "what", "are", "you", "doing"]}, {"character": "Ashley", "dialog": " Changing my life. ", "dialogSplit": ["Changing", "my", "life"]}, {"character": "Mr. Gold", "dialog": " Aaah! ", "dialogSplit": ["Aaah"]}]}, {"sceneDesc": "Storybrooke. Present. Mills House - Day. Dining Room / Foyer - Day. Regina prepares her makeup in a mirror.", "tense": "Present", "location": "Storybrooke", "dialog": [{"character": "Regina", "dialog": " I know you think otherwise, but I don't enjoy these Saturday city council meetings. Sometimes they're just unavoidable. Now, you know the rules?", "dialogSplit": ["I", "know", "you", "think", "otherwise", "but", "I", "don't", "enjoy", "these", "Saturday", "city", "council", "meetings", "Sometimes", "they're", "just", "unavoidable", "Now", "you", "know", "the", "rules"]}, {"character": "Henry", "dialog": " Yes on homework, no on TV, and stay inside.", "dialogSplit": ["Yes", "on", "homework", "no", "on", "TV", "and", "stay", "inside"]}, {"character": "Regina", "dialog": " Good boy. Under no circumstance do you leave this house.", "dialogSplit": ["Good", "boy", "Under", "no", "circumstance", "do", "you", "leave", "this", "house"]}, {"character": "Henry", "dialog": " You mean don't see my mom.", "dialogSplit": ["You", "mean", "don't", "see", "my", "mom"]}, {"character": "Regina", "dialog": " She's not your mother. She's just a woman passing through. Now do as I say or there will be consequences. I'll be back at 5:00 sharp. ", "dialogSplit": ["She's", "not", "your", "mother", "She's", "just", "a", "woman", "passing", "through", "Now", "do", "as", "I", "say", "or", "there", "will", "be", "consequences", "I'll", "be", "back", "at", "5", "00", "sharp"]}]}, {"sceneDesc": "Storybrooke - Present. The Blanchard loft - Day. Mary Margaret Blanchard is bringing a plate of food to Emma who is unpacking her recently arrived belongings.", "tense": "Present", "location": "Storybrooke", "dialog": [{"character": "Emma", "dialog": " I'm so glad my stuff is here. Oh, thanks. ", "dialogSplit": ["I'm", "so", "glad", "my", "stuff", "is", "here", "Oh", "thanks"]}, {"character": "Mary Margaret", "dialog": " So that is all your stuff?", "dialogSplit": ["So", "that", "is", "all", "your", "stuff"]}, {"character": "Emma", "dialog": " What do you mean?", "dialogSplit": ["What", "do", "you", "mean"]}, {"character": "Mary Margaret", "dialog": " Is the rest in storage?", "dialogSplit": ["Is", "the", "rest", "in", "storage"]}, {"character": "Emma", "dialog": " No, this is all of it. I'm not sentimental.", "dialogSplit": ["No", "this", "is", "all", "of", "it", "I'm", "not", "sentimental"]}, {"character": "Mary Margaret", "dialog": " Well, it must make things easier when you have to move. .", "dialogSplit": ["Well", "it", "must", "make", "things", "easier", "when", "you", "have", "to", "move"]}, {"character": "Mr. Gold", "dialog": " Ms. Blanchard, is Ms. Swan here?  Hi, my name is MrGold, we met briefly on your arrival.", "dialogSplit": ["Ms", "Blanchard", "is", "Ms", "Swan", "here", "Hi", "my", "name", "is", "MrGold", "we", "met", "briefly", "on", "your", "arrival"]}, {"character": "Emma", "dialog": " I remember.", "dialogSplit": ["I", "remember"]}, {"character": "Mr. Gold", "dialog": " Good, I have a proposition for you, Ms. Swan. I need your help. I'm looking for someone.", "dialogSplit": ["Good", "I", "have", "a", "proposition", "for", "you", "Ms", "Swan", "I", "need", "your", "help", "I'm", "looking", "for", "someone"]}, {"character": "Emma", "dialog": " Really? um...", "dialogSplit": ["Really", "um"]}, {"character": "Mary Margaret", "dialog": " You know what? I am going to jump in the bath. ", "dialogSplit": ["You", "know", "what", "I", "am", "going", "to", "jump", "in", "the", "bath"]}, {"character": "Mr. Gold", "dialog": " I have a photo.  Her name is Ashley Boyd and she's taken something quite valuable of mine.", "dialogSplit": ["I", "have", "a", "photo", "Her", "name", "is", "Ashley", "Boyd", "and", "she's", "taken", "something", "quite", "valuable", "of", "mine"]}, {"character": "Emma", "dialog": " So why don't you just call the police?", "dialogSplit": ["So", "why", "don't", "you", "just", "call", "the", "police"]}, {"character": "Mr. Gold", "dialog": " Because uh... she's a confused young woman. She's pregnant, alone, and scared. I don't want to ruin this young girl's life, but I just want my property returned.", "dialogSplit": ["Because", "uh", "she's", "a", "confused", "young", "woman", "She's", "pregnant", "alone", "and", "scared", "I", "don't", "want", "to", "ruin", "this", "young", "girl's", "life", "but", "I", "just", "want", "my", "property", "returned"]}, {"character": "Emma", "dialog": " And what is it?", "dialogSplit": ["And", "what", "is", "it"]}, {"character": "Mr. Gold", "dialog": " Well one of the advantages of you not being the police is discretion. Let's just say it's a precious object and leave it at that.", "dialogSplit": ["Well", "one", "of", "the", "advantages", "of", "you", "not", "being", "the", "police", "is", "discretion", "Let's", "just", "say", "it's", "a", "precious", "object", "and", "leave", "it", "at", "that"]}, {"character": "Emma", "dialog": " When did you see her last?", "dialogSplit": ["When", "did", "you", "see", "her", "last"]}, {"character": "Mr. Gold", "dialog": " Last night. That's how I got this.  It's so unlike her. She was quite wound up, rambling on and on about changing her life. I have not idea what got into her. Ms. Swan, please just help me find her. My only other choice is the police, and I don't think anyone wants to see that baby born in jail, now do they.", "dialogSplit": ["Last", "night", "That's", "how", "I", "got", "this", "It's", "so", "unlike", "her", "She", "was", "quite", "wound", "up", "rambling", "on", "and", "on", "about", "changing", "her", "life", "I", "have", "not", "idea", "what", "got", "into", "her", "Ms", "Swan", "please", "just", "help", "me", "find", "her", "My", "only", "other", "choice", "is", "the", "police", "and", "I", "don't", "think", "anyone", "wants", "to", "see", "that", "baby", "born", "in", "jail", "now", "do", "they"]}, {"character": "Emma", "dialog": " No, of course not.", "dialogSplit": ["No", "of", "course", "not"]}, {"character": "Mr. Gold", "dialog": " So you'll help me then?", "dialogSplit": ["So", "you'll", "help", "me", "then"]}, {"character": "Emma", "dialog": " I will help her", "dialogSplit": ["I", "will", "help", "her"]}, {"character": "Mr. Gold", "dialog": " Grand.", "dialogSplit": ["Grand"]}, {"character": "Henry", "dialog": " Hey Emma, I was thinking we...", "dialogSplit": ["Hey", "Emma", "I", "was", "thinking", "we"]}, {"character": "Mr. Gold", "dialog": " Hey Henry, how are you?", "dialogSplit": ["Hey", "Henry", "how", "are", "you"]}, {"character": "Henry", "dialog": " Okay.", "dialogSplit": ["Okay"]}, {"character": "Mr. Gold", "dialog": " Good. Give my regards to your mother, and um... good luck Ms. Swan. ", "dialogSplit": ["Good", "Give", "my", "regards", "to", "your", "mother", "and", "um", "good", "luck", "Ms", "Swan"]}, {"character": "Henry", "dialog": " Do you know who that is?", "dialogSplit": ["Do", "you", "know", "who", "that", "is"]}, {"character": "Emma", "dialog": " Yeah, of course I do.", "dialogSplit": ["Yeah", "of", "course", "I", "do"]}, {"character": "Henry", "dialog": " Who? Cause I'm still trying to figure it out.", "dialogSplit": ["Who", "Cause", "I'm", "still", "trying", "to", "figure", "it", "out"]}, {"character": "Emma", "dialog": " Oh, I meant in reality.", "dialogSplit": ["Oh", "I", "meant", "in", "reality"]}, {"character": "Henry", "dialog": " Is that all you brought?", "dialogSplit": ["Is", "that", "all", "you", "brought"]}, {"character": "Emma", "dialog": " Henry, what are you doing here?", "dialogSplit": ["Henry", "what", "are", "you", "doing", "here"]}, {"character": "Henry", "dialog": " My mom's gone till 5:00 I thought we could hang out.", "dialogSplit": ["My", "mom's", "gone", "till", "5", "00", "I", "thought", "we", "could", "hang", "out"]}, {"character": "Emma", "dialog": " Aw, kid I wish I could, but there's something I gotta do.", "dialogSplit": ["Aw", "kid", "I", "wish", "I", "could", "but", "there's", "something", "I", "gotta", "do"]}]}, {"sceneDesc": "Storybrooke. Present day. Emma and Henry walk down Main Street to Emma's car.", "tense": "Present", "location": "Storybrooke", "dialog": [{"character": "Henry", "dialog": " Please let me help.", "dialogSplit": ["Please", "let", "me", "help"]}, {"character": "Emma", "dialog": " No, no it could be dangerous.", "dialogSplit": ["No", "no", "it", "could", "be", "dangerous"]}, {"character": "Henry", "dialog": " The pregnant maid is dangerous?", "dialogSplit": ["The", "pregnant", "maid", "is", "dangerous"]}, {"character": "Emma", "dialog": " She assaulted MrGold.", "dialogSplit": ["She", "assaulted", "MrGold"]}, {"character": "Henry", "dialog": " Cool.", "dialogSplit": ["Cool"]}, {"character": "Emma", "dialog": " This isn't a game. She's desperate.", "dialogSplit": ["This", "isn't", "a", "game", "She's", "desperate"]}, {"character": "Henry", "dialog": " How do you know?", "dialogSplit": ["How", "do", "you", "know"]}, {"character": "Emma", "dialog": " Because I know.", "dialogSplit": ["Because", "I", "know"]}, {"character": "Henry", "dialog": " Well, then let's find her.", "dialogSplit": ["Well", "then", "let's", "find", "her"]}, {"character": "Emma", "dialog": " Oh no, no, no, no there is no \"let's\". You cannot come with me.", "dialogSplit": ["Oh", "no", "no", "no", "no", "there", "is", "no", "let's", "You", "cannot", "come", "with", "me"]}, {"character": "Henry", "dialog": " Then I'll look for her myself.", "dialogSplit": ["Then", "I'll", "look", "for", "her", "myself"]}, {"character": "Emma", "dialog": " Then I'll find you and I'll bring you back.", "dialogSplit": ["Then", "I'll", "find", "you", "and", "I'll", "bring", "you", "back"]}, {"character": "Henry", "dialog": " Then you wouldn't be helping the maid.", "dialogSplit": ["Then", "you", "wouldn't", "be", "helping", "the", "maid"]}, {"character": "Emma", "dialog": " I am just trying to be responsible here.", "dialogSplit": ["I", "am", "just", "trying", "to", "be", "responsible", "here"]}, {"character": "Henry", "dialog": " And I'm just trying to spend time with you. ", "dialogSplit": ["And", "I'm", "just", "trying", "to", "spend", "time", "with", "you"]}, {"character": "Emma", "dialog": " Oh, that is really not fair. ", "dialogSplit": ["Oh", "that", "is", "really", "not", "fair"]}, {"character": "Henry", "dialog": " So the maid, what's her story?", "dialogSplit": ["So", "the", "maid", "what's", "her", "story"]}]}, {"sceneDesc": "Enchanted Forest. Past. The King's Palace. Night.On her wedding night, Cinderella is viewing a fireworks display on the balcony, when Prince Thomas approaches her from behind.", "tense": "Past", "location": null, "dialog": [{"character": "Prince Thomas", "dialog": " What's wrong?", "dialogSplit": ["What's", "wrong"]}, {"character": "Cinderella", "dialog": " Nothing. Every year when I was growing up, I used to watch these fireworks from afar. And I knew what they meant. Something special was happening at the palace. Now they're for me, for our wedding. ", "dialogSplit": ["Nothing", "Every", "year", "when", "I", "was", "growing", "up", "I", "used", "to", "watch", "these", "fireworks", "from", "afar", "And", "I", "knew", "what", "they", "meant", "Something", "special", "was", "happening", "at", "the", "palace", "Now", "they're", "for", "me", "for", "our", "wedding"]}, {"character": "Cinderella", "dialog": " I'm so happy you could come.", "dialogSplit": ["I'm", "so", "happy", "you", "could", "come"]}, {"character": "The King", "dialog": " Son.", "dialogSplit": ["Son"]}, {"character": "Prince Thomas", "dialog": " Thank you, Father.", "dialogSplit": ["Thank", "you", "Father"]}, {"character": "Snow White", "dialog": " You look beautiful.", "dialogSplit": ["You", "look", "beautiful"]}, {"character": "The King", "dialog": " My dear Ella, we are thrilled to have you join our family, and I hope our family will soon be growing.", "dialogSplit": ["My", "dear", "Ella", "we", "are", "thrilled", "to", "have", "you", "join", "our", "family", "and", "I", "hope", "our", "family", "will", "soon", "be", "growing"]}, {"character": "Prince Charming", "dialog": " My darling.  Congratulations, Ella, you two are going to be very happy.", "dialogSplit": ["My", "darling", "Congratulations", "Ella", "you", "two", "are", "going", "to", "be", "very", "happy"]}, {"character": "Cinderella", "dialog": " Why thank you, James. ", "dialogSplit": ["Why", "thank", "you", "James"]}, {"character": "Snow White", "dialog": " Ella dear,  this is truly a night for celebration. Do you realize what an inspiration you are to everyone?", "dialogSplit": ["Ella", "dear", "this", "is", "truly", "a", "night", "for", "celebration", "Do", "you", "realize", "what", "an", "inspiration", "you", "are", "to", "everyone"]}, {"character": "Cinderella", "dialog": " All I did was get married.", "dialogSplit": ["All", "I", "did", "was", "get", "married"]}, {"character": "Snow White", "dialog": " All you did was show that anyone can change her life. I'm proud of you. ", "dialogSplit": ["All", "you", "did", "was", "show", "that", "anyone", "can", "change", "her", "life", "I'm", "proud", "of", "you"]}, {"character": "Rumplestiltskin", "dialog": " I'm proud of you, too.", "dialogSplit": ["I'm", "proud", "of", "you", "too"]}, {"character": "Cinderella", "dialog": " You. What are you doing here?", "dialogSplit": ["You", "What", "are", "you", "doing", "here"]}, {"character": "Rumplestiltskin", "dialog": " I just wanted to make sure you were happy with your end of the bargain. You know, true love, riches, happy endings. Did you get everything you desired?", "dialogSplit": ["I", "just", "wanted", "to", "make", "sure", "you", "were", "happy", "with", "your", "end", "of", "the", "bargain", "You", "know", "true", "love", "riches", "happy", "endings", "Did", "you", "get", "everything", "you", "desired"]}, {"character": "Cinderella", "dialog": " Yes. Yes, I did now what do you want? What's your price, my jewels? The ring?", "dialogSplit": ["Yes", "Yes", "I", "did", "now", "what", "do", "you", "want", "What's", "your", "price", "my", "jewels", "The", "ring"]}, {"character": "Rumplestiltskin", "dialog": " No, no, dear keep your baubles. What I want is something you don't yet possess, but something I know is coming: your firstborn. ", "dialogSplit": ["No", "no", "dear", "keep", "your", "baubles", "What", "I", "want", "is", "something", "you", "don't", "yet", "possess", "but", "something", "I", "know", "is", "coming", "your", "firstborn"]}]}, {"sceneDesc": "Enchanted Forest. Past. The King's Palace - Night. Cinderella's chambers.A thunderstorm rolls outside as Cinderella packs her things. Prince Thomas enters.", "tense": "Past", "location": null, "dialog": [{"character": "Prince Thomas", "dialog": " What are you doing?", "dialogSplit": ["What", "are", "you", "doing"]}, {"character": "Cinderella", "dialog": " I thought you were hunting.", "dialogSplit": ["I", "thought", "you", "were", "hunting"]}, {"character": "Prince Thomas", "dialog": " I was, but the weather wasn't agreeing so we came back early. Are we going somewhere? You're going somewhere.", "dialogSplit": ["I", "was", "but", "the", "weather", "wasn't", "agreeing", "so", "we", "came", "back", "early", "Are", "we", "going", "somewhere", "You're", "going", "somewhere"]}, {"character": "Cinderella", "dialog": " Something's happened.", "dialogSplit": ["Something's", "happened"]}, {"character": "Prince Thomas", "dialog": " What?", "dialogSplit": ["What"]}, {"character": "Cinderella", "dialog": " I'm pregnant.", "dialogSplit": ["I'm", "pregnant"]}, {"character": "Prince Thomas", "dialog": " Ella, that's wonderful. Why are you upset? This is what we wanted.", "dialogSplit": ["Ella", "that's", "wonderful", "Why", "are", "you", "upset", "This", "is", "what", "we", "wanted"]}, {"character": "Cinderella", "dialog": " There's something else. When we met that night at the ball, it wasn't my Fairy Godmother who sent me. It was Rumplestiltskin. I made a deal with him for this life. I was stupid. I didn't understand the price of magic. So I promised him something.", "dialogSplit": ["There's", "something", "else", "When", "we", "met", "that", "night", "at", "the", "ball", "it", "wasn't", "my", "Fairy", "Godmother", "who", "sent", "me", "It", "was", "Rumplestiltskin", "I", "made", "a", "deal", "with", "him", "for", "this", "life", "I", "was", "stupid", "I", "didn't", "understand", "the", "price", "of", "magic", "So", "I", "promised", "him", "something"]}, {"character": "Prince Thomas", "dialog": " What did you promise him?", "dialogSplit": ["What", "did", "you", "promise", "him"]}, {"character": "Cinderella", "dialog": " He tricked me. I thought that he'd want our gold or jewels...", "dialogSplit": ["He", "tricked", "me", "I", "thought", "that", "he'd", "want", "our", "gold", "or", "jewels"]}, {"character": "Prince Thomas", "dialog": " What was it?  Our baby?", "dialogSplit": ["What", "was", "it", "Our", "baby"]}, {"character": "Cinderella", "dialog": " I'm so sorry. And now I'm gonna lose it all, my...my life, you.", "dialogSplit": ["I'm", "so", "sorry", "And", "now", "I'm", "gonna", "lose", "it", "all", "my", "my", "life", "you"]}, {"character": "Prince Thomas", "dialog": " No. I don't care what that imp said. Magic may have brought us together but it didn't create this love.", "dialogSplit": ["No", "I", "don't", "care", "what", "that", "imp", "said", "Magic", "may", "have", "brought", "us", "together", "but", "it", "didn't", "create", "this", "love"]}, {"character": "Cinderella", "dialog": " But I made a deal. I can't break that. He's too powerful.", "dialogSplit": ["But", "I", "made", "a", "deal", "I", "can't", "break", "that", "He's", "too", "powerful"]}, {"character": "Prince Thomas", "dialog": " Then the answer is simple. We make another deal.", "dialogSplit": ["Then", "the", "answer", "is", "simple", "We", "make", "another", "deal"]}]}, {"sceneDesc": "Storybrooke - Present. Outside Granny's Diner - Day.Emma and Henry question Ruby about Ashley's disappearance. A tow truck is on Main Street putting down Ruby's car slowly.", "tense": "Present", "location": "Storybrooke", "dialog": [{"character": "Emma", "dialog": " So, this boyfriend of hers, you don't think he was involved in her disappearance?", "dialogSplit": ["So", "this", "boyfriend", "of", "hers", "you", "don't", "think", "he", "was", "involved", "in", "her", "disappearance"]}, {"character": "Ruby", "dialog": " Uh, that would mean that he was involved with her at all, which he isn't. He left her in the lurch right after they found out they were expecting. Hasn't spoken to her since. Like I said he's a...  Hey, hey, hey Billy, be careful. You almost shattered my wolf thing, Billy. It's good luck.", "dialogSplit": ["Uh", "that", "would", "mean", "that", "he", "was", "involved", "with", "her", "at", "all", "which", "he", "isn't", "He", "left", "her", "in", "the", "lurch", "right", "after", "they", "found", "out", "they", "were", "expecting", "Hasn't", "spoken", "to", "her", "since", "Like", "I", "said", "he's", "a", "Hey", "hey", "hey", "Billy", "be", "careful", "You", "almost", "shattered", "my", "wolf", "thing", "Billy", "It's", "good", "luck"]}, {"character": "Billy", "dialog": " I'm sorry Ruby, but look, it's fine.", "dialogSplit": ["I'm", "sorry", "Ruby", "but", "look", "it's", "fine"]}, {"character": "Emma", "dialog": " Um, Ruby what about her family?", "dialogSplit": ["Um", "Ruby", "what", "about", "her", "family"]}, {"character": "Ruby", "dialog": " Oh, um she's got a stepmom and two stepsisters that she doesn't talk to.", "dialogSplit": ["Oh", "um", "she's", "got", "a", "stepmom", "and", "two", "stepsisters", "that", "she", "doesn't", "talk", "to"]}, {"character": "Henry", "dialog": " Wait, stepmom, stepsisters, and she's a maid?", "dialogSplit": ["Wait", "stepmom", "stepsisters", "and", "she's", "a", "maid"]}, {"character": "Emma", "dialog": " Henry, not now.", "dialogSplit": ["Henry", "not", "now"]}, {"character": "Ruby", "dialog": " Look, I don't know what you've heard, but it's wrong. Everyone thinks she's not ready to have this kid, but she's trying, taking night classes, trying to better herself, trying to get her life together. Can you understand that?", "dialogSplit": ["Look", "I", "don't", "know", "what", "you've", "heard", "but", "it's", "wrong", "Everyone", "thinks", "she's", "not", "ready", "to", "have", "this", "kid", "but", "she's", "trying", "taking", "night", "classes", "trying", "to", "better", "herself", "trying", "to", "get", "her", "life", "together", "Can", "you", "understand", "that"]}, {"character": "Emma", "dialog": " I think so.", "dialogSplit": ["I", "think", "so"]}, {"character": "Ruby", "dialog": " Then maybe you should just stay out of it. She's been through enough already.", "dialogSplit": ["Then", "maybe", "you", "should", "just", "stay", "out", "of", "it", "She's", "been", "through", "enough", "already"]}, {"character": "Emma", "dialog": " I've been through it, too, Ruby, and I can help her.", "dialogSplit": ["I've", "been", "through", "it", "too", "Ruby", "and", "I", "can", "help", "her"]}, {"character": "Ruby", "dialog": " Then try her ex.", "dialogSplit": ["Then", "try", "her", "ex"]}, {"character": "Emma", "dialog": " Where can I find him?", "dialogSplit": ["Where", "can", "I", "find", "him"]}, {"character": "Ruby", "dialog": " He lives with his dad.", "dialogSplit": ["He", "lives", "with", "his", "dad"]}]}, {"sceneDesc": "Storybrooke. Present.  The Herman residence - Day.A car is pulling into the garage. Emma is knocking on the front door. Sean Herman answers. ", "tense": "Present", "location": "Storybrooke", "dialog": [{"character": "Sean", "dialog": " Can I help you?", "dialogSplit": ["Can", "I", "help", "you"]}, {"character": "Emma", "dialog": " Sean Herman?", "dialogSplit": ["Sean", "Herman"]}, {"character": "Sean", "dialog": " Yeah. Who are you?", "dialogSplit": ["Yeah", "Who", "are", "you"]}, {"character": "Emma", "dialog": " I'm Emma Swan. I'm... I'm looking for Ashley Boyd. She's in trouble. I just thought maybe she came to see you ", "dialogSplit": ["I'm", "Emma", "Swan", "I'm", "I'm", "looking", "for", "Ashley", "Boyd", "She's", "in", "trouble", "I", "just", "thought", "maybe", "she", "came", "to", "see", "you"]}, {"character": "Mitchell", "dialog": " My son doesn't have anything to do with that girl anymore, so whatever trouble she's in, I am sorry for, but there's nothing we can do to help you.", "dialogSplit": ["My", "son", "doesn't", "have", "anything", "to", "do", "with", "that", "girl", "anymore", "so", "whatever", "trouble", "she's", "in", "I", "am", "sorry", "for", "but", "there's", "nothing", "we", "can", "do", "to", "help", "you"]}, {"character": "Emma", "dialog": " You're the reason he broke up with her.", "dialogSplit": ["You're", "the", "reason", "he", "broke", "up", "with", "her"]}, {"character": "Mitchell", "dialog": " Absolutely. I'm not gonna let my son throw away his entire life over a mistake.", "dialogSplit": ["Absolutely", "I'm", "not", "gonna", "let", "my", "son", "throw", "away", "his", "entire", "life", "over", "a", "mistake"]}, {"character": "Emma", "dialog": " So you just told him to leave her?", "dialogSplit": ["So", "you", "just", "told", "him", "to", "leave", "her"]}, {"character": "Mitchell", "dialog": " Well what are they going to do, raise the child in the backseat of a car?", "dialogSplit": ["Well", "what", "are", "they", "going", "to", "do", "raise", "the", "child", "in", "the", "backseat", "of", "a", "car"]}, {"character": "Emma", "dialog": " Some people only have the backseat of a car.", "dialogSplit": ["Some", "people", "only", "have", "the", "backseat", "of", "a", "car"]}, {"character": "Mitchell", "dialog": " Well, they're to be pitied. I'm not letting that happen to my son. ", "dialogSplit": ["Well", "they're", "to", "be", "pitied", "I'm", "not", "letting", "that", "happen", "to", "my", "son"]}, {"character": "Sean", "dialog": " Dad, maybe we should help her look.", "dialogSplit": ["Dad", "maybe", "we", "should", "help", "her", "look"]}, {"character": "Mitchell", "dialog": " It's a waste, Sean.", "dialogSplit": ["It's", "a", "waste", "Sean"]}, {"character": "Emma", "dialog": " Sean, if you want to come, come. Stop letting other people make decisions for you. If Ashley runs away with this baby, she's gonna be in some serious trouble.", "dialogSplit": ["Sean", "if", "you", "want", "to", "come", "come", "Stop", "letting", "other", "people", "make", "decisions", "for", "you", "If", "Ashley", "runs", "away", "with", "this", "baby", "she's", "gonna", "be", "in", "some", "serious", "trouble"]}, {"character": "Sean", "dialog": " She's running away with the baby?", "dialogSplit": ["She's", "running", "away", "with", "the", "baby"]}, {"character": "Emma", "dialog": " Yes.", "dialogSplit": ["Yes"]}, {"character": "Mitchell", "dialog": " Sean, inside. Now.  Look, believe me if I knew where she was I would tell you. I went to a lot of trouble to get her that deal.", "dialogSplit": ["Sean", "inside", "Now", "Look", "believe", "me", "if", "I", "knew", "where", "she", "was", "I", "would", "tell", "you", "I", "went", "to", "a", "lot", "of", "trouble", "to", "get", "her", "that", "deal"]}, {"character": "Emma", "dialog": " Deal? What are you talking about?", "dialogSplit": ["Deal", "What", "are", "you", "talking", "about"]}, {"character": "Mitchell", "dialog": " You don't know? Ashley agreed to give up the child. And she's being paid very well to do so.", "dialogSplit": ["You", "don't", "know", "Ashley", "agreed", "to", "give", "up", "the", "child", "And", "she's", "being", "paid", "very", "well", "to", "do", "so"]}, {"character": "Emma", "dialog": " She sold the baby?", "dialogSplit": ["She", "sold", "the", "baby"]}, {"character": "Mitchell", "dialog": " Oh, you make it sound so crass. I found someone who's going to find that child a good a proper home.", "dialogSplit": ["Oh", "you", "make", "it", "sound", "so", "crass", "I", "found", "someone", "who's", "going", "to", "find", "that", "child", "a", "good", "a", "proper", "home"]}, {"character": "Emma", "dialog": " And who are you to judge whether Ashley is capable of providing that?", "dialogSplit": ["And", "who", "are", "you", "to", "judge", "whether", "Ashley", "is", "capable", "of", "providing", "that"]}, {"character": "Mitchell", "dialog": " Look at her, she's a teenager, and she's never shown any evidence of being responsible. How could she possibly know how to be a mother?", "dialogSplit": ["Look", "at", "her", "she's", "a", "teenager", "and", "she's", "never", "shown", "any", "evidence", "of", "being", "responsible", "How", "could", "she", "possibly", "know", "how", "to", "be", "a", "mother"]}, {"character": "Emma", "dialog": " Maybe she's changing her life.", "dialogSplit": ["Maybe", "she's", "changing", "her", "life"]}, {"character": "Mitchell", "dialog": " Everybody says that. Now look, I found someone who's going to pay Ashley extremely well, someone who is going to see to it that everybody's happy.", "dialogSplit": ["Everybody", "says", "that", "Now", "look", "I", "found", "someone", "who's", "going", "to", "pay", "Ashley", "extremely", "well", "someone", "who", "is", "going", "to", "see", "to", "it", "that", "everybody's", "happy"]}, {"character": "Emma", "dialog": " MrGold.", "dialogSplit": ["MrGold"]}, {"character": "Mitchell", "dialog": " Well, isn't that why you were hired, to bring him the baby?", "dialogSplit": ["Well", "isn't", "that", "why", "you", "were", "hired", "to", "bring", "him", "the", "baby"]}]}, {"sceneDesc": "Storybrooke - Present. Main Street - Day.Emma and Henry are driving in her car.", "tense": "Present", "location": "Storybrooke", "dialog": [{"character": "Henry", "dialog": " You can't make her double-cross Gold. No one's ever broken a deal with him.", "dialogSplit": ["You", "can't", "make", "her", "double", "cross", "Gold", "No", "one's", "ever", "broken", "a", "deal", "with", "him"]}, {"character": "Emma", "dialog": " Happy to be the first. If Ashley wants to have this baby, she should have it. Anyone who wants to be a mother should damn well be allowed to be one. ", "dialogSplit": ["Happy", "to", "be", "the", "first", "If", "Ashley", "wants", "to", "have", "this", "baby", "she", "should", "have", "it", "Anyone", "who", "wants", "to", "be", "a", "mother", "should", "damn", "well", "be", "allowed", "to", "be", "one"]}]}, {"sceneDesc": "Storybrooke - Present. Granny's Diner - Day.Emma and Henry enter. Ruby stands at the counter.", "tense": "Present", "location": "Storybrooke", "dialog": [{"character": "Emma", "dialog": " Why didn't you tell me she sold the baby?", "dialogSplit": ["Why", "didn't", "you", "tell", "me", "she", "sold", "the", "baby"]}, {"character": "Ruby", "dialog": " Because I didn't think it was important.", "dialogSplit": ["Because", "I", "didn't", "think", "it", "was", "important"]}, {"character": "Emma", "dialog": " Really, considering that's why she's running away?", "dialogSplit": ["Really", "considering", "that's", "why", "she's", "running", "away"]}, {"character": "Ruby", "dialog": " Look, Ashley's my friend. I don't like the idea of people judging her.", "dialogSplit": ["Look", "Ashley's", "my", "friend", "I", "don't", "like", "the", "idea", "of", "people", "judging", "her"]}, {"character": "Emma", "dialog": " Ruby, where's your car? You didn't send me to Sean to find her, you sent me there to give her a head start.", "dialogSplit": ["Ruby", "where's", "your", "car", "You", "didn't", "send", "me", "to", "Sean", "to", "find", "her", "you", "sent", "me", "there", "to", "give", "her", "a", "head", "start"]}, {"character": "Ruby", "dialog": " Look, I'm only trying to help her.", "dialogSplit": ["Look", "I'm", "only", "trying", "to", "help", "her"]}, {"character": "Emma", "dialog": " Yeah, so am I. Ashley's in more trouble than you know, Ruby. Where is she? Don't make her deal with Gold without me.", "dialogSplit": ["Yeah", "so", "am", "I", "Ashley's", "in", "more", "trouble", "than", "you", "know", "Ruby", "Where", "is", "she", "Don't", "make", "her", "deal", "with", "Gold", "without", "me"]}, {"character": "Ruby", "dialog": " I can't talk in front of him. He's the mayor's kid.", "dialogSplit": ["I", "can't", "talk", "in", "front", "of", "him", "He's", "the", "mayor's", "kid"]}, {"character": "Henry", "dialog": " Hey, I'm on your side.", "dialogSplit": ["Hey", "I'm", "on", "your", "side"]}, {"character": "Emma", "dialog": " Henry, I need to find this woman, and in order to do that, I need you to go home, okay? So please listen to me, seriously. She's not gonna tell me anything if you're around.", "dialogSplit": ["Henry", "I", "need", "to", "find", "this", "woman", "and", "in", "order", "to", "do", "that", "I", "need", "you", "to", "go", "home", "okay", "So", "please", "listen", "to", "me", "seriously", "She's", "not", "gonna", "tell", "me", "anything", "if", "you're", "around"]}, {"character": "Henry", "dialog": " Okay.", "dialogSplit": ["Okay"]}, {"character": "Emma", "dialog": " Thank you. ", "dialogSplit": ["Thank", "you"]}, {"character": "Ruby", "dialog": " She left town. Said she was gonna try Boston. Thought she could disappear there.", "dialogSplit": ["She", "left", "town", "Said", "she", "was", "gonna", "try", "Boston", "Thought", "she", "could", "disappear", "there"]}, {"character": "Emma", "dialog": " How long ago did she leave?", "dialogSplit": ["How", "long", "ago", "did", "she", "leave"]}, {"character": "Ruby", "dialog": " About a half an hour.", "dialogSplit": ["About", "a", "half", "an", "hour"]}]}, {"sceneDesc": "Storybrooke - Present. Granny's Diner - Day.Emma and Henry enter. Ruby stands at the counter.", "tense": "Present", "location": "Storybrooke", "dialog": [{"character": "", "dialog": "Emma exits.", "dialogSplit": ["Emma", "exits"]}]}, {"sceneDesc": "Storybrooke. Present day. Emma's Bug. Emma believes she is alone driving to Boston to look for Ashley. Henry sits up in the back seat.", "tense": "Present", "location": "Storybrooke", "dialog": [{"character": "Henry", "dialog": " What did she tell you?", "dialogSplit": ["What", "did", "she", "tell", "you"]}, {"character": "Emma", "dialog": " Henry! What the hell? I am going to Boston, you can't come with me.", "dialogSplit": ["Henry", "What", "the", "hell", "I", "am", "going", "to", "Boston", "you", "can't", "come", "with", "me"]}, {"character": "Henry", "dialog": " You can't go to Boston, she can't leave! Bad things happen to anyone that does.", "dialogSplit": ["You", "can't", "go", "to", "Boston", "she", "can't", "leave", "Bad", "things", "happen", "to", "anyone", "that", "does"]}, {"character": "Emma", "dialog": " I don't have time to argue with you over the curse. I've got to get you home.", "dialogSplit": ["I", "don't", "have", "time", "to", "argue", "with", "you", "over", "the", "curse", "I've", "got", "to", "get", "you", "home"]}, {"character": "Henry", "dialog": " We have to stop her before she gets hurt. We're wasting time. If you drop me off, you'll never catch up to her.", "dialogSplit": ["We", "have", "to", "stop", "her", "before", "she", "gets", "hurt", "We're", "wasting", "time", "If", "you", "drop", "me", "off", "you'll", "never", "catch", "up", "to", "her"]}, {"character": "Emma", "dialog": " Henry...", "dialogSplit": ["Henry"]}, {"character": "Henry", "dialog": " And then MrGold will call the police, and he'll have her sent to jail.", "dialogSplit": ["And", "then", "MrGold", "will", "call", "the", "police", "and", "he'll", "have", "her", "sent", "to", "jail"]}, {"character": "Emma", "dialog": " Buckle up. Ashley, what did you get yourself into?", "dialogSplit": ["Buckle", "up", "Ashley", "what", "did", "you", "get", "yourself", "into"]}]}, {"sceneDesc": "Enchanted Forest. Past. Grumpy, Prince Thomas, Prince Charming, and Cinderella enter the Dwarves' Mines.", "tense": "Past", "location": null, "dialog": [{"character": "Cinderella", "dialog": " Why are we down here?", "dialogSplit": ["Why", "are", "we", "down", "here"]}, {"character": "Prince Thomas", "dialog": " We need a place to keep him.", "dialogSplit": ["We", "need", "a", "place", "to", "keep", "him"]}, {"character": "Prince Charming", "dialog": " Rumplestiltskin is the most dangerous man in all the realms. He needs his own special prison, so we converted the mines to hold him.", "dialogSplit": ["Rumplestiltskin", "is", "the", "most", "dangerous", "man", "in", "all", "the", "realms", "He", "needs", "his", "own", "special", "prison", "so", "we", "converted", "the", "mines", "to", "hold", "him"]}, {"character": "Cinderella", "dialog": " But how will we get him here? He has eluded all forever.", "dialogSplit": ["But", "how", "will", "we", "get", "him", "here", "He", "has", "eluded", "all", "forever"]}, {"character": "Grumpy", "dialog": " His strength is also his weakness. His deals. He can't resist making them, and we already know who he wants to deal with next, you.", "dialogSplit": ["His", "strength", "is", "also", "his", "weakness", "His", "deals", "He", "can't", "resist", "making", "them", "and", "we", "already", "know", "who", "he", "wants", "to", "deal", "with", "next", "you"]}, {"character": "Prince Charming", "dialog": " We've sent word with one of Snow's bluebirds. He's accepted a meeting with you. You're going to tell him that Doc heard something with his stethoscope, two heartbeats.", "dialogSplit": ["We've", "sent", "word", "with", "one", "of", "Snow's", "bluebirds", "He's", "accepted", "a", "meeting", "with", "you", "You're", "going", "to", "tell", "him", "that", "Doc", "heard", "something", "with", "his", "stethoscope", "two", "heartbeats"]}, {"character": "Prince Thomas", "dialog": " You're going to tell him it's twins.", "dialogSplit": ["You're", "going", "to", "tell", "him", "it's", "twins"]}, {"character": "Prince Charming", "dialog": " And if he wants both, which he will, you propose a new deal. Grumpy... .", "dialogSplit": ["And", "if", "he", "wants", "both", "which", "he", "will", "you", "propose", "a", "new", "deal", "Grumpy"]}, {"character": "Cinderella", "dialog": " A quill, I... I don't understand.", "dialogSplit": ["A", "quill", "I", "I", "don't", "understand"]}, {"character": "Grumpy", "dialog": " The Blue Fairy cast a spell on it. Whoever signs with this will be frozen, their magic made impotent.", "dialogSplit": ["The", "Blue", "Fairy", "cast", "a", "spell", "on", "it", "Whoever", "signs", "with", "this", "will", "be", "frozen", "their", "magic", "made", "impotent"]}, {"character": "Prince Charming", "dialog": " All you must do is get him to sign the contract. Ella, this man is a scourge. You will be doing the entire land a service.", "dialogSplit": ["All", "you", "must", "do", "is", "get", "him", "to", "sign", "the", "contract", "Ella", "this", "man", "is", "a", "scourge", "You", "will", "be", "doing", "the", "entire", "land", "a", "service"]}, {"character": "Cinderella", "dialog": " Should we even use magic? Isn't that what's has causing these problems to begin with? What if this magic also has a price?", "dialogSplit": ["Should", "we", "even", "use", "magic", "Isn't", "that", "what's", "has", "causing", "these", "problems", "to", "begin", "with", "What", "if", "this", "magic", "also", "has", "a", "price"]}, {"character": "Prince Thomas", "dialog": " Then I will pay it. I will do whatever is needed to save you and our child.", "dialogSplit": ["Then", "I", "will", "pay", "it", "I", "will", "do", "whatever", "is", "needed", "to", "save", "you", "and", "our", "child"]}, {"character": "Prince Charming", "dialog": " Let's go. ", "dialogSplit": ["Let's", "go"]}, {"character": "Grumpy", "dialog": " I hope you like it. A lot of dwarf blood went into it.", "dialogSplit": ["I", "hope", "you", "like", "it", "A", "lot", "of", "dwarf", "blood", "went", "into", "it"]}, {"character": "Cinderella", "dialog": " You sure this will work?", "dialogSplit": ["You", "sure", "this", "will", "work"]}, {"character": "Prince Charming", "dialog": " Once he is in there he'll never get out. You'll be safe.", "dialogSplit": ["Once", "he", "is", "in", "there", "he'll", "never", "get", "out", "You'll", "be", "safe"]}, {"character": "Prince Thomas", "dialog": " We can do this, Ella.", "dialogSplit": ["We", "can", "do", "this", "Ella"]}, {"character": "Cinderella", "dialog": " Okay. Let's get him.", "dialogSplit": ["Okay", "Let's", "get", "him"]}]}, {"sceneDesc": "Storybrooke. Present day. Emma and Henry are still driving.", "tense": "Present", "location": "Storybrooke", "dialog": [{"character": "Henry", "dialog": " I told you. It's her car. ", "dialogSplit": ["I", "told", "you", "It's", "her", "car"]}, {"character": "Emma", "dialog": " Ashley? ", "dialogSplit": ["Ashley"]}, {"character": "Ashley", "dialog": " Aaah!  My baby. It's coming.", "dialogSplit": ["Aaah", "My", "baby", "It's", "coming"]}]}, {"sceneDesc": "Storybrooke. Present day. Emma and Henry are in Emma's car with Ashley about to give birth.", "tense": "Present", "location": "Storybrooke", "dialog": [{"character": "Henry", "dialog": " Is the baby really coming?", "dialogSplit": ["Is", "the", "baby", "really", "coming"]}, {"character": "Emma", "dialog": " Oh, yeah.  Don't worry. The hospital isn't that far.", "dialogSplit": ["Oh", "yeah", "Don't", "worry", "The", "hospital", "isn't", "that", "far"]}, {"character": "Ashley", "dialog": " No, no, no, no, take me to Boston. I can't go back there.", "dialogSplit": ["No", "no", "no", "no", "take", "me", "to", "Boston", "I", "can't", "go", "back", "there"]}, {"character": "Emma", "dialog": " Oh, no we don't have four hours, trust me. I know.", "dialogSplit": ["Oh", "no", "we", "don't", "have", "four", "hours", "trust", "me", "I", "know"]}, {"character": "Ashley", "dialog": " I can't go back there, please.  He's gonna take my baby.", "dialogSplit": ["I", "can't", "go", "back", "there", "please", "He's", "gonna", "take", "my", "baby"]}, {"character": "Emma", "dialog": " I won't let that happen, but do you know what you're asking for? If you keep this child are you really ready?", "dialogSplit": ["I", "won't", "let", "that", "happen", "but", "do", "you", "know", "what", "you're", "asking", "for", "If", "you", "keep", "this", "child", "are", "you", "really", "ready"]}, {"character": "Ashley", "dialog": " Yeah.", "dialogSplit": ["Yeah"]}, {"character": "Emma", "dialog": " Are you sure? Because I wasn't.", "dialogSplit": ["Are", "you", "sure", "Because", "I", "wasn't"]}, {"character": "Ashley", "dialog": " You weren't?", "dialogSplit": ["You", "weren't"]}, {"character": "Emma", "dialog": " Nope. If you want to give this kid its best chance, it's gonna be with someone who's ready, so know what that means. Your whole life is gonna change, and once you decide that it's yours, this running away can't happen. You have to grow up, and you can't ever leave. Understand?", "dialogSplit": ["Nope", "If", "you", "want", "to", "give", "this", "kid", "its", "best", "chance", "it's", "gonna", "be", "with", "someone", "who's", "ready", "so", "know", "what", "that", "means", "Your", "whole", "life", "is", "gonna", "change", "and", "once", "you", "decide", "that", "it's", "yours", "this", "running", "away", "can't", "happen", "You", "have", "to", "grow", "up", "and", "you", "can't", "ever", "leave", "Understand"]}, {"character": "Ashley", "dialog": " Yes. I want my baby.", "dialogSplit": ["Yes", "I", "want", "my", "baby"]}]}, {"sceneDesc": "Enchanted Forest. Past. The Palace Gardens. Night.A pregnant Cinderella stands waiting for Rumplestiltskin, who appears holding a small flask.", "tense": "Past", "location": null, "dialog": [{"character": "Rumplestiltskin", "dialog": " Well, well, well. You're starting to show. A little bird told me you wanted to speak.", "dialogSplit": ["Well", "well", "well", "You're", "starting", "to", "show", "A", "little", "bird", "told", "me", "you", "wanted", "to", "speak"]}, {"character": "Cinderella", "dialog": " Yes. I'd like to alter the bargain.", "dialogSplit": ["Yes", "I'd", "like", "to", "alter", "the", "bargain"]}, {"character": "Rumplestiltskin", "dialog": " That's not what I do.", "dialogSplit": ["That's", "not", "what", "I", "do"]}, {"character": "Cinderella", "dialog": " But I think you'll want to. I'm having twins. (He throws the flask away)", "dialogSplit": ["But", "I", "think", "you'll", "want", "to", "I'm", "having", "twins", "He", "throws", "the", "flask", "away"]}, {"character": "Rumplestiltskin", "dialog": " Is that so? Ooh, let's have a look. And you would, what, give up both? Why is that? I wonder.", "dialogSplit": ["Is", "that", "so", "Ooh", "let's", "have", "a", "look", "And", "you", "would", "what", "give", "up", "both", "Why", "is", "that", "I", "wonder"]}, {"character": "Cinderella", "dialog": " My husband... he's... he's having a hard time. Our kingdom is poor. We're losing money. Our crops are dying. We can't support ourselves or our people.", "dialogSplit": ["My", "husband", "he's", "he's", "having", "a", "hard", "time", "Our", "kingdom", "is", "poor", "We're", "losing", "money", "Our", "crops", "are", "dying", "We", "can't", "support", "ourselves", "or", "our", "people"]}, {"character": "Rumplestiltskin", "dialog": " And you would trade your other child for... comfort?", "dialogSplit": ["And", "you", "would", "trade", "your", "other", "child", "for", "comfort"]}, {"character": "Cinderella", "dialog": " I can always have more children, but I can't make crops grow where the soil is dead.  In exchange for our other child, you will see to it that our land is once again fertile. I think it's more than fair.", "dialogSplit": ["I", "can", "always", "have", "more", "children", "but", "I", "can't", "make", "crops", "grow", "where", "the", "soil", "is", "dead", "In", "exchange", "for", "our", "other", "child", "you", "will", "see", "to", "it", "that", "our", "land", "is", "once", "again", "fertile", "I", "think", "it's", "more", "than", "fair"]}, {"character": "Rumplestiltskin", "dialog": " Yes! Yes, yes. It is. If what you're saying is true.", "dialogSplit": ["Yes", "Yes", "yes", "It", "is", "If", "what", "you're", "saying", "is", "true"]}, {"character": "Cinderella", "dialog": " It is, and all you have to do is sign on the dotted line. ", "dialogSplit": ["It", "is", "and", "all", "you", "have", "to", "do", "is", "sign", "on", "the", "dotted", "line"]}, {"character": "Rumplestiltskin", "dialog": " What a lovely quill!  Wherever did you get it?", "dialogSplit": ["What", "a", "lovely", "quill", "Wherever", "did", "you", "get", "it"]}, {"character": "Cinderella", "dialog": " It's from our castle.", "dialogSplit": ["It's", "from", "our", "castle"]}, {"character": "Rumplestiltskin", "dialog": " You know, the only way to stop me is through magic.", "dialogSplit": ["You", "know", "the", "only", "way", "to", "stop", "me", "is", "through", "magic"]}, {"character": "Cinderella", "dialog": " I'm not trying to stop you.", "dialogSplit": ["I'm", "not", "trying", "to", "stop", "you"]}, {"character": "Rumplestiltskin", "dialog": " Of course you're not. Because as we all know, all magic comes with a price, and if you were to use it to say... imprison me, then your debt to me would only grow, and we wouldn't want that now, would we?", "dialogSplit": ["Of", "course", "you're", "not", "Because", "as", "we", "all", "know", "all", "magic", "comes", "with", "a", "price", "and", "if", "you", "were", "to", "use", "it", "to", "say", "imprison", "me", "then", "your", "debt", "to", "me", "would", "only", "grow", "and", "we", "wouldn't", "want", "that", "now", "would", "we"]}, {"character": "Cinderella", "dialog": " Just sign the contract please.", "dialogSplit": ["Just", "sign", "the", "contract", "please"]}, {"character": "Rumplestiltskin", "dialog": " Are you sure you're happy with this new arrangement?  Then so it shall be. ", "dialogSplit": ["Are", "you", "sure", "you're", "happy", "with", "this", "new", "arrangement", "Then", "so", "it", "shall", "be"]}, {"character": "Cinderella", "dialog": " Thomas!", "dialogSplit": ["Thomas"]}, {"character": "Rumplestiltskin", "dialog": " No one breaks deals with me, dearie. No one.  No matter where you are, no matter what land you find yourself in... I assure you I will have your baby.", "dialogSplit": ["No", "one", "breaks", "deals", "with", "me", "dearie", "No", "one", "No", "matter", "where", "you", "are", "no", "matter", "what", "land", "you", "find", "yourself", "in", "I", "assure", "you", "I", "will", "have", "your", "baby"]}]}, {"sceneDesc": "Storybrooke General Hospital. Present. Waiting Room. Day.Emma and Henry wait for the arrival of Ashley's baby.", "tense": "Present", "location": "Storybrooke", "dialog": [{"character": "Henry", "dialog": " You know Emma, you're different.", "dialogSplit": ["You", "know", "Emma", "you're", "different"]}, {"character": "Emma", "dialog": " What's that?", "dialogSplit": ["What's", "that"]}, {"character": "Henry", "dialog": " You're the only one who can do it.", "dialogSplit": ["You're", "the", "only", "one", "who", "can", "do", "it"]}, {"character": "Emma", "dialog": " Break the curse? Yes, I know. You keep telling me that.", "dialogSplit": ["Break", "the", "curse", "Yes", "I", "know", "You", "keep", "telling", "me", "that"]}, {"character": "Henry", "dialog": " No, leave. You're the only one who can leave Storybrooke.", "dialogSplit": ["No", "leave", "You're", "the", "only", "one", "who", "can", "leave", "Storybrooke"]}, {"character": "Emma", "dialog": " You left and came and found me in Boston.", "dialogSplit": ["You", "left", "and", "came", "and", "found", "me", "in", "Boston"]}, {"character": "Henry", "dialog": " But I came back. I'm ten. I had no choice, but if anyone else tried to go, bad things would happen.", "dialogSplit": ["But", "I", "came", "back", "I'm", "ten", "I", "had", "no", "choice", "but", "if", "anyone", "else", "tried", "to", "go", "bad", "things", "would", "happen"]}, {"character": "Emma", "dialog": " Anyone, except me?", "dialogSplit": ["Anyone", "except", "me"]}, {"character": "Henry", "dialog": " You're the savior. You can do whatever you want. You can go.", "dialogSplit": ["You're", "the", "savior", "You", "can", "do", "whatever", "you", "want", "You", "can", "go"]}, {"character": "Obstetrician", "dialog": " Ms. Swan, the baby is a healthy six-pound girl, and the mother is doing fine.", "dialogSplit": ["Ms", "Swan", "the", "baby", "is", "a", "healthy", "six", "pound", "girl", "and", "the", "mother", "is", "doing", "fine"]}, {"character": "Mr. Gold", "dialog": " What lovely news. Excellent work, Ms. Swan. Thank you for bringing me my merchandise.", "dialogSplit": ["What", "lovely", "news", "Excellent", "work", "Ms", "Swan", "Thank", "you", "for", "bringing", "me", "my", "merchandise"]}]}, {"sceneDesc": "Enchanted Forest. Past. The Palace Grounds - Night.Prince Charming and Grumpy place Rumplestiltskin in the armored carriage.", "tense": "Past", "location": null, "dialog": [{"character": "Cinderella", "dialog": " Did we really win?", "dialogSplit": ["Did", "we", "really", "win"]}, {"character": "Prince Thomas", "dialog": " Yes, I told you we would.", "dialogSplit": ["Yes", "I", "told", "you", "we", "would"]}, {"character": "Cinderella", "dialog": " I was so afraid. I was so afraid that we'd fail, that... I'd have to go back to that life, that... that terrible life. I was afraid I would lose you. And that nothing would have changed.", "dialogSplit": ["I", "was", "so", "afraid", "I", "was", "so", "afraid", "that", "we'd", "fail", "that", "I'd", "have", "to", "go", "back", "to", "that", "life", "that", "that", "terrible", "life", "I", "was", "afraid", "I", "would", "lose", "you", "And", "that", "nothing", "would", "have", "changed"]}, {"character": "Prince Thomas", "dialog": " As long as I am alive, you will never go back to that life.  Now... how is our little Alexandra?", "dialogSplit": ["As", "long", "as", "I", "am", "alive", "you", "will", "never", "go", "back", "to", "that", "life", "Now", "how", "is", "our", "little", "Alexandra"]}, {"character": "Cinderella", "dialog": " Alexandra?", "dialogSplit": ["Alexandra"]}, {"character": "Prince Thomas", "dialog": " Did I not mention that I picked out a name?", "dialogSplit": ["Did", "I", "not", "mention", "that", "I", "picked", "out", "a", "name"]}, {"character": "Cinderella", "dialog": " A name? That's more like a prison sentence.", "dialogSplit": ["A", "name", "That's", "more", "like", "a", "prison", "sentence"]}, {"character": "Prince Thomas", "dialog": " Well I like it.", "dialogSplit": ["Well", "I", "like", "it"]}, {"character": "Cinderella", "dialog": " Men, you really no nothing of ch...", "dialogSplit": ["Men", "you", "really", "no", "nothing", "of", "ch"]}, {"character": "Prince Thomas", "dialog": " Ella, what is it?", "dialogSplit": ["Ella", "what", "is", "it"]}, {"character": "Cinderella", "dialog": " Oh, it's... it's the baby. Something's wrong.", "dialogSplit": ["Oh", "it's", "it's", "the", "baby", "Something's", "wrong"]}, {"character": "Prince Thomas", "dialog": " No, no. It can't be; it's too soon. It must be the stress, the excitement.", "dialogSplit": ["No", "no", "It", "can't", "be", "it's", "too", "soon", "It", "must", "be", "the", "stress", "the", "excitement"]}, {"character": "Cinderella", "dialog": " Oh, I'm dizzy.", "dialogSplit": ["Oh", "I'm", "dizzy"]}, {"character": "Prince Thomas", "dialog": " Sit, sit. I'll go get you water.", "dialogSplit": ["Sit", "sit", "I'll", "go", "get", "you", "water"]}, {"character": "Cinderella", "dialog": " Okay.  Thomas, it's okay. It's passed. Thomas?  Thomas?!  What did you do?", "dialogSplit": ["Okay", "Thomas", "it's", "okay", "It's", "passed", "Thomas", "Thomas", "What", "did", "you", "do"]}, {"character": "Prince Charming", "dialog": " Ella, what's wrong?", "dialogSplit": ["Ella", "what's", "wrong"]}, {"character": "Grumpy", "dialog": " Your highness, what happened?", "dialogSplit": ["Your", "highness", "what", "happened"]}, {"character": "Cinderella", "dialog": " What did you do to my Thomas?", "dialogSplit": ["What", "did", "you", "do", "to", "my", "Thomas"]}, {"character": "Rumplestiltskin", "dialog": " I haven't done anything. In case you haven't noticed I've been otherwise engaged.", "dialogSplit": ["I", "haven't", "done", "anything", "In", "case", "you", "haven't", "noticed", "I've", "been", "otherwise", "engaged"]}, {"character": "Cinderella", "dialog": " Something's happened to him. You know. Tell me!", "dialogSplit": ["Something's", "happened", "to", "him", "You", "know", "Tell", "me"]}, {"character": "Rumplestiltskin", "dialog": " I have no idea, dearie, but I did warn you. All magic comes at a price. It looks like someone has just paid.", "dialogSplit": ["I", "have", "no", "idea", "dearie", "but", "I", "did", "warn", "you", "All", "magic", "comes", "at", "a", "price", "It", "looks", "like", "someone", "has", "just", "paid"]}, {"character": "Prince Charming", "dialog": " Don't listen to him, we'll find Thomas.", "dialogSplit": ["Don't", "listen", "to", "him", "we'll", "find", "Thomas"]}, {"character": "Rumplestiltskin", "dialog": " No, you won't. Until that debt is paid, until that baby is mine, you're never gonna see him again, in this world or the next Cinderella. I will have that baby.", "dialogSplit": ["No", "you", "won't", "Until", "that", "debt", "is", "paid", "until", "that", "baby", "is", "mine", "you're", "never", "gonna", "see", "him", "again", "in", "this", "world", "or", "the", "next", "Cinderella", "I", "will", "have", "that", "baby"]}]}, {"sceneDesc": "Storybrooke General Hospital. Present. Waiting Room. Day.Mr. Gold is standing at a coffee vending machine. He hits it and gets free coffee. Emma approaches him.", "tense": "Present", "location": "Storybrooke", "dialog": [{"character": "Mr. Gold", "dialog": " Well, well. Must be my lucky day. Care for a cup, Ms. Swan?", "dialogSplit": ["Well", "well", "Must", "be", "my", "lucky", "day", "Care", "for", "a", "cup", "Ms", "Swan"]}, {"character": "Emma", "dialog": " A baby? That's your merchandise? Why didn't you tell me?", "dialogSplit": ["A", "baby", "That's", "your", "merchandise", "Why", "didn't", "you", "tell", "me"]}, {"character": "Mr. Gold", "dialog": " Well, because at the time you didn't need to know.", "dialogSplit": ["Well", "because", "at", "the", "time", "you", "didn't", "need", "to", "know"]}, {"character": "Emma", "dialog": " Really, or you thought I wouldn't take the job?", "dialogSplit": ["Really", "or", "you", "thought", "I", "wouldn't", "take", "the", "job"]}, {"character": "Mr. Gold", "dialog": " On the contrary, I thought it would be more effective if you found out yourself. After seeing Ashley's hard life, I thought it would make sense... to you. I mean if anyone could understand the reasons behind giving up a baby, I assumed it would be you.", "dialogSplit": ["On", "the", "contrary", "I", "thought", "it", "would", "be", "more", "effective", "if", "you", "found", "out", "yourself", "After", "seeing", "Ashley's", "hard", "life", "I", "thought", "it", "would", "make", "sense", "to", "you", "I", "mean", "if", "anyone", "could", "understand", "the", "reasons", "behind", "giving", "up", "a", "baby", "I", "assumed", "it", "would", "be", "you"]}, {"character": "Emma", "dialog": " You're not getting that kid.", "dialogSplit": ["You're", "not", "getting", "that", "kid"]}, {"character": "Mr. Gold", "dialog": " Actually, we have an agreement. And my agreements are always honored. If not, I'm going to have to involve the police, and that baby is going to end up in the system, and that would be a pity. You didn't enjoy your time in the system, did you Emma?", "dialogSplit": ["Actually", "we", "have", "an", "agreement", "And", "my", "agreements", "are", "always", "honored", "If", "not", "I'm", "going", "to", "have", "to", "involve", "the", "police", "and", "that", "baby", "is", "going", "to", "end", "up", "in", "the", "system", "and", "that", "would", "be", "a", "pity", "You", "didn't", "enjoy", "your", "time", "in", "the", "system", "did", "you", "Emma"]}, {"character": "Emma", "dialog": " That's not gonna happen.", "dialogSplit": ["That's", "not", "gonna", "happen"]}, {"character": "Mr. Gold", "dialog": " I like your confidence. Charming, but all I have to do is press charges. She did, after all, break into my shop.", "dialogSplit": ["I", "like", "your", "confidence", "Charming", "but", "all", "I", "have", "to", "do", "is", "press", "charges", "She", "did", "after", "all", "break", "into", "my", "shop"]}, {"character": "Emma", "dialog": " Let me guess, to steal a contract.", "dialogSplit": ["Let", "me", "guess", "to", "steal", "a", "contract"]}, {"character": "Mr. Gold", "dialog": " Who knows what she was after.", "dialogSplit": ["Who", "knows", "what", "she", "was", "after"]}, {"character": "Emma", "dialog": " You know, no jury in the world will put a woman in jail whose only reason for breaking an entering was to keep her child. I'm willing to roll the dice that contract doesn't stand up. Are you? Not to mention what might come out about you in the process. Somehow I suspect there is more to you than a simple pawnbroker. You really want to start that fight?", "dialogSplit": ["You", "know", "no", "jury", "in", "the", "world", "will", "put", "a", "woman", "in", "jail", "whose", "only", "reason", "for", "breaking", "an", "entering", "was", "to", "keep", "her", "child", "I'm", "willing", "to", "roll", "the", "dice", "that", "contract", "doesn't", "stand", "up", "Are", "you", "Not", "to", "mention", "what", "might", "come", "out", "about", "you", "in", "the", "process", "Somehow", "I", "suspect", "there", "is", "more", "to", "you", "than", "a", "simple", "pawnbroker", "You", "really", "want", "to", "start", "that", "fight"]}, {"character": "Mr. Gold", "dialog": " I like you, Ms. Swan. You're not afraid of me, and that's either cocky or presumptuous. Either way I'd rather have you on my side.", "dialogSplit": ["I", "like", "you", "Ms", "Swan", "You're", "not", "afraid", "of", "me", "and", "that's", "either", "cocky", "or", "presumptuous", "Either", "way", "I'd", "rather", "have", "you", "on", "my", "side"]}, {"character": "Emma", "dialog": " So she can keep the baby?", "dialogSplit": ["So", "she", "can", "keep", "the", "baby"]}, {"character": "Mr. Gold", "dialog": " Not just yet. There's still the matter of my agreement with Ms. Boyd.", "dialogSplit": ["Not", "just", "yet", "There's", "still", "the", "matter", "of", "my", "agreement", "with", "Ms", "Boyd"]}, {"character": "Emma", "dialog": " Tear it up.", "dialogSplit": ["Tear", "it", "up"]}, {"character": "Mr. Gold", "dialog": " That's not what I do. You see, contracts, deals, well they're the very foundation of all civilized existence, so I put it to you now. If you want Ashley to have that baby, are you willing to make a deal with me?", "dialogSplit": ["That's", "not", "what", "I", "do", "You", "see", "contracts", "deals", "well", "they're", "the", "very", "foundation", "of", "all", "civilized", "existence", "so", "I", "put", "it", "to", "you", "now", "If", "you", "want", "Ashley", "to", "have", "that", "baby", "are", "you", "willing", "to", "make", "a", "deal", "with", "me"]}, {"character": "Emma", "dialog": " What do you want?", "dialogSplit": ["What", "do", "you", "want"]}, {"character": "Mr. Gold", "dialog": " Oh I don't know just yet. You'll owe me a favor.", "dialogSplit": ["Oh", "I", "don't", "know", "just", "yet", "You'll", "owe", "me", "a", "favor"]}, {"character": "Emma", "dialog": " Deal. ", "dialogSplit": ["Deal"]}]}, {"sceneDesc": "Storybrooke General Hospital. Present. Ashley's Room. Day.Emma and Henry visit Ashley, she is holding her baby", "tense": "Present", "location": "Storybrooke", "dialog": [{"character": "Emma", "dialog": " Hey. What's her name?", "dialogSplit": ["Hey", "What's", "her", "name"]}, {"character": "Ashley", "dialog": " Alexandra.", "dialogSplit": ["Alexandra"]}, {"character": "Emma", "dialog": " That's pretty.", "dialogSplit": ["That's", "pretty"]}, {"character": "Ashley", "dialog": " Thank you for getting me here.", "dialogSplit": ["Thank", "you", "for", "getting", "me", "here"]}, {"character": "Emma", "dialog": " MrGold was outside. I took care of it. She's yours.", "dialogSplit": ["MrGold", "was", "outside", "I", "took", "care", "of", "it", "She's", "yours"]}, {"character": "Ashley", "dialog": " She is? But what did you do?", "dialogSplit": ["She", "is", "But", "what", "did", "you", "do"]}, {"character": "Emma", "dialog": " Made a deal with him.", "dialogSplit": ["Made", "a", "deal", "with", "him"]}, {"character": "Ashley", "dialog": " Thank you. Thank you.", "dialogSplit": ["Thank", "you", "Thank", "you"]}, {"character": "Emma", "dialog": " Oh, hey kid, it's almost 5:00. You gotta get home. ", "dialogSplit": ["Oh", "hey", "kid", "it's", "almost", "5", "00", "You", "gotta", "get", "home"]}]}, {"sceneDesc": "Storybrooke. Present day. Granny's Bed & Breakfast. A Guest Room.Regina gets dressed. An unknown person is in the shower.", "tense": "Present", "location": "Storybrooke", "dialog": [{"character": "Regina", "dialog": " I have to go. Henry's expecting me home at 5:00. But I'll see you again, at the next council meeting. Oh, and don't forget, you left your socks under the bed. ", "dialogSplit": ["I", "have", "to", "go", "Henry's", "expecting", "me", "home", "at", "5", "00", "But", "I'll", "see", "you", "again", "at", "the", "next", "council", "meeting", "Oh", "and", "don't", "forget", "you", "left", "your", "socks", "under", "the", "bed"]}]}, {"sceneDesc": "Storybrooke. Present day. Emma and Henry are driving in Emma's car.", "tense": "Present", "location": "Storybrooke", "dialog": [{"character": "Emma", "dialog": " \"Pumpkin\". My code name. I was thinking in honor of Cinderella... \"Pumpkin.\"  You got a better one in mind?", "dialogSplit": ["Pumpkin", "My", "code", "name", "I", "was", "thinking", "in", "honor", "of", "Cinderella", "Pumpkin", "You", "got", "a", "better", "one", "in", "mind"]}, {"character": "Henry", "dialog": " Yep.", "dialogSplit": ["Yep"]}, {"character": "Emma", "dialog": " Well?", "dialogSplit": ["Well"]}, {"character": "Henry", "dialog": " I'm not sure you're ready yet. ", "dialogSplit": ["I'm", "not", "sure", "you're", "ready", "yet"]}, {"character": "Emma", "dialog": " Henry! About what you said at the hospital, about me being able to leave?", "dialogSplit": ["Henry", "About", "what", "you", "said", "at", "the", "hospital", "about", "me", "being", "able", "to", "leave"]}, {"character": "Henry", "dialog": " Yeah?", "dialogSplit": ["Yeah"]}, {"character": "Emma", "dialog": " See you tomorrow. ", "dialogSplit": ["See", "you", "tomorrow"]}, {"character": "Regina", "dialog": " Henry? Henry? What did I tell you? Do not... leave your shoes lying around on the stairs. Someone could get hurt. ", "dialogSplit": ["Henry", "Henry", "What", "did", "I", "tell", "you", "Do", "not", "leave", "your", "shoes", "lying", "around", "on", "the", "stairs", "Someone", "could", "get", "hurt"]}]}, {"sceneDesc": "Storybrooke. Present. Storybrooke General Hospital - Day.Sean enters Ashley's room and meets his new daughter.", "tense": "Present", "location": "Storybrooke", "dialog": [{"character": "Sean", "dialog": " Is that her?", "dialogSplit": ["Is", "that", "her"]}, {"character": "Ashley", "dialog": " Sean.", "dialogSplit": ["Sean"]}, {"character": "Sean", "dialog": " I am so sorry. I never should have left you.", "dialogSplit": ["I", "am", "so", "sorry", "I", "never", "should", "have", "left", "you"]}, {"character": "Ashley", "dialog": " You're back?", "dialogSplit": ["You're", "back"]}, {"character": "Sean", "dialog": " Yeah, I'm back. Here, I got her a present.  I don't know if they're gonna fit.", "dialogSplit": ["Yeah", "I'm", "back", "Here", "I", "got", "her", "a", "present", "I", "don't", "know", "if", "they're", "gonna", "fit"]}, {"character": "Ashley", "dialog": " They're perfect. ", "dialogSplit": ["They're", "perfect"]}]}, {"sceneDesc": "Storybrooke. Present day. Emma is standing outside her car. She calls Sheriff Graham who is in his apartment.", "tense": "Present", "location": "Storybrooke", "dialog": [{"character": "Graham", "dialog": " Hello?", "dialogSplit": ["Hello"]}, {"character": "Emma", "dialog": " Graham, it's Emma. I was thinking maybe some roots wouldn't be so bad. That deputy job still open?", "dialogSplit": ["Graham", "it's", "Emma", "I", "was", "thinking", "maybe", "some", "roots", "wouldn't", "be", "so", "bad", "That", "deputy", "job", "still", "open"]}, {"character": "Graham", "dialog": " Absolutely.", "dialogSplit": ["Absolutely"]}, {"character": "Emma", "dialog": " Then I'm in. Regina gonna be okay with this?", "dialogSplit": ["Then", "I'm", "in", "Regina", "gonna", "be", "okay", "with", "this"]}, {"character": "Graham", "dialog": " I don't care, it's my department. I'll see you Monday morning.", "dialogSplit": ["I", "don't", "care", "it's", "my", "department", "I'll", "see", "you", "Monday", "morning"]}, {"character": "Emma", "dialog": " I'll see ya.", "dialogSplit": ["I'll", "see", "ya"]}]}, {"sceneDesc": "Storybrooke. Present day. Emma is standing outside her car. She calls Sheriff Graham who is in his apartment.", "tense": "Present", "location": "Storybrooke", "dialog": [{"character": "", "dialog": "", "dialogSplit": []}]}, {"sceneDesc": "Storybrooke. Present. Granny's Bed and Breakfast. Day.Guest Room.", "tense": "Present", "location": "Storybrooke", "dialog": [{"character": "", "dialog": "Graham, shirtless, hangs up the phone. He reaches under the bed to retrieve his socks after his previous tryst with Regina.", "dialogSplit": ["Graham", "shirtless", "hangs", "up", "the", "phone", "He", "reaches", "under", "the", "bed", "to", "retrieve", "his", "socks", "after", "his", "previous", "tryst", "with", "Regina"]}]}]}