{"episode": "Lady_of_the_Lake", "scenes": [{"sceneDesc": "The Enchanted Forest. Past. Red Riding Hood running in a forest.", "tense": "Past", "location": "The Enchanted Forest", "dialog": [{"character": "Prince Charming", "dialog": "King George's men are here on this ridge.", "dialogSplit": ["King", "George's", "men", "are", "here", "on", "this", "ridge"]}, {"character": "Red", "dialog": " We have to move camp. They're coming for us.", "dialogSplit": ["We", "have", "to", "move", "camp", "They're", "coming", "for", "us"]}, {"character": "Prince Charming", "dialog": " No! We will not run! We said we were gonna take the kingdom back, and we can't do that with our tails between our legs.  No offense.", "dialogSplit": ["No", "We", "will", "not", "run", "We", "said", "we", "were", "gonna", "take", "the", "kingdom", "back", "and", "we", "can't", "do", "that", "with", "our", "tails", "between", "our", "legs", "No", "offense"]}, {"character": "Red", "dialog": " But matters have worsened. The King has a new general.", "dialogSplit": ["But", "matters", "have", "worsened", "The", "King", "has", "a", "new", "general"]}, {"character": "Snow White", "dialog": " Who is he?", "dialogSplit": ["Who", "is", "he"]}, {"character": "Red", "dialog": " They call him the Leviathan. They say he attacks like a monster striking from the depths of the sea. You never see him coming, and you never survive.", "dialogSplit": ["They", "call", "him", "the", "Leviathan", "They", "say", "he", "attacks", "like", "a", "monster", "striking", "from", "the", "depths", "of", "the", "sea", "You", "never", "see", "him", "coming", "and", "you", "never", "survive"]}, {"character": "Prince Charming", "dialog": " We'll see about that.", "dialogSplit": ["We'll", "see", "about", "that"]}, {"character": "Snow White", "dialog": " How close is his army? ", "dialogSplit": ["How", "close", "is", "his", "army"]}, {"character": "Prince Charming", "dialog": " I'd say pretty close.", "dialogSplit": ["I'd", "say", "pretty", "close"]}, {"character": "Snow White", "dialog": " We should split up. Divide them.", "dialogSplit": ["We", "should", "split", "up", "Divide", "them"]}, {"character": "Prince Charming", "dialog": " Exactly. Go! Go! Go.", "dialogSplit": ["Exactly", "Go", "Go", "Go"]}, {"character": "Snow White", "dialog": " Aren't you coming?", "dialogSplit": ["Aren't", "you", "coming"]}, {"character": "Prince Charming", "dialog": " He's after me.", "dialogSplit": ["He's", "after", "me"]}, {"character": "Snow White", "dialog": " You'll have a better chance of escaping on your own.", "dialogSplit": ["You'll", "have", "a", "better", "chance", "of", "escaping", "on", "your", "own"]}, {"character": "Prince Charming", "dialog": " Don't worry. Meet me in two days' time at the cabin.", "dialogSplit": ["Don't", "worry", "Meet", "me", "in", "two", "days", "time", "at", "the", "cabin"]}, {"character": "Snow White", "dialog": " The cabin? Where she is? Are you sure?", "dialogSplit": ["The", "cabin", "Where", "she", "is", "Are", "you", "sure"]}, {"character": "Prince Charming", "dialog": " We're engaged. I think it's about time you met my mother.  Go. Go.", "dialogSplit": ["We're", "engaged", "I", "think", "it's", "about", "time", "you", "met", "my", "mother", "Go", "Go"]}, {"character": "Snow White", "dialog": " Ah! What kind of general hides behind a mask? Who are you really, Leviathan?", "dialogSplit": ["Ah", "What", "kind", "of", "general", "hides", "behind", "a", "mask", "Who", "are", "you", "really", "Leviathan"]}, {"character": "Lancelot", "dialog": " \"Leviathan\"? That's what they're calling me?  Name's Lancelot.", "dialogSplit": ["Leviathan", "That's", "what", "they're", "calling", "me", "Name's", "Lancelot"]}, {"character": "Snow White", "dialog": " Lancelot? Of the Round Table?", "dialogSplit": ["Lancelot", "Of", "the", "Round", "Table"]}, {"character": "Lancelot", "dialog": " Not anymore. ", "dialogSplit": ["Not", "anymore"]}]}, {"sceneDesc": "The Enchanted Forest. Present Day. The safe haven. Cora tends an unconscious Mary Margaret while Emma watches in the pit where they are being held.", "tense": "Present", "location": "The Enchanted Forest", "dialog": [{"character": "Emma", "dialog": " You sure she's gonna be okay?", "dialogSplit": ["You", "sure", "she's", "gonna", "be", "okay"]}, {"character": "Cora", "dialog": " Don't worry. She'll be fine.", "dialogSplit": ["Don't", "worry", "She'll", "be", "fine"]}, {"character": "Emma", "dialog": " What is this place? Where are we?", "dialogSplit": ["What", "is", "this", "place", "Where", "are", "we"]}, {"character": "Cora", "dialog": " It's a little island our captors like to think of as their haven.", "dialogSplit": ["It's", "a", "little", "island", "our", "captors", "like", "to", "think", "of", "as", "their", "haven"]}, {"character": "Emma", "dialog": " Haven? From what?", "dialogSplit": ["Haven", "From", "what"]}, {"character": "Cora", "dialog": " The world's dangerous. What's left of it, anyway.", "dialogSplit": ["The", "world's", "dangerous", "What's", "left", "of", "it", "anyway"]}, {"character": "Emma", "dialog": " Well, they can't keep us down here. We didn't do anything wrong.", "dialogSplit": ["Well", "they", "can't", "keep", "us", "down", "here", "We", "didn't", "do", "anything", "wrong"]}, {"character": "Cora", "dialog": " Neither did I.", "dialogSplit": ["Neither", "did", "I"]}, {"character": "Emma", "dialog": " Then why are you here?", "dialogSplit": ["Then", "why", "are", "you", "here"]}, {"character": "Cora", "dialog": " I'm here because of something my daughter did. The curse that ravaged this land? She cast it.", "dialogSplit": ["I'm", "here", "because", "of", "something", "my", "daughter", "did", "The", "curse", "that", "ravaged", "this", "land", "She", "cast", "it"]}, {"character": "Emma", "dialog": "Regina? You're Regina's mother?", "dialogSplit": ["Regina", "You're", "Regina's", "mother"]}, {"character": "Cora", "dialog": " Yes. But you've nothing to fear from me. The apple fell very far from the tree. You're from over there, aren't you? How'd you get back?", "dialogSplit": ["Yes", "But", "you've", "nothing", "to", "fear", "from", "me", "The", "apple", "fell", "very", "far", "from", "the", "tree", "You're", "from", "over", "there", "aren't", "you", "How'd", "you", "get", "back"]}, {"character": "Mary Margaret", "dialog": " Emma. No...", "dialogSplit": ["Emma", "No"]}, {"character": "Cora", "dialog": " Oh, Snow, you're awake. I'm so relieved.", "dialogSplit": ["Oh", "Snow", "you're", "awake", "I'm", "so", "relieved"]}, {"character": "Mary Margaret", "dialog": " As bad as you think Regina is, this woman is worse.", "dialogSplit": ["As", "bad", "as", "you", "think", "Regina", "is", "this", "woman", "is", "worse"]}, {"character": "Cora", "dialog": " Oh, Snow. Sweet Snow, please believe me. Whatever she told you isn't true. I just want to help you.", "dialogSplit": ["Oh", "Snow", "Sweet", "Snow", "please", "believe", "me", "Whatever", "she", "told", "you", "isn't", "true", "I", "just", "want", "to", "help", "you"]}, {"character": "Emma", "dialog": " Let's hear her out.", "dialogSplit": ["Let's", "hear", "her", "out"]}, {"character": "Mary Margaret", "dialog": " Emma.", "dialogSplit": ["Emma"]}, {"character": "Emma", "dialog": " Okay. Right now, we're at the bottom of a hole with no other options. And Henry is back in Storybrooke with Regina.", "dialogSplit": ["Okay", "Right", "now", "we're", "at", "the", "bottom", "of", "a", "hole", "with", "no", "other", "options", "And", "Henry", "is", "back", "in", "Storybrooke", "with", "Regina"]}, {"character": "Cora", "dialog": " Who's Henry?", "dialogSplit": ["Who's", "Henry"]}, {"character": "Emma", "dialog": " My son. I kind of share him with Regina. It's complicated.", "dialogSplit": ["My", "son", "I", "kind", "of", "share", "him", "with", "Regina", "It's", "complicated"]}, {"character": "Mary Margaret", "dialog": " Don't talk to her!", "dialogSplit": ["Don't", "talk", "to", "her"]}, {"character": "Man", "dialog": " Enough! Our leader requests an audience.", "dialogSplit": ["Enough", "Our", "leader", "requests", "an", "audience"]}]}, {"sceneDesc": "Storybrooke. Present. David walks with Henry to the school bus.", "tense": "Present", "location": "Storybrooke", "dialog": [{"character": "Henry", "dialog": " So what's on the agenda for Operation Scorpion?", "dialogSplit": ["So", "what's", "on", "the", "agenda", "for", "Operation", "Scorpion"]}, {"character": "David", "dialog": " What's Operation Scorpion?", "dialogSplit": ["What's", "Operation", "Scorpion"]}, {"character": "Henry", "dialog": " The code name for our mission to find Emma and Snow. Do you prefer Viper? That was my second choice.", "dialogSplit": ["The", "code", "name", "for", "our", "mission", "to", "find", "Emma", "and", "Snow", "Do", "you", "prefer", "Viper", "That", "was", "my", "second", "choice"]}, {"character": "David", "dialog": " Henry, we need to talk.", "dialogSplit": ["Henry", "we", "need", "to", "talk"]}, {"character": "Henry", "dialog": " Yeah, Scorpion's better.", "dialogSplit": ["Yeah", "Scorpion's", "better"]}, {"character": "David", "dialog": " No, it's not that. It's...", "dialogSplit": ["No", "it's", "not", "that", "It's"]}, {"character": "Henry", "dialog": " I'm not coming with you? But I-I thought we were gonna find Jefferson.", "dialogSplit": ["I'm", "not", "coming", "with", "you", "But", "I", "I", "thought", "we", "were", "gonna", "find", "Jefferson"]}, {"character": "David", "dialog": " I already did.", "dialogSplit": ["I", "already", "did"]}, {"character": "Henry", "dialog": " What? Is he gonna help us?", "dialogSplit": ["What", "Is", "he", "gonna", "help", "us"]}, {"character": "David", "dialog": " No. No, Henry, he's not.", "dialogSplit": ["No", "No", "Henry", "he's", "not"]}, {"character": "Henry", "dialog": " But why didn't you tell me you talked to him?", "dialogSplit": ["But", "why", "didn't", "you", "tell", "me", "you", "talked", "to", "him"]}, {"character": "David", "dialog": " Because I didn't want to disappoint you. I know you want to find your mom, but Jefferson can't help us. I need to find a way to restore the hat.", "dialogSplit": ["Because", "I", "didn't", "want", "to", "disappoint", "you", "I", "know", "you", "want", "to", "find", "your", "mom", "but", "Jefferson", "can't", "help", "us", "I", "need", "to", "find", "a", "way", "to", "restore", "the", "hat"]}, {"character": "Henry", "dialog": " So why can't I help you look?", "dialogSplit": ["So", "why", "can't", "I", "help", "you", "look"]}, {"character": "David", "dialog": " It'll require magic, Henry, and magic...", "dialogSplit": ["It'll", "require", "magic", "Henry", "and", "magic"]}, {"character": "Henry", "dialog": " Always comes with a price. I've read the book, you know?", "dialogSplit": ["Always", "comes", "with", "a", "price", "I've", "read", "the", "book", "you", "know"]}, {"character": "David", "dialog": " I'm sorry, but I just can't let you anywhere near this stuff. If you really want to help me, you'll go to school where I know you'll be safe. Okay?", "dialogSplit": ["I'm", "sorry", "but", "I", "just", "can't", "let", "you", "anywhere", "near", "this", "stuff", "If", "you", "really", "want", "to", "help", "me", "you'll", "go", "to", "school", "where", "I", "know", "you'll", "be", "safe", "Okay"]}, {"character": "Henry", "dialog": " Okay. Henry goes towards the school bus and David leaves. Henry looks back and runs away.", "dialogSplit": ["Okay", "Henry", "goes", "towards", "the", "school", "bus", "and", "David", "leaves", "Henry", "looks", "back", "and", "runs", "away"]}]}, {"sceneDesc": "The Enchanted Forest. Present Day. The Safe Haven. Emma and Mary Margaret walking through the camp.", "tense": "Present", "location": "The Enchanted Forest", "dialog": [{"character": "Mary Margaret", "dialog": " Why can't you just listen to me?", "dialogSplit": ["Why", "can't", "you", "just", "listen", "to", "me"]}, {"character": "Emma", "dialog": " Why couldn't you have trusted me? I was just trying to find a way to get us home. I could've handled her.", "dialogSplit": ["Why", "couldn't", "you", "have", "trusted", "me", "I", "was", "just", "trying", "to", "find", "a", "way", "to", "get", "us", "home", "I", "could've", "handled", "her"]}, {"character": "Mary Margaret", "dialog": " Cora? Don't be so sure. I've lived here, Emma. I know this world and its dangers.", "dialogSplit": ["Cora", "Don't", "be", "so", "sure", "I've", "lived", "here", "Emma", "I", "know", "this", "world", "and", "its", "dangers"]}, {"character": "Man", "dialog": " Wait here.", "dialogSplit": ["Wait", "here"]}, {"character": "Emma", "dialog": " Is that why you came through the portal? Because you thought I was helpless here?", "dialogSplit": ["Is", "that", "why", "you", "came", "through", "the", "portal", "Because", "you", "thought", "I", "was", "helpless", "here"]}, {"character": "Mary Margaret", "dialog": " No. I came through to be with you. Lancelot?", "dialogSplit": ["No", "I", "came", "through", "to", "be", "with", "you", "Lancelot"]}, {"character": "Lancelot", "dialog": " Snow?", "dialogSplit": ["Snow"]}, {"character": "Mary Margaret", "dialog": " Oh! Oh!", "dialogSplit": ["Oh", "Oh"]}, {"character": "Lancelot", "dialog": " If I had known that you were the prisoners Mulan had brought back, I never would've locked you away. Please, forgive me.", "dialogSplit": ["If", "I", "had", "known", "that", "you", "were", "the", "prisoners", "Mulan", "had", "brought", "back", "I", "never", "would've", "locked", "you", "away", "Please", "forgive", "me"]}, {"character": "Mary Margaret", "dialog": " Of course.", "dialogSplit": ["Of", "course"]}, {"character": "Emma", "dialog": " Lancelot? Really?", "dialogSplit": ["Lancelot", "Really"]}, {"character": "Mary Margaret", "dialog": " He's an old friend. We can trust him. This is Emma.", "dialogSplit": ["He's", "an", "old", "friend", "We", "can", "trust", "him", "This", "is", "Emma"]}, {"character": "Aurora", "dialog": " Why is he embracing them? They were responsible for Phillip's death.", "dialogSplit": ["Why", "is", "he", "embracing", "them", "They", "were", "responsible", "for", "Phillip's", "death"]}, {"character": "Mulan", "dialog": " You're new here, Aurora. Phillip trusted Lancelot. So must we.", "dialogSplit": ["You're", "new", "here", "Aurora", "Phillip", "trusted", "Lancelot", "So", "must", "we"]}, {"character": "Aurora", "dialog": " I want justice.", "dialogSplit": ["I", "want", "justice"]}, {"character": "Mulan", "dialog": " Tread carefully. It's dangerous to confuse vengeance with justice. Do you understand me? Do you understand me?", "dialogSplit": ["Tread", "carefully", "It's", "dangerous", "to", "confuse", "vengeance", "with", "justice", "Do", "you", "understand", "me", "Do", "you", "understand", "me"]}, {"character": "Aurora", "dialog": " Yes. Mulan leaves. Aurora draws out a concealed dagger and looks back at Emma and Mary Margaret.", "dialogSplit": ["Yes", "Mulan", "leaves", "Aurora", "draws", "out", "a", "concealed", "dagger", "and", "looks", "back", "at", "Emma", "and", "Mary", "Margaret"]}]}, {"sceneDesc": "The Enchanted Forest. Present Day. The Safe Haven. Emma and Mary Margaret receive a comprehensive meal.", "tense": "Present", "location": "The Enchanted Forest", "dialog": [{"character": "Emma", "dialog": " What the hell is that?", "dialogSplit": ["What", "the", "hell", "is", "that"]}, {"character": "Lancelot", "dialog": " That is Chimera. An acquired taste, but all our hunting party could bring back. One part lion, one part serpent, one part goat.", "dialogSplit": ["That", "is", "Chimera", "An", "acquired", "taste", "but", "all", "our", "hunting", "party", "could", "bring", "back", "One", "part", "lion", "one", "part", "serpent", "one", "part", "goat"]}, {"character": "Emma", "dialog": " Like turducken?", "dialogSplit": ["Like", "turducken"]}, {"character": "Mary Margaret", "dialog": " I don't understand. We were told this land didn't even exist anymore. How did you all escape the curse?", "dialogSplit": ["I", "don't", "understand", "We", "were", "told", "this", "land", "didn't", "even", "exist", "anymore", "How", "did", "you", "all", "escape", "the", "curse"]}, {"character": "Lancelot", "dialog": " It is a mystery. The curse struck, and when the smoke cleared, most of us had been torn from this land. But some of us here, in this particular region, were left behind. We don't know how and we don't know why. Finding this safe haven wasn't easy. It took some spilt blood. But, worry not, you're safe here.", "dialogSplit": ["It", "is", "a", "mystery", "The", "curse", "struck", "and", "when", "the", "smoke", "cleared", "most", "of", "us", "had", "been", "torn", "from", "this", "land", "But", "some", "of", "us", "here", "in", "this", "particular", "region", "were", "left", "behind", "We", "don't", "know", "how", "and", "we", "don't", "know", "why", "Finding", "this", "safe", "haven", "wasn't", "easy", "It", "took", "some", "spilt", "blood", "But", "worry", "not", "you're", "safe", "here"]}, {"character": "Mary Margaret", "dialog": " We can't stay. My husband's back there. Emma's son, my grandson. We have to get back to them. Can you help us find a portal?", "dialogSplit": ["We", "can't", "stay", "My", "husband's", "back", "there", "Emma's", "son", "my", "grandson", "We", "have", "to", "get", "back", "to", "them", "Can", "you", "help", "us", "find", "a", "portal"]}, {"character": "Lancelot", "dialog": " No, leaving is unwise. The Enchanted Forest is not as you remember it. The Ogres have returned.", "dialogSplit": ["No", "leaving", "is", "unwise", "The", "Enchanted", "Forest", "is", "not", "as", "you", "remember", "it", "The", "Ogres", "have", "returned"]}, {"character": "Emma", "dialog": " Ogres? Like, as in \"Fee-Fi-Fo-Fum\"?", "dialogSplit": ["Ogres", "Like", "as", "in", "Fee", "Fi", "Fo", "Fum"]}, {"character": "Mary Margaret", "dialog": " Those would be giants.", "dialogSplit": ["Those", "would", "be", "giants"]}, {"character": "Lancelot", "dialog": " Ogres are far worse. That's why we live here, on this island, where it's safe. Please, Snow, stay here. There are no more portals left.", "dialogSplit": ["Ogres", "are", "far", "worse", "That's", "why", "we", "live", "here", "on", "this", "island", "where", "it's", "safe", "Please", "Snow", "stay", "here", "There", "are", "no", "more", "portals", "left"]}, {"character": "Mary Margaret", "dialog": " I might know of one.", "dialogSplit": ["I", "might", "know", "of", "one"]}, {"character": "Emma", "dialog": " You do?", "dialogSplit": ["You", "do"]}, {"character": "Lancelot", "dialog": " Where?", "dialogSplit": ["Where"]}, {"character": "Mary Margaret", "dialog": " Cora's near. I don't feel comfortable voicing my plans. She's powerful.", "dialogSplit": ["Cora's", "near", "I", "don't", "feel", "comfortable", "voicing", "my", "plans", "She's", "powerful"]}, {"character": "Lancelot", "dialog": " Not any more. The curse stripped her of her powers. But given her reputation, we've kept her locked up as a precaution.", "dialogSplit": ["Not", "any", "more", "The", "curse", "stripped", "her", "of", "her", "powers", "But", "given", "her", "reputation", "we've", "kept", "her", "locked", "up", "as", "a", "precaution"]}, {"character": "Mary Margaret", "dialog": " Nevertheless, I'm not taking chances. Just trust me, I may have a way. Let us go.", "dialogSplit": ["Nevertheless", "I'm", "not", "taking", "chances", "Just", "trust", "me", "I", "may", "have", "a", "way", "Let", "us", "go"]}, {"character": "Lancelot", "dialog": " I'll allow it. But on one condition. Take my bravest warrior with you. Allow Mulan to defend you.", "dialogSplit": ["I'll", "allow", "it", "But", "on", "one", "condition", "Take", "my", "bravest", "warrior", "with", "you", "Allow", "Mulan", "to", "defend", "you"]}, {"character": "Emma", "dialog": " We can defend ourselves.", "dialogSplit": ["We", "can", "defend", "ourselves"]}, {"character": "Mary Margaret", "dialog": " Deal. Thank you, Lancelot. For always looking out for me.", "dialogSplit": ["Deal", "Thank", "you", "Lancelot", "For", "always", "looking", "out", "for", "me"]}]}, {"sceneDesc": "The Enchanted Forest. Past. Royal Castle.", "tense": "Past", "location": "The Enchanted Forest", "dialog": [{"character": "Snow White", "dialog": " I don't care what you do to me. I will never tell you where he is!", "dialogSplit": ["I", "don't", "care", "what", "you", "do", "to", "me", "I", "will", "never", "tell", "you", "where", "he", "is"]}, {"character": "King George", "dialog": " I know. That's not why you're here. Would you bring our guest some water? Times have been good for you, haven't they? I can see a light in your eyes. Cherish that, because that light can die and be replaced by something else... pain.", "dialogSplit": ["I", "know", "That's", "not", "why", "you're", "here", "Would", "you", "bring", "our", "guest", "some", "water", "Times", "have", "been", "good", "for", "you", "haven't", "they", "I", "can", "see", "a", "light", "in", "your", "eyes", "Cherish", "that", "because", "that", "light", "can", "die", "and", "be", "replaced", "by", "something", "else", "pain"]}, {"character": "Snow White", "dialog": " The only thing you know of pain is how to inflict it.", "dialogSplit": ["The", "only", "thing", "you", "know", "of", "pain", "is", "how", "to", "inflict", "it"]}, {"character": "King George", "dialog": " That's where you're so very, very wrong. I've had my share of pain. I had a son that I loved die before his time. I tried to replace him with your \"Charming,\" offered him the world, but he rejected me, humiliated me in front of my kingdom, all for the sake of true love.", "dialogSplit": ["That's", "where", "you're", "so", "very", "very", "wrong", "I've", "had", "my", "share", "of", "pain", "I", "had", "a", "son", "that", "I", "loved", "die", "before", "his", "time", "I", "tried", "to", "replace", "him", "with", "your", "Charming", "offered", "him", "the", "world", "but", "he", "rejected", "me", "humiliated", "me", "in", "front", "of", "my", "kingdom", "all", "for", "the", "sake", "of", "true", "love"]}, {"character": "Snow White", "dialog": " Something about which you know nothing.", "dialogSplit": ["Something", "about", "which", "you", "know", "nothing"]}, {"character": "King George", "dialog": " I know more than you think.", "dialogSplit": ["I", "know", "more", "than", "you", "think"]}, {"character": "Snow White", "dialog": "You... were in love?", "dialogSplit": ["You", "were", "in", "love"]}, {"character": "King George", "dialog": " Yes, and she loved me. We were happy, blissful, but then she became cursed. She drank a vile potion that made it impossible for us to conceive a child. Family is everything, my dear. Losing all hope of having one... there is no greater misery. Charming could've been that hope for me, but instead, he made my suffering worse. For that, death is too good for him. First, he must know pain... my pain.", "dialogSplit": ["Yes", "and", "she", "loved", "me", "We", "were", "happy", "blissful", "but", "then", "she", "became", "cursed", "She", "drank", "a", "vile", "potion", "that", "made", "it", "impossible", "for", "us", "to", "conceive", "a", "child", "Family", "is", "everything", "my", "dear", "Losing", "all", "hope", "of", "having", "one", "there", "is", "no", "greater", "misery", "Charming", "could've", "been", "that", "hope", "for", "me", "but", "instead", "he", "made", "my", "suffering", "worse", "For", "that", "death", "is", "too", "good", "for", "him", "First", "he", "must", "know", "pain", "my", "pain"]}, {"character": "Snow White", "dialog": " No.", "dialogSplit": ["No"]}, {"character": "Lancelot", "dialog": " You poisoned her?", "dialogSplit": ["You", "poisoned", "her"]}, {"character": "King George", "dialog": " I cursed her. She will never bear a child.", "dialogSplit": ["I", "cursed", "her", "She", "will", "never", "bear", "a", "child"]}]}, {"sceneDesc": "The Enchanted Forest. Present. The Safe Haven.", "tense": "Present", "location": "The Enchanted Forest", "dialog": [{"character": "Mulan", "dialog": " Choose wisely. We must be vigilant if we hope to survive the journey.", "dialogSplit": ["Choose", "wisely", "We", "must", "be", "vigilant", "if", "we", "hope", "to", "survive", "the", "journey"]}, {"character": "Emma", "dialog": " Where's my gun? I want it back.", "dialogSplit": ["Where's", "my", "gun", "I", "want", "it", "back"]}, {"character": "Mulan", "dialog": " Is it magic?", "dialogSplit": ["Is", "it", "magic"]}, {"character": "Emma", "dialog": " Depends on who's pulling the trigger.", "dialogSplit": ["Depends", "on", "who's", "pulling", "the", "trigger"]}, {"character": "Mulan", "dialog": " Follow my lead, step where I step, do exactly as I say, and we might survive.", "dialogSplit": ["Follow", "my", "lead", "step", "where", "I", "step", "do", "exactly", "as", "I", "say", "and", "we", "might", "survive"]}, {"character": "Emma", "dialog": " Thanks for the pep talk, but I think we're okay. I just killed a dragon last week.", "dialogSplit": ["Thanks", "for", "the", "pep", "talk", "but", "I", "think", "we're", "okay", "I", "just", "killed", "a", "dragon", "last", "week"]}, {"character": "Mulan", "dialog": " Have you ever seen an ogre?", "dialogSplit": ["Have", "you", "ever", "seen", "an", "ogre"]}, {"character": "Emma", "dialog": " Pretty sure I've dated a few.", "dialogSplit": ["Pretty", "sure", "I've", "dated", "a", "few"]}, {"character": "Mulan", "dialog": " Legend has it that when they kill you, the last thing you see is yourself dying in the reflection in their eyes. Let's walk. It'll be dark soon.", "dialogSplit": ["Legend", "has", "it", "that", "when", "they", "kill", "you", "the", "last", "thing", "you", "see", "is", "yourself", "dying", "in", "the", "reflection", "in", "their", "eyes", "Let's", "walk", "It'll", "be", "dark", "soon"]}, {"character": "Mary Margaret", "dialog": " Don't let her rattle you. I won't let anything happen to us. Stick to the plan.", "dialogSplit": ["Don't", "let", "her", "rattle", "you", "I", "won't", "let", "anything", "happen", "to", "us", "Stick", "to", "the", "plan"]}, {"character": "Emma", "dialog": " What is the plan? You haven't told me anything. What's going on?", "dialogSplit": ["What", "is", "the", "plan", "You", "haven't", "told", "me", "anything", "What's", "going", "on"]}, {"character": "Mary Margaret", "dialog": " The wardrobe.", "dialogSplit": ["The", "wardrobe"]}, {"character": "Emma", "dialog": " Wardrobe? The wardrobe? Like, the wardrobe that sent little baby me to Maine?", "dialogSplit": ["Wardrobe", "The", "wardrobe", "Like", "the", "wardrobe", "that", "sent", "little", "baby", "me", "to", "Maine"]}, {"character": "Mary Margaret", "dialog": " Mm-hmm.", "dialogSplit": ["Mm", "hmm"]}, {"character": "Emma", "dialog": " You think it could get us back to Storybrooke?", "dialogSplit": ["You", "think", "it", "could", "get", "us", "back", "to", "Storybrooke"]}, {"character": "Mary Margaret", "dialog": " I don't know. First we have to see if it survived the curse, then we'll worry about making it work.", "dialogSplit": ["I", "don't", "know", "First", "we", "have", "to", "see", "if", "it", "survived", "the", "curse", "then", "we'll", "worry", "about", "making", "it", "work"]}, {"character": "Emma", "dialog": " Where is it?", "dialogSplit": ["Where", "is", "it"]}, {"character": "Mary Margaret", "dialog": " My place. You wanna see where you're from, Emma? That's right. We're going home.", "dialogSplit": ["My", "place", "You", "wanna", "see", "where", "you're", "from", "Emma", "That's", "right", "We're", "going", "home"]}]}, {"sceneDesc": "Storybrooke. Present. Henry found Jefferson.", "tense": "Present", "location": "Storybrooke", "dialog": [{"character": "Henry", "dialog": " Jefferson. Right? The mad hatter. I need your help.", "dialogSplit": ["Jefferson", "Right", "The", "mad", "hatter", "I", "need", "your", "help"]}, {"character": "Jefferson", "dialog": " Look, I already told your grandfather... I can't do anything.", "dialogSplit": ["Look", "I", "already", "told", "your", "grandfather", "I", "can't", "do", "anything"]}, {"character": "Henry", "dialog": " I know, but there must be something we can do.", "dialogSplit": ["I", "know", "but", "there", "must", "be", "something", "we", "can", "do"]}, {"character": "Jefferson", "dialog": " I'm the wrong person to talk to, kid. Magic's not my thing. Try your mother. Maybe she's got something in that vault of hers she can help you with.", "dialogSplit": ["I'm", "the", "wrong", "person", "to", "talk", "to", "kid", "Magic's", "not", "my", "thing", "Try", "your", "mother", "Maybe", "she's", "got", "something", "in", "that", "vault", "of", "hers", "she", "can", "help", "you", "with"]}, {"character": "Henry", "dialog": " Vault? Her vault is here? In Storybrooke?", "dialogSplit": ["Vault", "Her", "vault", "is", "here", "In", "Storybrooke"]}, {"character": "Jefferson", "dialog": " It's none of my business. Talk to her.", "dialogSplit": ["It's", "none", "of", "my", "business", "Talk", "to", "her"]}, {"character": "Henry", "dialog": " What's that? Your daughter's looking for you, isn't she?", "dialogSplit": ["What's", "that", "Your", "daughter's", "looking", "for", "you", "isn't", "she"]}, {"character": "Jefferson", "dialog": " What do you know about it?", "dialogSplit": ["What", "do", "you", "know", "about", "it"]}, {"character": "Henry", "dialog": " I've read your story. I know how the two of you were separated. Why are you here? She's at school.", "dialogSplit": ["I've", "read", "your", "story", "I", "know", "how", "the", "two", "of", "you", "were", "separated", "Why", "are", "you", "here", "She's", "at", "school"]}, {"character": "Jefferson", "dialog": " I gotta go home, kid.", "dialogSplit": ["I", "gotta", "go", "home", "kid"]}, {"character": "Henry", "dialog": " She probably wants to see you.", "dialogSplit": ["She", "probably", "wants", "to", "see", "you"]}, {"character": "Jefferson", "dialog": " Get out of my way. Get out of my way.", "dialogSplit": ["Get", "out", "of", "my", "way", "Get", "out", "of", "my", "way"]}, {"character": "Henry", "dialog": " Why aren't you going to find her?", "dialogSplit": ["Why", "aren't", "you", "going", "to", "find", "her"]}, {"character": "Jefferson", "dialog": " Because I left her! And she'll hate me.", "dialogSplit": ["Because", "I", "left", "her", "And", "she'll", "hate", "me"]}, {"character": "Henry", "dialog": " How do you know that?", "dialogSplit": ["How", "do", "you", "know", "that"]}, {"character": "Jefferson", "dialog": " I was on my way, but fate reminded me I shouldn't.", "dialogSplit": ["I", "was", "on", "my", "way", "but", "fate", "reminded", "me", "I", "shouldn't"]}, {"character": "Henry", "dialog": " You should. I've been left, too. Anything's better than nothing. She'll spend her whole life wondering why you left her. Not knowing is the worst.", "dialogSplit": ["You", "should", "I've", "been", "left", "too", "Anything's", "better", "than", "nothing", "She'll", "spend", "her", "whole", "life", "wondering", "why", "you", "left", "her", "Not", "knowing", "is", "the", "worst"]}, {"character": "Regina", "dialog": " Henry. I'm just packing up the office. I've been asked to leave. No, of course it can wait. I'd love to have lunch with you. Granny's, ten minutes.", "dialogSplit": ["Henry", "I'm", "just", "packing", "up", "the", "office", "I've", "been", "asked", "to", "leave", "No", "of", "course", "it", "can", "wait", "I'd", "love", "to", "have", "lunch", "with", "you", "Granny's", "ten", "minutes"]}]}, {"sceneDesc": "The Enchanted Forest. Present. The Safe Haven.", "tense": "Present", "location": "The Enchanted Forest", "dialog": [{"character": "Mulan", "dialog": " This will do. We'll make camp here for the night. We just need to find water, collect some firewood.", "dialogSplit": ["This", "will", "do", "We'll", "make", "camp", "here", "for", "the", "night", "We", "just", "need", "to", "find", "water", "collect", "some", "firewood"]}, {"character": "Emma", "dialog": " Uh, if we're hiding from ogres, shouldn't we maybe, I don't know, not start a fire?", "dialogSplit": ["Uh", "if", "we're", "hiding", "from", "ogres", "shouldn't", "we", "maybe", "I", "don't", "know", "not", "start", "a", "fire"]}, {"character": "Mary Margaret", "dialog": " Ogres are blind. They hunt by sound alone.", "dialogSplit": ["Ogres", "are", "blind", "They", "hunt", "by", "sound", "alone"]}, {"character": "Emma", "dialog": " Right. Because that's something everyone would know about ogres.", "dialogSplit": ["Right", "Because", "that's", "something", "everyone", "would", "know", "about", "ogres"]}, {"character": "Mary Margaret", "dialog": " Look... I know you're out of your element...", "dialogSplit": ["Look", "I", "know", "you're", "out", "of", "your", "element"]}, {"character": "Emma", "dialog": " I'm fine.", "dialogSplit": ["I'm", "fine"]}, {"character": "Mary Margaret", "dialog": " I know, but maybe you should just stay here while we get wood and water, guard the campsite.", "dialogSplit": ["I", "know", "but", "maybe", "you", "should", "just", "stay", "here", "while", "we", "get", "wood", "and", "water", "guard", "the", "campsite"]}, {"character": "Emma", "dialog": " You mean the big, empty clearing?", "dialogSplit": ["You", "mean", "the", "big", "empty", "clearing"]}, {"character": "Mary Margaret", "dialog": " It's the safest place. We'll be right back.", "dialogSplit": ["It's", "the", "safest", "place", "We'll", "be", "right", "back"]}]}, {"sceneDesc": "The Enchanted Forest. Past. Snow White realizes that she is being pursued. She ambushes Lancelot.", "tense": "Past", "location": "The Enchanted Forest", "dialog": [{"character": "Snow White", "dialog": " Aah! Uhh!  Ya!", "dialogSplit": ["Aah", "Uhh", "Ya"]}, {"character": "Lancelot", "dialog": " Wait! I've come to help.", "dialogSplit": ["Wait", "I've", "come", "to", "help"]}, {"character": "Snow White", "dialog": " After what you did to me?", "dialogSplit": ["After", "what", "you", "did", "to", "me"]}, {"character": "Lancelot", "dialog": " After what the King did to you. I still do have a small shred of honor left.", "dialogSplit": ["After", "what", "the", "King", "did", "to", "you", "I", "still", "do", "have", "a", "small", "shred", "of", "honor", "left"]}, {"character": "Snow White", "dialog": " Do you really think I'm that naive? You're going to earn my trust so I can lead you straight...", "dialogSplit": ["Do", "you", "really", "think", "I'm", "that", "naive", "You're", "going", "to", "earn", "my", "trust", "so", "I", "can", "lead", "you", "straight"]}, {"character": "Lancelot", "dialog": " To the cabin where your prince is hiding his mother?", "dialogSplit": ["To", "the", "cabin", "where", "your", "prince", "is", "hiding", "his", "mother"]}, {"character": "Snow White", "dialog": " How did you know?", "dialogSplit": ["How", "did", "you", "know"]}, {"character": "Lancelot", "dialog": " Because George knows where it is. He sent men there to kill your man's mother.", "dialogSplit": ["Because", "George", "knows", "where", "it", "is", "He", "sent", "men", "there", "to", "kill", "your", "man's", "mother"]}, {"character": "Snow White", "dialog": " Charming's at the cabin, too.", "dialogSplit": ["Charming's", "at", "the", "cabin", "too"]}, {"character": "Prince Charming", "dialog": " Mother, the place looks beautiful. Will you come inside?", "dialogSplit": ["Mother", "the", "place", "looks", "beautiful", "Will", "you", "come", "inside"]}, {"character": "Ruth", "dialog": " I'm sorry if I want things to be perfect when I meet the girl... My son is going to marry.", "dialogSplit": ["I'm", "sorry", "if", "I", "want", "things", "to", "be", "perfect", "when", "I", "meet", "the", "girl", "My", "son", "is", "going", "to", "marry"]}, {"character": "Prince Charming", "dialog": " Wait. Did you hear that? Go in. Bolt the door. Whatever happens, stay inside. Go.  What? That's it? Ah!", "dialogSplit": ["Wait", "Did", "you", "hear", "that", "Go", "in", "Bolt", "the", "door", "Whatever", "happens", "stay", "inside", "Go", "What", "That's", "it", "Ah"]}, {"character": "Ruth", "dialog": " Son?", "dialogSplit": ["Son"]}, {"character": "Prince Charming", "dialog": " Mother! Mother! I told you to stay inside.", "dialogSplit": ["Mother", "Mother", "I", "told", "you", "to", "stay", "inside"]}, {"character": "Ruth", "dialog": " I know, but I heard you. I thought you were hurt. I'm sorry.", "dialogSplit": ["I", "know", "but", "I", "heard", "you", "I", "thought", "you", "were", "hurt", "I'm", "sorry"]}, {"character": "Prince Charming", "dialog": " No. You're gonna be okay. Okay? Everything's gonna be okay.", "dialogSplit": ["No", "You're", "gonna", "be", "okay", "Okay", "Everything's", "gonna", "be", "okay"]}, {"character": "Snow White", "dialog": " I'm so sorry. We came as quickly as we could.", "dialogSplit": ["I'm", "so", "sorry", "We", "came", "as", "quickly", "as", "we", "could"]}, {"character": "Ruth", "dialog": " Is this... Snow?", "dialogSplit": ["Is", "this", "Snow"]}]}, {"sceneDesc": "The Enchanted Forest. Present. At their camp, Mary Margaret is making a fire, when Aurora appears with a knife and tries to kill her. She flips Aurora over and the two start to fight.", "tense": "Present", "location": "The Enchanted Forest", "dialog": [{"character": "Aurora", "dialog": " Don't move. Phillip's gone because of you.", "dialogSplit": ["Don't", "move", "Phillip's", "gone", "because", "of", "you"]}, {"character": "Mary Margaret", "dialog": " You listen to me, princess! You think I don't know what it's like to be separated from the people that I love? What happened to Phillip was not our fault. So I suggest you find another way to channel your anger.", "dialogSplit": ["You", "listen", "to", "me", "princess", "You", "think", "I", "don't", "know", "what", "it's", "like", "to", "be", "separated", "from", "the", "people", "that", "I", "love", "What", "happened", "to", "Phillip", "was", "not", "our", "fault", "So", "I", "suggest", "you", "find", "another", "way", "to", "channel", "your", "anger"]}, {"character": "Mulan", "dialog": " Don't talk to her like that.", "dialogSplit": ["Don't", "talk", "to", "her", "like", "that"]}, {"character": "Mary Margaret", "dialog": " She tried to kill me.", "dialogSplit": ["She", "tried", "to", "kill", "me"]}, {"character": "Mulan", "dialog": " I will deal with her. ", "dialogSplit": ["I", "will", "deal", "with", "her"]}, {"character": "Mary Margaret", "dialog": " Emma, what are you doing?", "dialogSplit": ["Emma", "what", "are", "you", "doing"]}, {"character": "Emma", "dialog": " Protecting you. Drop the weapon!", "dialogSplit": ["Protecting", "you", "Drop", "the", "weapon"]}, {"character": "Mary Margaret", "dialog": " Do you have any idea what you've just done?", "dialogSplit": ["Do", "you", "have", "any", "idea", "what", "you've", "just", "done"]}, {"character": "Emma", "dialog": " Ogres?", "dialogSplit": ["Ogres"]}, {"character": "Mary Margaret", "dialog": " RUUUNNN\u00a0!!!", "dialogSplit": ["RUUUNNN"]}, {"character": "Mulan", "dialog": " Aurora. This way. Come on!", "dialogSplit": ["Aurora", "This", "way", "Come", "on"]}, {"character": "Mary Margaret", "dialog": " Split up!", "dialogSplit": ["Split", "up"]}, {"character": "Mulan", "dialog": " Come on!", "dialogSplit": ["Come", "on"]}, {"character": "Mary Margaret", "dialog": " Over there.", "dialogSplit": ["Over", "there"]}, {"character": "Emma", "dialog": " Seriously?", "dialogSplit": ["Seriously"]}, {"character": "Mary Margaret", "dialog": " Back away from my daughter!  You have to shoot them in the eye.", "dialogSplit": ["Back", "away", "from", "my", "daughter", "You", "have", "to", "shoot", "them", "in", "the", "eye"]}, {"character": "Emma", "dialog": " When was the last time you shot an arrow?", "dialogSplit": ["When", "was", "the", "last", "time", "you", "shot", "an", "arrow"]}, {"character": "Mary Margaret", "dialog": " 28 years ago. Guess it's like riding a bike.", "dialogSplit": ["28", "years", "ago", "Guess", "it's", "like", "riding", "a", "bike"]}, {"character": "Emma", "dialog": " Yeah, but how did you know you could hit that?", "dialogSplit": ["Yeah", "but", "how", "did", "you", "know", "you", "could", "hit", "that"]}, {"character": "Mary Margaret", "dialog": " I didn't.", "dialogSplit": ["I", "didn't"]}, {"character": "Mary Margaret", "dialog": " Next time, listen to me. That kind of thing isn't gonna work here.", "dialogSplit": ["Next", "time", "listen", "to", "me", "That", "kind", "of", "thing", "isn't", "gonna", "work", "here"]}, {"character": "Emma", "dialog": " Yeah.", "dialogSplit": ["Yeah"]}, {"character": "Margaret", "dialog": " We should get going.", "dialogSplit": ["We", "should", "get", "going"]}]}, {"sceneDesc": "The Enchanted Forest. Past. Prince Charming and Lancelot are talking about the arrow.", "tense": "Past", "location": "The Enchanted Forest", "dialog": [{"character": "Lancelot", "dialog": " It's poisoned.", "dialogSplit": ["It's", "poisoned"]}, {"character": "Prince Charming", "dialog": " Can we find an antidote?", "dialogSplit": ["Can", "we", "find", "an", "antidote"]}, {"character": "Snow White", "dialog": " Or the fairies. They can help us.", "dialogSplit": ["Or", "the", "fairies", "They", "can", "help", "us"]}, {"character": "Lancelot", "dialog": " No. I'm afraid this is gonna take something stronger than fairy dust.", "dialogSplit": ["No", "I'm", "afraid", "this", "is", "gonna", "take", "something", "stronger", "than", "fairy", "dust"]}, {"character": "Prince Charming", "dialog": " Lake Nostos... I've been there before. Its waters have powerful magical properties. I've seen them turn a man from solid gold back into flesh. It isn't far. A day's journey at most.", "dialogSplit": ["Lake", "Nostos", "I've", "been", "there", "before", "Its", "waters", "have", "powerful", "magical", "properties", "I've", "seen", "them", "turn", "a", "man", "from", "solid", "gold", "back", "into", "flesh", "It", "isn't", "far", "A", "day's", "journey", "at", "most"]}, {"character": "Lancelot", "dialog": " I'll prepare a wagon.", "dialogSplit": ["I'll", "prepare", "a", "wagon"]}, {"character": "Prince Charming", "dialog": " Must be a curious tale.", "dialogSplit": ["Must", "be", "a", "curious", "tale"]}, {"character": "Lancelot", "dialog": " What?", "dialogSplit": ["What"]}, {"character": "Prince Charming", "dialog": " Well, how a knight of the round table ended up a sword for hire.", "dialogSplit": ["Well", "how", "a", "knight", "of", "the", "round", "table", "ended", "up", "a", "sword", "for", "hire"]}, {"character": "Lancelot", "dialog": " You mean how did I fall from grace? The same way you ended up running from King George. A woman.", "dialogSplit": ["You", "mean", "how", "did", "I", "fall", "from", "grace", "The", "same", "way", "you", "ended", "up", "running", "from", "King", "George", "A", "woman"]}, {"character": "Prince Charming", "dialog": " We're gonna scout ahead. We won't be long.", "dialogSplit": ["We're", "gonna", "scout", "ahead", "We", "won't", "be", "long"]}, {"character": "Ruth", "dialog": " Thank you.", "dialogSplit": ["Thank", "you"]}, {"character": "Snow White", "dialog": " Oh. It's the least I can do. Are you comfortable?", "dialogSplit": ["Oh", "It's", "the", "least", "I", "can", "do", "Are", "you", "comfortable"]}, {"character": "Ruth", "dialog": "No. For giving my son something to believe in. All he's ever dreamt of was having a wife and a son. Fret not. It could be a daughter. But trust me, all that matters is that it's healthy. Let me show you something. My mother gave this to me when I was pregnant. She said it was spelled by a gypsy to predict the sex of your firstborn even before you are with child.", "dialogSplit": ["No", "For", "giving", "my", "son", "something", "to", "believe", "in", "All", "he's", "ever", "dreamt", "of", "was", "having", "a", "wife", "and", "a", "son", "Fret", "not", "It", "could", "be", "a", "daughter", "But", "trust", "me", "all", "that", "matters", "is", "that", "it's", "healthy", "Let", "me", "show", "you", "something", "My", "mother", "gave", "this", "to", "me", "when", "I", "was", "pregnant", "She", "said", "it", "was", "spelled", "by", "a", "gypsy", "to", "predict", "the", "sex", "of", "your", "firstborn", "even", "before", "you", "are", "with", "child"]}, {"character": "Snow White", "dialog": " And it works?", "dialogSplit": ["And", "it", "works"]}, {"character": "Ruth", "dialog": " It did with my boys. If it swings North to South, it's a boy. East to West, it's a girl.", "dialogSplit": ["It", "did", "with", "my", "boys", "If", "it", "swings", "North", "to", "South", "it's", "a", "boy", "East", "to", "West", "it's", "a", "girl"]}, {"character": "Snow White", "dialog": " Mm.", "dialogSplit": ["Mm"]}, {"character": "Ruth", "dialog": " Shall we? Just between us?", "dialogSplit": ["Shall", "we", "Just", "between", "us"]}, {"character": "Snow White", "dialog": " Oh, I don't think that's a good idea.", "dialogSplit": ["Oh", "I", "don't", "think", "that's", "a", "good", "idea"]}, {"character": "Ruth", "dialog": " Indulge an old woman. It'll help take my mind off the... well, you know. Here.", "dialogSplit": ["Indulge", "an", "old", "woman", "It'll", "help", "take", "my", "mind", "off", "the", "well", "you", "know", "Here"]}, {"character": "Ruth", "dialog": " Don't worry. It's just... a silly superstition. What's wrong, child? You can tell me anything, Snow.", "dialogSplit": ["Don't", "worry", "It's", "just", "a", "silly", "superstition", "What's", "wrong", "child", "You", "can", "tell", "me", "anything", "Snow"]}, {"character": "Snow White", "dialog": " It's the King. When he captured me, he cursed me, so... so that I can never have children.", "dialogSplit": ["It's", "the", "King", "When", "he", "captured", "me", "he", "cursed", "me", "so", "so", "that", "I", "can", "never", "have", "children"]}, {"character": "Ruth", "dialog": " Worry not. If the water from Lake Nostos can heal me, it should be able to do the same for you.", "dialogSplit": ["Worry", "not", "If", "the", "water", "from", "Lake", "Nostos", "can", "heal", "me", "it", "should", "be", "able", "to", "do", "the", "same", "for", "you"]}, {"character": "Snow White", "dialog": " Do you really think so?", "dialogSplit": ["Do", "you", "really", "think", "so"]}, {"character": "Ruth", "dialog": " You are going to be a wonderful mother.", "dialogSplit": ["You", "are", "going", "to", "be", "a", "wonderful", "mother"]}]}, {"sceneDesc": "The Enchanted Forest. Present. They approach the castle.", "tense": "Present", "location": "The Enchanted Forest", "dialog": [{"character": "Mary Margaret", "dialog": " We're getting close.", "dialogSplit": ["We're", "getting", "close"]}, {"character": "Mulan", "dialog": "Aurora, you've gotta keep up.", "dialogSplit": ["Aurora", "you've", "gotta", "keep", "up"]}, {"character": "Aurora", "dialog": " Sorry, but I'm not exactly dressed for the woods. It's cold out here.", "dialogSplit": ["Sorry", "but", "I'm", "not", "exactly", "dressed", "for", "the", "woods", "It's", "cold", "out", "here"]}, {"character": "Mulan", "dialog": " Then maybe you should've listened to me and stayed back.", "dialogSplit": ["Then", "maybe", "you", "should've", "listened", "to", "me", "and", "stayed", "back"]}, {"character": "Emma", "dialog": " Here.", "dialogSplit": ["Here"]}, {"character": "Aurora", "dialog": " But I tried to kill your friend.", "dialogSplit": ["But", "I", "tried", "to", "kill", "your", "friend"]}, {"character": "Emma", "dialog": " Actually, she's my mom and I have a feeling she can take care of herself. And I get it. You're not the only one who's been screwing up lately.", "dialogSplit": ["Actually", "she's", "my", "mom", "and", "I", "have", "a", "feeling", "she", "can", "take", "care", "of", "herself", "And", "I", "get", "it", "You're", "not", "the", "only", "one", "who's", "been", "screwing", "up", "lately"]}, {"character": "Aurora", "dialog": " What kind of corset is this?", "dialogSplit": ["What", "kind", "of", "corset", "is", "this"]}, {"character": "Mulan", "dialog": " Up here!", "dialogSplit": ["Up", "here"]}, {"character": "Emma", "dialog": " Is that it?", "dialogSplit": ["Is", "that", "it"]}, {"character": "Mary Margaret", "dialog": " Yeah. That's our home.", "dialogSplit": ["Yeah", "That's", "our", "home"]}]}, {"sceneDesc": "The Enchanted Forest. Past. Lake Nostos. Prince Charming, Ruth, Snow White and Lancelot discover that the lake is bone dry.", "tense": "Past", "location": "The Enchanted Forest", "dialog": [{"character": "Prince Charming", "dialog": " Whoa.", "dialogSplit": ["Whoa"]}, {"character": "Snow White", "dialog": " Where's the lake?", "dialogSplit": ["Where's", "the", "lake"]}, {"character": "Prince Charming", "dialog": " You're looking at it. It's gone.", "dialogSplit": ["You're", "looking", "at", "it", "It's", "gone"]}]}, {"sceneDesc": "Storybrooke. Present. Henry breaks into Regina's vault. There are many shelves that contain hearts, which thump loudly as he passes by them. He stumbles onto a box, but upon opening it, Agrabahn Viper spring out in attack. He is saved when David arrives in time to close the box.", "tense": "Present", "location": "Storybrooke", "dialog": [{"character": "David", "dialog": " Maybe we should've gone with Operation Viper. You all right?", "dialogSplit": ["Maybe", "we", "should've", "gone", "with", "Operation", "Viper", "You", "all", "right"]}, {"character": "Henry", "dialog": " Yeah. How'd you know I was down here?", "dialogSplit": ["Yeah", "How'd", "you", "know", "I", "was", "down", "here"]}, {"character": "David", "dialog": " Your mom said you asked her to lunch, and when you stood her up, she checked her office, saw her keys missing, figured out the rest. She would've come herself, but she didn't think you'd go with her.", "dialogSplit": ["Your", "mom", "said", "you", "asked", "her", "to", "lunch", "and", "when", "you", "stood", "her", "up", "she", "checked", "her", "office", "saw", "her", "keys", "missing", "figured", "out", "the", "rest", "She", "would've", "come", "herself", "but", "she", "didn't", "think", "you'd", "go", "with", "her"]}, {"character": "David", "dialog": " Henry, what were you thinking?", "dialogSplit": ["Henry", "what", "were", "you", "thinking"]}, {"character": "Henry", "dialog": " I just want them back. It wasn't supposed to be this way. I should be over there with them, riding horses, learning how to sword fight.", "dialogSplit": ["I", "just", "want", "them", "back", "It", "wasn't", "supposed", "to", "be", "this", "way", "I", "should", "be", "over", "there", "with", "them", "riding", "horses", "learning", "how", "to", "sword", "fight"]}, {"character": "David", "dialog": " I know. I know. It's okay, because we are gonna do this together. Come on now. You gotta get to school... and I gotta make sure no one else finds this place.", "dialogSplit": ["I", "know", "I", "know", "It's", "okay", "because", "we", "are", "gonna", "do", "this", "together", "Come", "on", "now", "You", "gotta", "get", "to", "school", "and", "I", "gotta", "make", "sure", "no", "one", "else", "finds", "this", "place"]}]}, {"sceneDesc": "The Enchanted Forest. Past. At the lake, Lancelot searches the lake bed trying to find any water that remained, but can only find a tiny bit in a seashell, only enough for a sip.", "tense": "Past", "location": "The Enchanted Forest", "dialog": [{"character": "Prince Charming", "dialog": " This is my fault. The siren who lived here... I killed her. That's why the lake is dry.", "dialogSplit": ["This", "is", "my", "fault", "The", "siren", "who", "lived", "here", "I", "killed", "her", "That's", "why", "the", "lake", "is", "dry"]}, {"character": "Lancelot", "dialog": " You needn't worry. My mother raised me by a lake. There may yet be water. You just... need to know where to look. God in his mercy, lend her grace.", "dialogSplit": ["You", "needn't", "worry", "My", "mother", "raised", "me", "by", "a", "lake", "There", "may", "yet", "be", "water", "You", "just", "need", "to", "know", "where", "to", "look", "God", "in", "his", "mercy", "lend", "her", "grace"]}, {"character": "Prince Charming", "dialog": " You found it?", "dialogSplit": ["You", "found", "it"]}, {"character": "Lancelot", "dialog": " It's all that's left. Just enough for one sip.", "dialogSplit": ["It's", "all", "that's", "left", "Just", "enough", "for", "one", "sip"]}, {"character": "Prince Charming", "dialog": " Enough to heal my mother.", "dialogSplit": ["Enough", "to", "heal", "my", "mother"]}, {"character": "Lancelot", "dialog": " We shall find out.", "dialogSplit": ["We", "shall", "find", "out"]}, {"character": "Ruth", "dialog": " I want you to have it. That last sip of water... I want you to drink it.", "dialogSplit": ["I", "want", "you", "to", "have", "it", "That", "last", "sip", "of", "water", "I", "want", "you", "to", "drink", "it"]}, {"character": "Snow White", "dialog": " No. No, I couldn't.", "dialogSplit": ["No", "No", "I", "couldn't"]}, {"character": "Ruth", "dialog": " That water can lift your curse, allow you and my son to have a child.", "dialogSplit": ["That", "water", "can", "lift", "your", "curse", "allow", "you", "and", "my", "son", "to", "have", "a", "child"]}, {"character": "Snow White", "dialog": " But you'll die. I won't let you give your life for this.", "dialogSplit": ["But", "you'll", "die", "I", "won't", "let", "you", "give", "your", "life", "for", "this"]}, {"character": "Ruth", "dialog": " That's what parents do. They put their children first. Someday you will understand", "dialogSplit": ["That's", "what", "parents", "do", "They", "put", "their", "children", "first", "Someday", "you", "will", "understand"]}, {"character": "Snow White", "dialog": " No. Maybe it's for the best. I was raised without a mother. I wouldn't even know how to be one. This water was meant for you.", "dialogSplit": ["No", "Maybe", "it's", "for", "the", "best", "I", "was", "raised", "without", "a", "mother", "I", "wouldn't", "even", "know", "how", "to", "be", "one", "This", "water", "was", "meant", "for", "you"]}, {"character": "Prince Charming", "dialog": " Mother. Mother. Our prayers are answered. There is magic in this lake yet. Here. Drink.", "dialogSplit": ["Mother", "Mother", "Our", "prayers", "are", "answered", "There", "is", "magic", "in", "this", "lake", "yet", "Here", "Drink"]}, {"character": "Ruth", "dialog": " Have faith, Snow. We'll find another way.", "dialogSplit": ["Have", "faith", "Snow", "We'll", "find", "another", "way"]}]}, {"sceneDesc": "The Enchanted Forest. Present. Royal Castle. Emma and Mary Margaret enter Emma's nursery.", "tense": "Present", "location": "The Enchanted Forest", "dialog": [{"character": "Emma", "dialog": " Oh, my God. I recognize this from Henry's book.", "dialogSplit": ["Oh", "my", "God", "I", "recognize", "this", "from", "Henry's", "book"]}, {"character": "Mulan", "dialog": " Come. We'll stand watch at the gate.", "dialogSplit": ["Come", "We'll", "stand", "watch", "at", "the", "gate"]}, {"character": "Mary Margaret", "dialog": " I never thought I'd see this place again. This room. It was your nursery.", "dialogSplit": ["I", "never", "thought", "I'd", "see", "this", "place", "again", "This", "room", "It", "was", "your", "nursery"]}, {"character": "Emma", "dialog": " I lived here?", "dialogSplit": ["I", "lived", "here"]}, {"character": "Mary Margaret", "dialog": " You never even got to spend a night.  This is the life I wanted you to have. I was going to teach you how to walk in here, how to talk, how to dress for your first ball. You never got to do any of it. We never got to be a family.", "dialogSplit": ["You", "never", "even", "got", "to", "spend", "a", "night", "This", "is", "the", "life", "I", "wanted", "you", "to", "have", "I", "was", "going", "to", "teach", "you", "how", "to", "walk", "in", "here", "how", "to", "talk", "how", "to", "dress", "for", "your", "first", "ball", "You", "never", "got", "to", "do", "any", "of", "it", "We", "never", "got", "to", "be", "a", "family"]}, {"character": "Emma", "dialog": " We have a family... in Storybrooke and right now they need us to get back there. So... how do we get this to work?", "dialogSplit": ["We", "have", "a", "family", "in", "Storybrooke", "and", "right", "now", "they", "need", "us", "to", "get", "back", "there", "So", "how", "do", "we", "get", "this", "to", "work"]}]}, {"sceneDesc": "The Enchanted Forest. Past. Lake Nostos. Prince Charming is frustrated that Ruth is still dying.", "tense": "Past", "location": "The Enchanted Forest", "dialog": [{"character": "Prince Charming", "dialog": " Why isn't it working?", "dialogSplit": ["Why", "isn't", "it", "working"]}, {"character": "Lancelot", "dialog": " Wounds take time to heal.", "dialogSplit": ["Wounds", "take", "time", "to", "heal"]}, {"character": "Prince Charming", "dialog": " No. No. I used this magic before. It worked instantly. There wasn't enough water. We need more.", "dialogSplit": ["No", "No", "I", "used", "this", "magic", "before", "It", "worked", "instantly", "There", "wasn't", "enough", "water", "We", "need", "more"]}, {"character": "Ruth", "dialog": "Son... stop. There's no m-more magic here, and I don't want to spend my last moments this way.", "dialogSplit": ["Son", "stop", "There's", "no", "m", "more", "magic", "here", "and", "I", "don't", "want", "to", "spend", "my", "last", "moments", "this", "way"]}, {"character": "Prince Charming", "dialog": " This is all my fault. I am so sorry.", "dialogSplit": ["This", "is", "all", "my", "fault", "I", "am", "so", "sorry"]}, {"character": "Ruth", "dialog": " F... for what? For being happy? For finding your true love? For your happiness, I would gladly give my life. My only regret is that I won't live to see you marry Snow.", "dialogSplit": ["F", "for", "what", "For", "being", "happy", "For", "finding", "your", "true", "love", "For", "your", "happiness", "I", "would", "gladly", "give", "my", "life", "My", "only", "regret", "is", "that", "I", "won't", "live", "to", "see", "you", "marry", "Snow"]}, {"character": "Prince Charming", "dialog": " Shh.", "dialogSplit": ["Shh"]}, {"character": "Snow White", "dialog": " Yes, you will. Lancelot, does a disgraced member of the round table still have the power to perform a wedding?", "dialogSplit": ["Yes", "you", "will", "Lancelot", "does", "a", "disgraced", "member", "of", "the", "round", "table", "still", "have", "the", "power", "to", "perform", "a", "wedding"]}, {"character": "Lancelot", "dialog": " It would be my honor. In my kingdom, there is legend of a cup that has the power to grant eternal life. And so may the love between you always be strong, true, and eternal..)", "dialogSplit": ["It", "would", "be", "my", "honor", "In", "my", "kingdom", "there", "is", "legend", "of", "a", "cup", "that", "has", "the", "power", "to", "grant", "eternal", "life", "And", "so", "may", "the", "love", "between", "you", "always", "be", "strong", "true", "and", "eternal"]}, {"character": "Prince Charming", "dialog": " Good-bye, mother.", "dialogSplit": ["Good", "bye", "mother"]}]}, {"sceneDesc": "The Enchanted Forest. Present. Royal Castle.", "tense": "Present", "location": "The Enchanted Forest", "dialog": [{"character": "Emma", "dialog": " Where's the \"on\" switch?", "dialogSplit": ["Where's", "the", "on", "switch"]}, {"character": "Mary Margaret", "dialog": " It's more complicated than that. We'll have to get it back to the island. Hopefully, someone there has access to enough magic to make it work again.", "dialogSplit": ["It's", "more", "complicated", "than", "that", "We'll", "have", "to", "get", "it", "back", "to", "the", "island", "Hopefully", "someone", "there", "has", "access", "to", "enough", "magic", "to", "make", "it", "work", "again"]}, {"character": "Emma", "dialog": " How are we gonna carry this thing?", "dialogSplit": ["How", "are", "we", "gonna", "carry", "this", "thing"]}, {"character": "Lancelot", "dialog": " With the help of an old friend.", "dialogSplit": ["With", "the", "help", "of", "an", "old", "friend"]}, {"character": "Mary Margaret", "dialog": " Lancelot. What are you doing here?", "dialogSplit": ["Lancelot", "What", "are", "you", "doing", "here"]}, {"character": "Lancelot", "dialog": " We heard about the ogre attack, and I had to make sure you were alright", "dialogSplit": ["We", "heard", "about", "the", "ogre", "attack", "and", "I", "had", "to", "make", "sure", "you", "were", "alright"]}, {"character": "Mary Margaret", "dialog": " Oh. Where are Mulan and Aurora?", "dialogSplit": ["Oh", "Where", "are", "Mulan", "and", "Aurora"]}, {"character": "Lancelot", "dialog": " I sent them to find food. Tonight we'll make camp, and in the morning, we'll head back. So... this is it... the portal you were after.", "dialogSplit": ["I", "sent", "them", "to", "find", "food", "Tonight", "we'll", "make", "camp", "and", "in", "the", "morning", "we'll", "head", "back", "So", "this", "is", "it", "the", "portal", "you", "were", "after"]}, {"character": "Mary Margaret", "dialog": " The same one Emma went through. It's how she escaped the curse.", "dialogSplit": ["The", "same", "one", "Emma", "went", "through", "It's", "how", "she", "escaped", "the", "curse"]}, {"character": "Lancelot", "dialog": " Remarkable.", "dialogSplit": ["Remarkable"]}, {"character": "Mary Margaret", "dialog": " Geppetto carved it from an enchanted tree, but... there's no magic left.", "dialogSplit": ["Geppetto", "carved", "it", "from", "an", "enchanted", "tree", "but", "there's", "no", "magic", "left"]}, {"character": "Lancelot", "dialog": " A portal this powerful... there must be another way to recharge it.", "dialogSplit": ["A", "portal", "this", "powerful", "there", "must", "be", "another", "way", "to", "recharge", "it"]}, {"character": "Mary Margaret", "dialog": " Why are you so interested in the wardrobe?", "dialogSplit": ["Why", "are", "you", "so", "interested", "in", "the", "wardrobe"]}, {"character": "Lancelot", "dialog": " Well, I just want you to get home to your husband and son. Henry. They must miss you. ", "dialogSplit": ["Well", "I", "just", "want", "you", "to", "get", "home", "to", "your", "husband", "and", "son", "Henry", "They", "must", "miss", "you"]}, {"character": "Mary Margaret", "dialog": " Stay away from him, Emma. He is not who he says he is.", "dialogSplit": ["Stay", "away", "from", "him", "Emma", "He", "is", "not", "who", "he", "says", "he", "is"]}, {"character": "Emma", "dialog": " What are you talking about? Who the hell is he?", "dialogSplit": ["What", "are", "you", "talking", "about", "Who", "the", "hell", "is", "he"]}, {"character": "Mary Margaret", "dialog": " There is only one person you told Henry's name.", "dialogSplit": ["There", "is", "only", "one", "person", "you", "told", "Henry's", "name"]}, {"character": "Emma", "dialog": " Cora.", "dialogSplit": ["Cora"]}, {"character": "Cora", "dialog": " Clever girl.", "dialogSplit": ["Clever", "girl"]}, {"character": "Mary Margaret", "dialog": " Where's Lancelot?", "dialogSplit": ["Where's", "Lancelot"]}, {"character": "Cora", "dialog": " He's dead. I killed him a long time ago.", "dialogSplit": ["He's", "dead", "I", "killed", "him", "a", "long", "time", "ago"]}, {"character": "Mary Margaret", "dialog": " And you've been posing as him ever since.", "dialogSplit": ["And", "you've", "been", "posing", "as", "him", "ever", "since"]}, {"character": "Cora", "dialog": " Well, they'd never listen to me. And besides, every kingdom needs a hero, don't you think?", "dialogSplit": ["Well", "they'd", "never", "listen", "to", "me", "And", "besides", "every", "kingdom", "needs", "a", "hero", "don't", "you", "think"]}, {"character": "Mary Margaret", "dialog": " Aah! Oh!", "dialogSplit": ["Aah", "Oh"]}, {"character": "Cora", "dialog": " Thank you, Snow. I've been looking for a way over for so long. I never thought the person to help me find it... would be you.", "dialogSplit": ["Thank", "you", "Snow", "I've", "been", "looking", "for", "a", "way", "over", "for", "so", "long", "I", "never", "thought", "the", "person", "to", "help", "me", "find", "it", "would", "be", "you"]}, {"character": "Mary Margaret", "dialog": " Why? Why are you doing this?", "dialogSplit": ["Why", "Why", "are", "you", "doing", "this"]}, {"character": "Cora", "dialog": " I want to see my daughter. It's been too long. And you know, I would love to meet my grandson Henry.", "dialogSplit": ["I", "want", "to", "see", "my", "daughter", "It's", "been", "too", "long", "And", "you", "know", "I", "would", "love", "to", "meet", "my", "grandson", "Henry"]}, {"character": "Emma", "dialog": " No, you won't! ", "dialogSplit": ["No", "you", "won't"]}, {"character": "Cora", "dialog": " NO!", "dialogSplit": ["NO"]}, {"character": "Aurora", "dialog": " Mulan!", "dialogSplit": ["Mulan"]}, {"character": "Cora", "dialog": " We're not done.", "dialogSplit": ["We're", "not", "done"]}, {"character": "Mary Margaret", "dialog": " Oh!", "dialogSplit": ["Oh"]}, {"character": "Emma", "dialog": " You okay?", "dialogSplit": ["You", "okay"]}, {"character": "Mary Margaret", "dialog": " You saved me.", "dialogSplit": ["You", "saved", "me"]}, {"character": "Emma", "dialog": " Yeah, well... where is she?", "dialogSplit": ["Yeah", "well", "where", "is", "she"]}, {"character": "Mary Margaret", "dialog": " Gone.", "dialogSplit": ["Gone"]}, {"character": "Emma", "dialog": " So's our ride home.", "dialogSplit": ["So's", "our", "ride", "home"]}]}, {"sceneDesc": "The Enchanted Forest. Past. Prince Charming is seen burning a candle in his mother's memory. ", "tense": "Past", "location": "The Enchanted Forest", "dialog": [{"character": "Snow White", "dialog": " I'm so sorry. She was all the family you had left.", "dialogSplit": ["I'm", "so", "sorry", "She", "was", "all", "the", "family", "you", "had", "left"]}, {"character": "Prince Charming", "dialog": " No. I still have you. I love you, Snow. And together, we can start a new family. Here.  This belonged to her. She would've wanted you to have it. She said that it could tell you what your child would be. ", "dialogSplit": ["No", "I", "still", "have", "you", "I", "love", "you", "Snow", "And", "together", "we", "can", "start", "a", "new", "family", "Here", "This", "belonged", "to", "her", "She", "would've", "wanted", "you", "to", "have", "it", "She", "said", "that", "it", "could", "tell", "you", "what", "your", "child", "would", "be"]}, {"character": "Snow White", "dialog": " Please don't.", "dialogSplit": ["Please", "don't"]}, {"character": "Prince Charming", "dialog": " It's just a superstition.", "dialogSplit": ["It's", "just", "a", "superstition"]}, {"character": "Snow White", "dialog": " There's something I need to tell you.", "dialogSplit": ["There's", "something", "I", "need", "to", "tell", "you"]}, {"character": "Prince Charming", "dialog": " What is it? What's wrong?", "dialogSplit": ["What", "is", "it", "What's", "wrong"]}, {"character": "Snow White", "dialog": " Wh...  we're going to have a child.", "dialogSplit": ["Wh", "we're", "going", "to", "have", "a", "child"]}, {"character": "Prince Charming", "dialog": "What?", "dialogSplit": ["What"]}, {"character": "Snow White", "dialog": " We're going to have a child.", "dialogSplit": ["We're", "going", "to", "have", "a", "child"]}, {"character": "Prince Charming", "dialog": " Is there something I need to know?", "dialogSplit": ["Is", "there", "something", "I", "need", "to", "know"]}, {"character": "Snow White", "dialog": " I mean someday.", "dialogSplit": ["I", "mean", "someday"]}, {"character": "Prince Charming", "dialog": " Well, of course we are. What's it say it's gonna be? It's gonna be a boy, right? I can never remember which direction means what.", "dialogSplit": ["Well", "of", "course", "we", "are", "What's", "it", "say", "it's", "gonna", "be", "It's", "gonna", "be", "a", "boy", "right", "I", "can", "never", "remember", "which", "direction", "means", "what"]}, {"character": "Snow White", "dialog": " It's a surprise.", "dialogSplit": ["It's", "a", "surprise"]}, {"character": "Prince Charming", "dialog": " I'll send the signal for the army to regroup. We are gonna take back the kingdom, Snow, and we are going to do it as a family.", "dialogSplit": ["I'll", "send", "the", "signal", "for", "the", "army", "to", "regroup", "We", "are", "gonna", "take", "back", "the", "kingdom", "Snow", "and", "we", "are", "going", "to", "do", "it", "as", "a", "family"]}, {"character": "Snow White", "dialog": " This is because of you, isn't it? Ruth only pretended to drink the water. She had you put it in the wedding chalice so I would drink it. That's how King George's curse was broken, wasn't it?", "dialogSplit": ["This", "is", "because", "of", "you", "isn't", "it", "Ruth", "only", "pretended", "to", "drink", "the", "water", "She", "had", "you", "put", "it", "in", "the", "wedding", "chalice", "so", "I", "would", "drink", "it", "That's", "how", "King", "George's", "curse", "was", "broken", "wasn't", "it"]}, {"character": "Lancelot", "dialog": " I have no idea what you're talking about. So... what's your child gonna be?", "dialogSplit": ["I", "have", "no", "idea", "what", "you're", "talking", "about", "So", "what's", "your", "child", "gonna", "be"]}, {"character": "Snow White", "dialog": " A girl.", "dialogSplit": ["A", "girl"]}]}, {"sceneDesc": "The Enchanted Forest. Present. Royal Castle.", "tense": "Present", "location": "The Enchanted Forest", "dialog": [{"character": "Mary Margaret", "dialog": " Lancelot was one of the most noble knights I ever knew.", "dialogSplit": ["Lancelot", "was", "one", "of", "the", "most", "noble", "knights", "I", "ever", "knew"]}, {"character": "Mulan", "dialog": " How could I be so blind? How could I not see that it was Cora?", "dialogSplit": ["How", "could", "I", "be", "so", "blind", "How", "could", "I", "not", "see", "that", "it", "was", "Cora"]}, {"character": "Emma", "dialog": " Well, to be fair, the whole shape-shifting thing threw me, too.", "dialogSplit": ["Well", "to", "be", "fair", "the", "whole", "shape", "shifting", "thing", "threw", "me", "too"]}, {"character": "Mulan", "dialog": " What are we going to tell the people on the island?", "dialogSplit": ["What", "are", "we", "going", "to", "tell", "the", "people", "on", "the", "island"]}, {"character": "Mary Margaret", "dialog": " The truth... that Lancelot was cut down by a terrible villain. He died an honorable death.", "dialogSplit": ["The", "truth", "that", "Lancelot", "was", "cut", "down", "by", "a", "terrible", "villain", "He", "died", "an", "honorable", "death"]}, {"character": "Mulan", "dialog": " Cora's still out there. We need to find her. We need to defend what's left of the kingdom.", "dialogSplit": ["Cora's", "still", "out", "there", "We", "need", "to", "find", "her", "We", "need", "to", "defend", "what's", "left", "of", "the", "kingdom"]}, {"character": "Aurora", "dialog": " Who's going to lead us? You?", "dialogSplit": ["Who's", "going", "to", "lead", "us", "You"]}, {"character": "Mulan", "dialog": " No. Her.", "dialogSplit": ["No", "Her"]}, {"character": "Mary Margaret", "dialog": " I'm honored, but Emma and I still have to find a way back to Storybrooke.", "dialogSplit": ["I'm", "honored", "but", "Emma", "and", "I", "still", "have", "to", "find", "a", "way", "back", "to", "Storybrooke"]}, {"character": "Mulan", "dialog": " We'll help you. We'll find a way, won't we?", "dialogSplit": ["We'll", "help", "you", "We'll", "find", "a", "way", "won't", "we"]}, {"character": "Aurora", "dialog": " Yes. Perhaps it'll help me channel my anger.", "dialogSplit": ["Yes", "Perhaps", "it'll", "help", "me", "channel", "my", "anger"]}, {"character": "Mulan", "dialog": " Come.", "dialogSplit": ["Come"]}, {"character": "Emma", "dialog": " I'm, uh... sorry I torched our ride home. I couldn't let her get to Henry. I just...", "dialogSplit": ["I'm", "uh", "sorry", "I", "torched", "our", "ride", "home", "I", "couldn't", "let", "her", "get", "to", "Henry", "I", "just"]}, {"character": "Mary Margaret", "dialog": " You had to put Henry first.", "dialogSplit": ["You", "had", "to", "put", "Henry", "first"]}, {"character": "Emma", "dialog": " I was angry for so long... wondering how you could choose to let me grow up without you. But then just seeing all this... You gave up everything for me and you're still doing that. Sorry. I'm not good at this. I... I guess I just... I'm not... I'm not used to someone putting me first.", "dialogSplit": ["I", "was", "angry", "for", "so", "long", "wondering", "how", "you", "could", "choose", "to", "let", "me", "grow", "up", "without", "you", "But", "then", "just", "seeing", "all", "this", "You", "gave", "up", "everything", "for", "me", "and", "you're", "still", "doing", "that", "Sorry", "I'm", "not", "good", "at", "this", "I", "I", "guess", "I", "just", "I'm", "not", "I'm", "not", "used", "to", "someone", "putting", "me", "first"]}, {"character": "Mary Margaret", "dialog": " Oh.  Well, get used to it. ", "dialogSplit": ["Oh", "Well", "get", "used", "to", "it"]}]}, {"sceneDesc": "Storybrooke. Present. Jefferson waits for Paige at the school bus stop. He calls to her, and they are both overjoyed to be reunited. They share a massive embrace.", "tense": "Present", "location": "Storybrooke", "dialog": [{"character": "Jefferson", "dialog": " Grace.", "dialogSplit": ["Grace"]}, {"character": "Grace", "dialog": " Papa! You found me. I knew you would.", "dialogSplit": ["Papa", "You", "found", "me", "I", "knew", "you", "would"]}, {"character": "David", "dialog": " I've been thinking, if you're gonna start helping me, we gotta make sure we do this right. So I picked these up on my way home.", "dialogSplit": ["I've", "been", "thinking", "if", "you're", "gonna", "start", "helping", "me", "we", "gotta", "make", "sure", "we", "do", "this", "right", "So", "I", "picked", "these", "up", "on", "my", "way", "home"]}, {"character": "Henry", "dialog": "Seriously?", "dialogSplit": ["Seriously"]}, {"character": "David", "dialog": " Yeah, you're the grandson of a prince. I think it's about time you learned how to use a sword. Henry, I can't get 'em back without you. So? What do you say? You with me?", "dialogSplit": ["Yeah", "you're", "the", "grandson", "of", "a", "prince", "I", "think", "it's", "about", "time", "you", "learned", "how", "to", "use", "a", "sword", "Henry", "I", "can't", "get", "em", "back", "without", "you", "So", "What", "do", "you", "say", "You", "with", "me"]}, {"character": "Henry", "dialog": " Can you teach me how to fight a dragon? We'll work our way up to it.", "dialogSplit": ["Can", "you", "teach", "me", "how", "to", "fight", "a", "dragon", "We'll", "work", "our", "way", "up", "to", "it"]}, {"character": "David", "dialog": " My liege. En garde. Hey. Come over here. Up top. Ah, you wanna fight on the same level.", "dialogSplit": ["My", "liege", "En", "garde", "Hey", "Come", "over", "here", "Up", "top", "Ah", "you", "wanna", "fight", "on", "the", "same", "level"]}, {"character": "Henry", "dialog": " Yep!", "dialogSplit": ["Yep"]}]}]}